                0 MAKE_CELL                0 (self)
                2 MAKE_CELL               89 (_collect_character_name_map)
                4 MAKE_CELL               90 (_crop_to_ratio)
                6 MAKE_CELL               91 (_image_to_base64)
                8 MAKE_CELL               92 (_is_vietnamese_text)
               10 MAKE_CELL               93 (encode_one)
               12 MAKE_CELL               94 (ex)
               14 MAKE_CELL               95 (ratio_h)
               16 MAKE_CELL               96 (ratio_w)
               18 MAKE_CELL               97 (style_prefix)

2203           20 RESUME                   0

2205           22 NOP

2207           24 LOAD_DEREF               0 (self)
               26 LOAD_ATTR                0 (prompts_edit)
               36 LOAD_METHOD              1 (toPlainText)
               58 PRECALL                  0
               62 CALL                     0
               72 LOAD_METHOD              2 (strip)
               94 PRECALL                  0
               98 CALL                     0
              108 STORE_FAST               1 (prompts_text)

2208          110 LOAD_FAST                1 (prompts_text)
              112 POP_JUMP_FORWARD_IF_TRUE    24 (to 162)

2209          114 LOAD_GLOBAL              7 (NULL + QMessageBox)
              126 LOAD_ATTR                4 (warning)
              136 LOAD_DEREF               0 (self)
              138 LOAD_CONST               1 ('Lỗi')
              140 LOAD_CONST               2 ('Vui lòng nhập ít nhất một prompt!')
              142 PRECALL                  3
              146 CALL                     3
              156 POP_TOP

2210          158 LOAD_CONST               3 (None)
              160 RETURN_VALUE

2213     >>   162 LOAD_CONST               4 (<code object <listcomp> at 0x100b9d350, file "main_window_imagen.pyc", line 2213>)
              164 MAKE_FUNCTION            0
              166 LOAD_FAST                1 (prompts_text)
              168 LOAD_METHOD              5 (split)
              190 LOAD_CONST               5 ('\n')
              192 PRECALL                  1
              196 CALL                     1
              206 GET_ITER
              208 PRECALL                  0
              212 CALL                     0
              222 STORE_FAST               2 (prompts)

2214          224 LOAD_FAST                2 (prompts)
              226 POP_JUMP_FORWARD_IF_TRUE    24 (to 276)

2215          228 LOAD_GLOBAL              7 (NULL + QMessageBox)
              240 LOAD_ATTR                4 (warning)
              250 LOAD_DEREF               0 (self)
              252 LOAD_CONST               1 ('Lỗi')
              254 LOAD_CONST               6 ('Không có prompt hợp lệ!')
              256 PRECALL                  3
              260 CALL                     3
              270 POP_TOP

2216          272 LOAD_CONST               3 (None)
              274 RETURN_VALUE

2219     >>   276 LOAD_DEREF               0 (self)
              278 LOAD_METHOD              6 (check_generation_conditions)
              300 LOAD_GLOBAL             15 (NULL + len)
              312 LOAD_FAST                2 (prompts)
              314 PRECALL                  1
              318 CALL                     1
              328 PRECALL                  1
              332 CALL                     1
              342 POP_JUMP_FORWARD_IF_TRUE     2 (to 348)

2220          344 LOAD_CONST               3 (None)
              346 RETURN_VALUE

2223     >>   348 LOAD_DEREF               0 (self)
              350 LOAD_ATTR                8 (settings)
              360 LOAD_METHOD              9 (value)
              382 LOAD_CONST               7 ('license/key')
              384 LOAD_CONST               3 (None)
              386 PRECALL                  2
              390 CALL                     2
              400 STORE_FAST               3 (license_key)

2224          402 LOAD_FAST                3 (license_key)
              404 POP_JUMP_FORWARD_IF_TRUE    24 (to 454)

2225          406 LOAD_GLOBAL              7 (NULL + QMessageBox)
              418 LOAD_ATTR                4 (warning)
              428 LOAD_DEREF               0 (self)
              430 LOAD_CONST               1 ('Lỗi')
              432 LOAD_CONST               8 ('Không có license key! Vui lòng kích hoạt lại.')
              434 PRECALL                  3
              438 CALL                     3
              448 POP_TOP

2226          450 LOAD_CONST               3 (None)
              452 RETURN_VALUE

2229     >>   454 LOAD_DEREF               0 (self)
              456 LOAD_ATTR               10 (aspect_combo)
              466 LOAD_METHOD             11 (currentText)
              488 PRECALL                  0
              492 CALL                     0
              502 STORE_FAST               4 (aspect_text)

2230          504 LOAD_DEREF               0 (self)
              506 LOAD_ATTR               12 (aspect_mapping)
              516 LOAD_METHOD             13 (get)
              538 LOAD_FAST                4 (aspect_text)
              540 LOAD_CONST               9 ('IMAGE_ASPECT_RATIO_LANDSCAPE')
              542 PRECALL                  2
              546 CALL                     2
              556 STORE_FAST               5 (aspect_ratio)

2231          558 LOAD_DEREF               0 (self)
              560 LOAD_ATTR               14 (output_label)
              570 LOAD_METHOD             15 (toolTip)
              592 PRECALL                  0
              596 CALL                     0
              606 STORE_FAST               6 (output_dir)

2234          608 LOAD_DEREF               0 (self)
              610 LOAD_ATTR               16 (style_combo)
              620 LOAD_METHOD             11 (currentText)
              642 PRECALL                  0
              646 CALL                     0
              656 STORE_FAST               7 (style_text)

2235          658 LOAD_DEREF               0 (self)
              660 LOAD_ATTR               17 (style_mapping)
              670 LOAD_METHOD             13 (get)
              692 LOAD_FAST                7 (style_text)
              694 LOAD_CONST              10 ('')
              696 PRECALL                  2
              700 CALL                     2
              710 STORE_DEREF             97 (style_prefix)

2238          712 LOAD_DEREF              97 (style_prefix)
              714 LOAD_CONST              10 ('')
              716 COMPARE_OP               2 (==)
              722 POP_JUMP_FORWARD_IF_FALSE    27 (to 778)
              724 LOAD_DEREF               0 (self)
              726 LOAD_ATTR               18 (super_resolution_checkbox)
              736 LOAD_METHOD             19 (isChecked)
              758 PRECALL                  0
              762 CALL                     0
              772 POP_JUMP_FORWARD_IF_FALSE     2 (to 778)

2239          774 LOAD_CONST              11 ('an image of')
              776 STORE_DEREF             97 (style_prefix)

2241     >>   778 LOAD_FAST                2 (prompts)
              780 LOAD_METHOD             20 (copy)
              802 PRECALL                  0
              806 CALL                     0
              816 STORE_FAST               8 (final_prompts)

2242          818 LOAD_DEREF              97 (style_prefix)
              820 POP_JUMP_FORWARD_IF_FALSE    54 (to 930)

2243          822 LOAD_CLOSURE            97 (style_prefix)
              824 BUILD_TUPLE              1
              826 LOAD_CONST              12 (<code object <listcomp> at 0x100bbe6b0, file "main_window_imagen.pyc", line 2243>)
              828 MAKE_FUNCTION            8 (closure)
              830 LOAD_FAST                2 (prompts)
              832 GET_ITER
              834 PRECALL                  0
              838 CALL                     0
              848 STORE_FAST               8 (final_prompts)

2244          850 LOAD_GLOBAL             43 (NULL + logging)
              862 LOAD_ATTR               22 (info)
              872 LOAD_CONST              13 ("Applied style '")
              874 LOAD_FAST                7 (style_text)
              876 FORMAT_VALUE             0
              878 LOAD_CONST              14 ("' to ")
              880 LOAD_GLOBAL             15 (NULL + len)
              892 LOAD_FAST                2 (prompts)
              894 PRECALL                  1
              898 CALL                     1
              908 FORMAT_VALUE             0
              910 LOAD_CONST              15 (' prompts')
              912 BUILD_STRING             5
              914 PRECALL                  1
              918 CALL                     1
              928 POP_TOP

2246     >>   930 LOAD_FAST                8 (final_prompts)
              932 LOAD_METHOD             20 (copy)
              954 PRECALL                  0
              958 CALL                     0
              968 STORE_FAST               9 (final_prompts_before_replace)

2249          970 LOAD_FAST                6 (output_dir)
              972 POP_JUMP_FORWARD_IF_FALSE    33 (to 1040)
              974 LOAD_GLOBAL             47 (NULL + Path)
              986 LOAD_FAST                6 (output_dir)
              988 PRECALL                  1
              992 CALL                     1
             1002 LOAD_METHOD             24 (exists)
             1024 PRECALL                  0
             1028 CALL                     0
             1038 POP_JUMP_FORWARD_IF_TRUE    24 (to 1088)

2250     >>  1040 LOAD_GLOBAL              7 (NULL + QMessageBox)
             1052 LOAD_ATTR                4 (warning)
             1062 LOAD_DEREF               0 (self)
             1064 LOAD_CONST               1 ('Lỗi')
             1066 LOAD_CONST              16 ('Thư mục đầu ra không tồn tại!')
             1068 PRECALL                  3
             1072 CALL                     3
             1082 POP_TOP

2251         1084 LOAD_CONST               3 (None)
             1086 RETURN_VALUE

2253     >>  1088 LOAD_FAST                6 (output_dir)
             1090 LOAD_DEREF               0 (self)
             1092 STORE_ATTR              25 (current_output_dir)

2256         1102 LOAD_DEREF               0 (self)
             1104 LOAD_ATTR               26 (keep_seed_checkbox)
             1114 LOAD_METHOD             19 (isChecked)
             1136 PRECALL                  0
             1140 CALL                     0
             1150 POP_JUMP_FORWARD_IF_FALSE   192 (to 1536)

2257         1152 LOAD_DEREF               0 (self)
             1154 LOAD_METHOD             27 (is_current_session_regeneration)
             1176 PRECALL                  0
             1180 CALL                     0
             1190 POP_JUMP_FORWARD_IF_FALSE    60 (to 1312)

2259         1192 LOAD_CONST              17 (0)
             1194 LOAD_CONST               3 (None)
             1196 IMPORT_NAME             28 (random)
             1198 STORE_FAST              10 (random)

2260         1200 LOAD_FAST               10 (random)
             1202 LOAD_METHOD             29 (randint)
             1224 LOAD_CONST              18 (1)
             1226 LOAD_CONST              19 (100000)
             1228 PRECALL                  2
             1232 CALL                     2
             1242 LOAD_DEREF               0 (self)
             1244 STORE_ATTR              30 (current_seed)

2261         1254 LOAD_GLOBAL             43 (NULL + logging)
             1266 LOAD_ATTR               22 (info)
             1276 LOAD_CONST              20 ('[REGEN] Tạo seed mới cho regeneration: ')
             1278 LOAD_DEREF               0 (self)
             1280 LOAD_ATTR               30 (current_seed)
             1290 FORMAT_VALUE             0
             1292 BUILD_STRING             2
             1294 PRECALL                  1
             1298 CALL                     1
             1308 POP_TOP
             1310 JUMP_FORWARD           104 (to 1520)

2262     >>  1312 LOAD_GLOBAL             63 (NULL + hasattr)
             1324 LOAD_DEREF               0 (self)
             1326 LOAD_CONST              21 ('current_seed')
             1328 PRECALL                  2
             1332 CALL                     2
             1342 POP_JUMP_FORWARD_IF_TRUE    60 (to 1464)

2264         1344 LOAD_CONST              17 (0)
             1346 LOAD_CONST               3 (None)
             1348 IMPORT_NAME             28 (random)
             1350 STORE_FAST              10 (random)

2265         1352 LOAD_FAST               10 (random)
             1354 LOAD_METHOD             29 (randint)
             1376 LOAD_CONST              18 (1)
             1378 LOAD_CONST              19 (100000)
             1380 PRECALL                  2
             1384 CALL                     2
             1394 LOAD_DEREF               0 (self)
             1396 STORE_ATTR              30 (current_seed)

2266         1406 LOAD_GLOBAL             43 (NULL + logging)
             1418 LOAD_ATTR               22 (info)
             1428 LOAD_CONST              22 ('Tạo seed mới cho generation thường: ')
             1430 LOAD_DEREF               0 (self)
             1432 LOAD_ATTR               30 (current_seed)
             1442 FORMAT_VALUE             0
             1444 BUILD_STRING             2
             1446 PRECALL                  1
             1450 CALL                     1
             1460 POP_TOP
             1462 JUMP_FORWARD            28 (to 1520)

2268     >>  1464 LOAD_GLOBAL             43 (NULL + logging)
             1476 LOAD_ATTR               22 (info)
             1486 LOAD_CONST              23 ('Sử dụng lại seed cũ: ')
             1488 LOAD_DEREF               0 (self)
             1490 LOAD_ATTR               30 (current_seed)
             1500 FORMAT_VALUE             0
             1502 BUILD_STRING             2
             1504 PRECALL                  1
             1508 CALL                     1
             1518 POP_TOP

2270     >>  1520 LOAD_DEREF               0 (self)
             1522 LOAD_ATTR               30 (current_seed)
             1532 STORE_FAST              11 (seed)
             1534 JUMP_FORWARD            22 (to 1580)

2272     >>  1536 LOAD_CONST               3 (None)
             1538 STORE_FAST              11 (seed)

2273         1540 LOAD_GLOBAL             43 (NULL + logging)
             1552 LOAD_ATTR               22 (info)
             1562 LOAD_CONST              24 ('Sử dụng seed ngẫu nhiên')
             1564 PRECALL                  1
             1568 CALL                     1
             1578 POP_TOP

2276     >>  1580 LOAD_GLOBAL             15 (NULL + len)
             1592 LOAD_FAST                2 (prompts)
             1594 PRECALL                  1
             1598 CALL                     1
             1608 LOAD_DEREF               0 (self)
             1610 STORE_ATTR              32 (total_tasks)

2277         1620 LOAD_CONST              17 (0)
             1622 LOAD_DEREF               0 (self)
             1624 STORE_ATTR              33 (completed_tasks)

2278         1634 LOAD_CONST              25 (True)
             1636 LOAD_DEREF               0 (self)
             1638 STORE_ATTR              34 (is_generating)

2279         1648 LOAD_DEREF               0 (self)
             1650 COPY                     1
             1652 LOAD_ATTR               35 (generation_session_id)
             1662 LOAD_CONST              18 (1)
             1664 BINARY_OP               13 (+=)
             1668 SWAP                     2
             1670 STORE_ATTR              35 (generation_session_id)

2282         1680 LOAD_GLOBAL             63 (NULL + hasattr)
             1692 LOAD_DEREF               0 (self)
             1694 LOAD_CONST              26 ('results_panel')
             1696 PRECALL                  2
             1700 CALL                     2
             1710 POP_JUMP_FORWARD_IF_FALSE    26 (to 1764)

2283         1712 LOAD_DEREF               0 (self)
             1714 LOAD_ATTR               36 (results_panel)
             1724 LOAD_METHOD             37 (set_generating_state)
             1746 LOAD_CONST              25 (True)
             1748 PRECALL                  1
             1752 CALL                     1
             1762 POP_TOP

2285     >>  1764 LOAD_GLOBAL             43 (NULL + logging)
             1776 LOAD_ATTR               22 (info)
             1786 LOAD_CONST              27 ('🔧 Starting generation session #')
             1788 LOAD_DEREF               0 (self)
             1790 LOAD_ATTR               35 (generation_session_id)
             1800 FORMAT_VALUE             0
             1802 BUILD_STRING             2
             1804 PRECALL                  1
             1808 CALL                     1
             1818 POP_TOP

2287         1820 LOAD_DEREF               0 (self)
             1822 LOAD_ATTR               38 (main_btn)
             1832 LOAD_METHOD             39 (setText)
             1854 LOAD_CONST              28 ('⏳ Đang tạo ảnh...')
             1856 PRECALL                  1
             1860 CALL                     1
             1870 POP_TOP

2288         1872 LOAD_DEREF               0 (self)
             1874 LOAD_ATTR               38 (main_btn)
             1884 LOAD_METHOD             40 (setEnabled)
             1906 LOAD_CONST              29 (False)
             1908 PRECALL                  1
             1912 CALL                     1
             1922 POP_TOP

2289         1924 LOAD_DEREF               0 (self)
             1926 LOAD_ATTR               38 (main_btn)
             1936 LOAD_METHOD             41 (setFixedWidth)
             1958 LOAD_CONST              30 (300)
             1960 PRECALL                  1
             1964 CALL                     1
             1974 POP_TOP

2290         1976 LOAD_DEREF               0 (self)
             1978 LOAD_METHOD             42 (apply_modern_style)
             2000 PRECALL                  0
             2004 CALL                     0
             2014 POP_TOP

2291         2016 LOAD_DEREF               0 (self)
             2018 LOAD_ATTR               36 (results_panel)
             2028 LOAD_ATTR               43 (progress_bar)
             2038 LOAD_METHOD             44 (setVisible)
             2060 LOAD_CONST              25 (True)
             2062 PRECALL                  1
             2066 CALL                     1
             2076 POP_TOP

2292         2078 LOAD_DEREF               0 (self)
             2080 LOAD_ATTR               36 (results_panel)
             2090 LOAD_ATTR               43 (progress_bar)
             2100 LOAD_METHOD             45 (setRange)
             2122 LOAD_CONST              17 (0)
             2124 LOAD_DEREF               0 (self)
             2126 LOAD_ATTR               32 (total_tasks)
             2136 PRECALL                  2
             2140 CALL                     2
             2150 POP_TOP

2293         2152 LOAD_DEREF               0 (self)
             2154 LOAD_ATTR               36 (results_panel)
             2164 LOAD_ATTR               43 (progress_bar)
             2174 LOAD_METHOD             46 (setValue)
             2196 LOAD_CONST              17 (0)
             2198 PRECALL                  1
             2202 CALL                     1
             2212 POP_TOP

2295         2214 NOP

2297         2216 LOAD_GLOBAL             63 (NULL + hasattr)
             2228 LOAD_DEREF               0 (self)
             2230 LOAD_ATTR               36 (results_panel)
             2240 LOAD_CONST              31 ('_remove_empty_help')
             2242 PRECALL                  2
             2246 CALL                     2
             2256 POP_JUMP_FORWARD_IF_FALSE    25 (to 2308)

2298         2258 LOAD_DEREF               0 (self)
             2260 LOAD_ATTR               36 (results_panel)
             2270 LOAD_METHOD             47 (_remove_empty_help)
             2292 PRECALL                  0
             2296 CALL                     0
             2306 POP_TOP
         >>  2308 JUMP_FORWARD            16 (to 2342)
         >>  2310 PUSH_EXC_INFO

2299         2312 LOAD_GLOBAL             96 (Exception)
             2324 CHECK_EXC_MATCH
             2326 POP_JUMP_FORWARD_IF_FALSE     3 (to 2334)
             2328 POP_TOP

2300         2330 POP_EXCEPT
             2332 JUMP_FORWARD             4 (to 2342)

2299     >>  2334 RERAISE                  0
         >>  2336 COPY                     3
             2338 POP_EXCEPT
             2340 RERAISE                  1

2302     >>  2342 LOAD_DEREF               0 (self)
             2344 LOAD_ATTR               35 (generation_session_id)
             2354 LOAD_DEREF               0 (self)
             2356 STORE_ATTR              49 (current_generation_session)

2306         2366 LOAD_GLOBAL             43 (NULL + logging)
             2378 LOAD_ATTR               22 (info)
             2388 LOAD_CONST              32 ('🚀 Starting new WebSocket generation (active threads: ')
             2390 LOAD_GLOBAL             15 (NULL + len)
             2402 LOAD_DEREF               0 (self)
             2404 LOAD_ATTR               50 (generation_threads)
             2414 PRECALL                  1
             2418 CALL                     1
             2428 FORMAT_VALUE             0
             2430 LOAD_CONST              33 (')')
             2432 BUILD_STRING             3
             2434 PRECALL                  1
             2438 CALL                     1
             2448 POP_TOP

2309         2450 LOAD_CONST              34 (<code object _compute_ratio_nums at 0x100b621f0, file "main_window_imagen.pyc", line 2309>)
             2452 MAKE_FUNCTION            0
             2454 STORE_FAST              12 (_compute_ratio_nums)

2319         2456 LOAD_CONST              35 ('image_path')
             2458 LOAD_GLOBAL            102 (str)
             2470 LOAD_CONST              36 ('ratio_w')
             2472 LOAD_GLOBAL            104 (int)
             2484 LOAD_CONST              37 ('ratio_h')
             2486 LOAD_GLOBAL            104 (int)
             2498 LOAD_CONST              38 ('return')
             2500 LOAD_GLOBAL            106 (QImage)
             2512 BUILD_TUPLE              8
             2514 LOAD_CONST              39 (<code object _crop_to_ratio at 0x14d882c00, file "main_window_imagen.pyc", line 2319>)
             2516 MAKE_FUNCTION            4 (annotations)
             2518 STORE_DEREF             90 (_crop_to_ratio)

2360         2520 LOAD_CONST              40 ('img')
             2522 LOAD_GLOBAL            106 (QImage)
             2534 LOAD_CONST              38 ('return')
             2536 LOAD_GLOBAL            102 (str)
             2548 BUILD_TUPLE              4
             2550 LOAD_CONST              41 (<code object _image_to_base64 at 0x14d6573c0, file "main_window_imagen.pyc", line 2360>)
             2552 MAKE_FUNCTION            4 (annotations)
             2554 STORE_DEREF             91 (_image_to_base64)

2379         2556 LOAD_DEREF               0 (self)
             2558 LOAD_ATTR               10 (aspect_combo)
             2568 LOAD_METHOD             11 (currentText)
             2590 PRECALL                  0
             2594 CALL                     0
             2604 STORE_FAST               4 (aspect_text)

2380         2606 PUSH_NULL
             2608 LOAD_FAST               12 (_compute_ratio_nums)
             2610 LOAD_FAST                4 (aspect_text)
             2612 PRECALL                  1
             2616 CALL                     1
             2626 UNPACK_SEQUENCE          2
             2630 STORE_DEREF             96 (ratio_w)
             2632 STORE_DEREF             95 (ratio_h)

2381         2634 BUILD_LIST               0
             2636 STORE_FAST              13 (images_payload)

2382         2638 NOP

2383         2640 LOAD_GLOBAL            109 (NULL + getattr)
             2652 LOAD_DEREF               0 (self)
             2654 LOAD_CONST              42 ('max_character_slots')
             2656 LOAD_CONST              43 (10)
             2658 PRECALL                  3
             2662 CALL                     3
             2672 STORE_FAST              14 (max_slots)

2384         2674 LOAD_GLOBAL            111 (NULL + list)
             2686 LOAD_GLOBAL            109 (NULL + getattr)
             2698 LOAD_DEREF               0 (self)
             2700 LOAD_CONST              44 ('character_import_slots')
             2702 BUILD_LIST               0
             2704 PRECALL                  3
             2708 CALL                     3
             2718 LOAD_CONST               3 (None)
             2720 LOAD_FAST               14 (max_slots)
             2722 BUILD_SLICE              2
             2724 BINARY_SUBSCR
             2734 PRECALL                  1
             2738 CALL                     1
             2748 STORE_FAST              15 (slots)

2386         2750 LOAD_CONST              45 (<code object <listcomp> at 0x100bbe950, file "main_window_imagen.pyc", line 2386>)
             2752 MAKE_FUNCTION            0

2388         2754 LOAD_GLOBAL            113 (NULL + range)
             2766 LOAD_FAST               14 (max_slots)
             2768 PRECALL                  1
             2772 CALL                     1

2386         2782 GET_ITER
             2784 PRECALL                  0
             2788 CALL                     0
             2798 STORE_FAST              13 (images_payload)

2391         2800 BUILD_LIST               0
             2802 STORE_FAST              16 (work_items)

2392         2804 LOAD_GLOBAL            115 (NULL + enumerate)
             2816 LOAD_FAST               15 (slots)
             2818 PRECALL                  1
             2822 CALL                     1
             2832 GET_ITER
         >>  2834 FOR_ITER                52 (to 2940)
             2836 UNPACK_SEQUENCE          2
             2840 STORE_FAST              17 (idx)
             2842 STORE_FAST              18 (slot)

2393         2844 LOAD_FAST               18 (slot)
             2846 POP_JUMP_FORWARD_IF_FALSE    45 (to 2938)
             2848 LOAD_GLOBAL            109 (NULL + getattr)
             2860 LOAD_FAST               18 (slot)
             2862 LOAD_CONST              35 ('image_path')
             2864 LOAD_CONST               3 (None)
             2866 PRECALL                  3
             2870 CALL                     3
             2880 POP_JUMP_FORWARD_IF_FALSE    28 (to 2938)

2394         2882 LOAD_FAST               16 (work_items)
             2884 LOAD_METHOD             58 (append)
             2906 LOAD_FAST               17 (idx)
             2908 LOAD_FAST               18 (slot)
             2910 LOAD_ATTR               59 (image_path)
             2920 BUILD_TUPLE              2
             2922 PRECALL                  1
             2926 CALL                     1
             2936 POP_TOP
         >>  2938 JUMP_BACKWARD           53 (to 2834)

2395     >>  2940 LOAD_FAST               16 (work_items)
             2942 POP_JUMP_FORWARD_IF_FALSE   146 (to 3236)

2396         2944 LOAD_CLOSURE            90 (_crop_to_ratio)
             2946 LOAD_CLOSURE            91 (_image_to_base64)
             2948 LOAD_CLOSURE            95 (ratio_h)
             2950 LOAD_CLOSURE            96 (ratio_w)
             2952 BUILD_TUPLE              4
             2954 LOAD_CONST              46 (<code object encode_one at 0x14d657910, file "main_window_imagen.pyc", line 2396>)
             2956 MAKE_FUNCTION            8 (closure)
             2958 STORE_DEREF             93 (encode_one)

2408         2960 LOAD_GLOBAL            121 (NULL + ThreadPoolExecutor)
             2972 LOAD_GLOBAL            123 (NULL + min)
             2984 LOAD_CONST              47 (5)
             2986 LOAD_GLOBAL             15 (NULL + len)
             2998 LOAD_FAST               16 (work_items)
             3000 PRECALL                  1
             3004 CALL                     1
             3014 PRECALL                  2
             3018 CALL                     2
             3028 KW_NAMES                48
             3030 PRECALL                  1
             3034 CALL                     1
             3044 BEFORE_WITH
             3046 STORE_DEREF             94 (ex)

2409         3048 LOAD_CLOSURE            93 (encode_one)
             3050 LOAD_CLOSURE            94 (ex)
             3052 BUILD_TUPLE              2
             3054 LOAD_CONST              49 (<code object <listcomp> at 0x100bcd130, file "main_window_imagen.pyc", line 2409>)
             3056 MAKE_FUNCTION            8 (closure)
             3058 LOAD_FAST               16 (work_items)
             3060 GET_ITER
             3062 PRECALL                  0
             3066 CALL                     0
             3076 STORE_FAST              19 (futures)

2410         3078 LOAD_GLOBAL            125 (NULL + as_completed)
             3090 LOAD_FAST               19 (futures)
             3092 PRECALL                  1
             3096 CALL                     1
             3106 GET_ITER
         >>  3108 FOR_ITER                39 (to 3188)
             3110 STORE_FAST              20 (f)

2411         3112 LOAD_FAST               20 (f)
             3114 LOAD_METHOD             63 (result)
             3136 PRECALL                  0
             3140 CALL                     0
             3150 UNPACK_SEQUENCE          2
             3154 STORE_FAST              21 (idx_slot)
             3156 STORE_FAST              22 (b64)

2412         3158 LOAD_FAST               22 (b64)
             3160 POP_JUMP_FORWARD_IF_FALSE    12 (to 3186)

2414         3162 LOAD_FAST               21 (idx_slot)
             3164 LOAD_CONST              18 (1)
             3166 BINARY_OP                0 (+)

2415         3170 LOAD_FAST               22 (b64)

2416         3172 LOAD_CONST              50 ('image/jpeg')

2413         3174 LOAD_CONST              51 (('index', 'base64', 'mimeType'))
             3176 BUILD_CONST_KEY_MAP      3
             3178 LOAD_FAST               13 (images_payload)
             3180 LOAD_FAST               21 (idx_slot)
             3182 STORE_SUBSCR
         >>  3186 JUMP_BACKWARD           40 (to 3108)

2410     >>  3188 NOP

2408         3190 LOAD_CONST               3 (None)
             3192 LOAD_CONST               3 (None)
             3194 LOAD_CONST               3 (None)
             3196 PRECALL                  2
             3200 CALL                     2
             3210 POP_TOP
             3212 JUMP_FORWARD            11 (to 3236)
         >>  3214 PUSH_EXC_INFO
             3216 WITH_EXCEPT_START
             3218 POP_JUMP_FORWARD_IF_TRUE     4 (to 3228)
             3220 RERAISE                  2
         >>  3222 COPY                     3
             3224 POP_EXCEPT
             3226 RERAISE                  1
         >>  3228 POP_TOP
             3230 POP_EXCEPT
             3232 POP_TOP
             3234 POP_TOP

2419     >>  3236 LOAD_FAST               13 (images_payload)
             3238 LOAD_METHOD             64 (sort)
             3260 LOAD_CONST              52 (<code object <lambda> at 0x100bcd230, file "main_window_imagen.pyc", line 2419>)
             3262 MAKE_FUNCTION            0
             3264 KW_NAMES                53
             3266 PRECALL                  1
             3270 CALL                     1
             3280 POP_TOP

2421         3282 LOAD_CONST              17 (0)
             3284 STORE_FAST              23 (non_empty_count)

2422         3286 NOP

2423         3288 LOAD_FAST               13 (images_payload)
             3290 GET_ITER
         >>  3292 FOR_ITER                30 (to 3354)
             3294 STORE_FAST              24 (it)

2424         3296 LOAD_FAST               24 (it)
             3298 POP_JUMP_FORWARD_IF_FALSE    26 (to 3352)
             3300 LOAD_FAST               24 (it)
             3302 LOAD_METHOD             13 (get)
             3324 LOAD_CONST              54 ('base64')
             3326 PRECALL                  1
             3330 CALL                     1
             3340 POP_JUMP_FORWARD_IF_FALSE     5 (to 3352)

2425         3342 LOAD_FAST               23 (non_empty_count)
             3344 LOAD_CONST              18 (1)
             3346 BINARY_OP               13 (+=)
             3350 STORE_FAST              23 (non_empty_count)
         >>  3352 JUMP_BACKWARD           31 (to 3292)

2423     >>  3354 JUMP_FORWARD            18 (to 3392)
         >>  3356 PUSH_EXC_INFO

2426         3358 LOAD_GLOBAL             96 (Exception)
             3370 CHECK_EXC_MATCH
             3372 POP_JUMP_FORWARD_IF_FALSE     5 (to 3384)
             3374 POP_TOP

2427         3376 LOAD_CONST              17 (0)
             3378 STORE_FAST              23 (non_empty_count)
             3380 POP_EXCEPT
             3382 JUMP_FORWARD             4 (to 3392)

2426     >>  3384 RERAISE                  0
         >>  3386 COPY                     3
             3388 POP_EXCEPT
             3390 RERAISE                  1

2428     >>  3392 LOAD_FAST               23 (non_empty_count)
             3394 LOAD_CONST              17 (0)
             3396 COMPARE_OP               2 (==)
             3402 POP_JUMP_FORWARD_IF_FALSE     2 (to 3408)

2429         3404 BUILD_LIST               0
             3406 STORE_FAST              13 (images_payload)
         >>  3408 JUMP_FORWARD            46 (to 3502)
         >>  3410 PUSH_EXC_INFO

2430         3412 LOAD_GLOBAL             96 (Exception)
             3424 CHECK_EXC_MATCH
             3426 POP_JUMP_FORWARD_IF_FALSE    33 (to 3494)
             3428 STORE_FAST              25 (e)

2431         3430 LOAD_GLOBAL             43 (NULL + logging)
             3442 LOAD_ATTR               65 (error)
             3452 LOAD_CONST              55 ('❌ Parallel attachments encode error: ')
             3454 LOAD_FAST               25 (e)
             3456 FORMAT_VALUE             0
             3458 BUILD_STRING             2
             3460 PRECALL                  1
             3464 CALL                     1
             3474 POP_TOP
             3476 POP_EXCEPT
             3478 LOAD_CONST               3 (None)
             3480 STORE_FAST              25 (e)
             3482 DELETE_FAST             25 (e)
             3484 JUMP_FORWARD             8 (to 3502)
         >>  3486 LOAD_CONST               3 (None)
             3488 STORE_FAST              25 (e)
             3490 DELETE_FAST             25 (e)
             3492 RERAISE                  1

2430     >>  3494 RERAISE                  0
         >>  3496 COPY                     3
             3498 POP_EXCEPT
             3500 RERAISE                  1

2436     >>  3502 LOAD_FAST               13 (images_payload)

2433         3504 POP_JUMP_FORWARD_IF_FALSE    30 (to 3566)

2434         3506 LOAD_FAST               13 (images_payload)

2435         3508 LOAD_DEREF               0 (self)
             3510 LOAD_ATTR               12 (aspect_mapping)
             3520 LOAD_METHOD             13 (get)
             3542 LOAD_FAST                4 (aspect_text)
             3544 LOAD_CONST               9 ('IMAGE_ASPECT_RATIO_LANDSCAPE')
             3546 PRECALL                  2
             3550 CALL                     2

2433         3560 LOAD_CONST              56 (('images', 'aspectRatio'))
             3562 BUILD_CONST_KEY_MAP      2
             3564 JUMP_FORWARD             1 (to 3568)

2436     >>  3566 LOAD_CONST               3 (None)

2433     >>  3568 STORE_FAST              26 (attachments_payload)

2438         3570 NOP

2439         3572 LOAD_FAST               26 (attachments_payload)
             3574 EXTENDED_ARG             1
             3576 POP_JUMP_FORWARD_IF_FALSE   447 (to 4472)

2440         3578 LOAD_GLOBAL             43 (NULL + logging)
             3590 LOAD_ATTR               22 (info)
             3600 LOAD_CONST              57 ('📎 Prepared attachments: ')
             3602 LOAD_GLOBAL             15 (NULL + len)
             3614 LOAD_FAST               13 (images_payload)
             3616 PRECALL                  1
             3620 CALL                     1
             3630 FORMAT_VALUE             0
             3632 LOAD_CONST              58 (' images, aspect=')
             3634 LOAD_FAST               26 (attachments_payload)
             3636 LOAD_CONST              59 ('aspectRatio')
             3638 BINARY_SUBSCR
             3648 FORMAT_VALUE             0
             3650 BUILD_STRING             4
             3652 PRECALL                  1
             3656 CALL                     1
             3666 POP_TOP

2442         3668 NOP

2443         3670 LOAD_GLOBAL            109 (NULL + getattr)
             3682 LOAD_DEREF               0 (self)
             3684 LOAD_CONST              42 ('max_character_slots')
             3686 LOAD_CONST              43 (10)
             3688 PRECALL                  3
             3692 CALL                     3
             3702 STORE_FAST              27 (max_slots_dbg)

2444         3704 LOAD_GLOBAL            113 (NULL + range)
             3716 LOAD_FAST               27 (max_slots_dbg)
             3718 PRECALL                  1
             3722 CALL                     1
             3732 GET_ITER
         >>  3734 EXTENDED_ARG             1
             3736 FOR_ITER               350 (to 4438)
             3738 STORE_FAST              28 (i_dbg)

2445         3740 LOAD_CONST              10 ('')
             3742 STORE_FAST              29 (name_dbg)

2446         3744 NOP

2447         3746 LOAD_FAST               28 (i_dbg)
             3748 LOAD_GLOBAL             15 (NULL + len)
             3760 LOAD_DEREF               0 (self)
             3762 LOAD_ATTR               66 (character_name_edits)
             3772 PRECALL                  1
             3776 CALL                     1
             3786 COMPARE_OP               0 (<)
             3792 POP_JUMP_FORWARD_IF_FALSE    51 (to 3896)

2448         3794 LOAD_DEREF               0 (self)
             3796 LOAD_ATTR               66 (character_name_edits)
             3806 LOAD_FAST               28 (i_dbg)
             3808 BINARY_SUBSCR
             3818 LOAD_METHOD             67 (text)
             3840 PRECALL                  0
             3844 CALL                     0
             3854 JUMP_IF_TRUE_OR_POP      1 (to 3858)
             3856 LOAD_CONST              10 ('')
         >>  3858 LOAD_METHOD              2 (strip)
             3880 PRECALL                  0
             3884 CALL                     0
             3894 STORE_FAST              29 (name_dbg)
         >>  3896 JUMP_FORWARD            18 (to 3934)
         >>  3898 PUSH_EXC_INFO

2449         3900 LOAD_GLOBAL             96 (Exception)
             3912 CHECK_EXC_MATCH
             3914 POP_JUMP_FORWARD_IF_FALSE     5 (to 3926)
             3916 POP_TOP

2450         3918 LOAD_CONST              10 ('')
             3920 STORE_FAST              29 (name_dbg)
             3922 POP_EXCEPT
             3924 JUMP_FORWARD             4 (to 3934)

2449     >>  3926 RERAISE                  0
         >>  3928 COPY                     3
             3930 POP_EXCEPT
             3932 RERAISE                  1

2451     >>  3934 LOAD_CONST               3 (None)
             3936 STORE_FAST              30 (file_dbg)

2452         3938 NOP

2453         3940 LOAD_FAST               28 (i_dbg)
             3942 LOAD_GLOBAL             15 (NULL + len)
             3954 LOAD_FAST               15 (slots)
             3956 PRECALL                  1
             3960 CALL                     1
             3970 COMPARE_OP               0 (<)
             3976 POP_JUMP_FORWARD_IF_FALSE    31 (to 4040)
             3978 LOAD_FAST               15 (slots)
             3980 LOAD_FAST               28 (i_dbg)
             3982 BINARY_SUBSCR
             3992 POP_JUMP_FORWARD_IF_FALSE    23 (to 4040)

2454         3994 LOAD_GLOBAL            109 (NULL + getattr)
             4006 LOAD_FAST               15 (slots)
             4008 LOAD_FAST               28 (i_dbg)
             4010 BINARY_SUBSCR
             4020 LOAD_CONST              35 ('image_path')
             4022 LOAD_CONST               3 (None)
             4024 PRECALL                  3
             4028 CALL                     3
             4038 STORE_FAST              30 (file_dbg)
         >>  4040 JUMP_FORWARD            18 (to 4078)
         >>  4042 PUSH_EXC_INFO

2455         4044 LOAD_GLOBAL             96 (Exception)
             4056 CHECK_EXC_MATCH
             4058 POP_JUMP_FORWARD_IF_FALSE     5 (to 4070)
             4060 POP_TOP

2456         4062 LOAD_CONST               3 (None)
             4064 STORE_FAST              30 (file_dbg)
             4066 POP_EXCEPT
             4068 JUMP_FORWARD             4 (to 4078)

2455     >>  4070 RERAISE                  0
         >>  4072 COPY                     3
             4074 POP_EXCEPT
             4076 RERAISE                  1

2457     >>  4078 LOAD_CONST              10 ('')
             4080 STORE_FAST              31 (b64_dbg)

2458         4082 NOP

2459         4084 LOAD_FAST               28 (i_dbg)
             4086 LOAD_GLOBAL             15 (NULL + len)
             4098 LOAD_FAST               13 (images_payload)
             4100 PRECALL                  1
             4104 CALL                     1
             4114 COMPARE_OP               0 (<)
             4120 POP_JUMP_FORWARD_IF_FALSE    28 (to 4178)

2460         4122 LOAD_FAST               13 (images_payload)
             4124 LOAD_FAST               28 (i_dbg)
             4126 BINARY_SUBSCR
             4136 LOAD_METHOD             13 (get)
             4158 LOAD_CONST              54 ('base64')
             4160 LOAD_CONST              10 ('')
             4162 PRECALL                  2
             4166 CALL                     2
             4176 STORE_FAST              31 (b64_dbg)
         >>  4178 JUMP_FORWARD            18 (to 4216)
         >>  4180 PUSH_EXC_INFO

2461         4182 LOAD_GLOBAL             96 (Exception)
             4194 CHECK_EXC_MATCH
             4196 POP_JUMP_FORWARD_IF_FALSE     5 (to 4208)
             4198 POP_TOP

2462         4200 LOAD_CONST              10 ('')
             4202 STORE_FAST              31 (b64_dbg)
             4204 POP_EXCEPT
             4206 JUMP_FORWARD             4 (to 4216)

2461     >>  4208 RERAISE                  0
         >>  4210 COPY                     3
             4212 POP_EXCEPT
             4214 RERAISE                  1

2463     >>  4216 LOAD_FAST               31 (b64_dbg)
             4218 POP_JUMP_FORWARD_IF_FALSE    15 (to 4250)
             4220 LOAD_GLOBAL             15 (NULL + len)
             4232 LOAD_FAST               31 (b64_dbg)
             4234 PRECALL                  1
             4238 CALL                     1
             4248 JUMP_FORWARD             1 (to 4252)
         >>  4250 LOAD_CONST              17 (0)
         >>  4252 STORE_FAST              32 (b64_len_dbg)

2464         4254 NOP

2465         4256 LOAD_FAST               30 (file_dbg)
             4258 POP_JUMP_FORWARD_IF_FALSE    31 (to 4322)
             4260 LOAD_GLOBAL            136 (os)
             4272 LOAD_ATTR               69 (path)
             4282 LOAD_METHOD             70 (basename)
             4304 LOAD_FAST               30 (file_dbg)
             4306 PRECALL                  1
             4310 CALL                     1
             4320 JUMP_FORWARD             1 (to 4324)
         >>  4322 LOAD_CONST              60 ('-')
         >>  4324 STORE_FAST              33 (base_dbg)
             4326 JUMP_FORWARD            18 (to 4364)
         >>  4328 PUSH_EXC_INFO

2466         4330 LOAD_GLOBAL             96 (Exception)
             4342 CHECK_EXC_MATCH
             4344 POP_JUMP_FORWARD_IF_FALSE     5 (to 4356)
             4346 POP_TOP

2467         4348 LOAD_CONST              60 ('-')
             4350 STORE_FAST              33 (base_dbg)
             4352 POP_EXCEPT
             4354 JUMP_FORWARD             4 (to 4364)

2466     >>  4356 RERAISE                  0
         >>  4358 COPY                     3
             4360 POP_EXCEPT
             4362 RERAISE                  1

2468     >>  4364 LOAD_GLOBAL             43 (NULL + logging)
             4376 LOAD_ATTR               22 (info)
             4386 LOAD_CONST              61 ('[ATTACH][MAP] idx=')
             4388 LOAD_FAST               28 (i_dbg)
             4390 LOAD_CONST              18 (1)
             4392 BINARY_OP                0 (+)
             4396 FORMAT_VALUE             0
             4398 LOAD_CONST              62 (" name='")
             4400 LOAD_FAST               29 (name_dbg)
             4402 FORMAT_VALUE             0
             4404 LOAD_CONST              63 ("' file='")
             4406 LOAD_FAST               33 (base_dbg)
             4408 FORMAT_VALUE             0
             4410 LOAD_CONST              64 ("' b64_len=")
             4412 LOAD_FAST               32 (b64_len_dbg)
             4414 FORMAT_VALUE             0
             4416 BUILD_STRING             8
             4418 PRECALL                  1
             4422 CALL                     1
             4432 POP_TOP
             4434 EXTENDED_ARG             1
             4436 JUMP_BACKWARD          352 (to 3734)

2444     >>  4438 JUMP_FORWARD            36 (to 4512)
         >>  4440 PUSH_EXC_INFO

2469         4442 LOAD_GLOBAL             96 (Exception)
             4454 CHECK_EXC_MATCH
             4456 POP_JUMP_FORWARD_IF_FALSE     3 (to 4464)
             4458 POP_TOP

2470         4460 POP_EXCEPT
             4462 JUMP_FORWARD            24 (to 4512)

2469     >>  4464 RERAISE                  0
         >>  4466 COPY                     3
             4468 POP_EXCEPT
             4470 RERAISE                  1

2472     >>  4472 LOAD_GLOBAL             43 (NULL + logging)
             4484 LOAD_ATTR               22 (info)
             4494 LOAD_CONST              65 ('📎 No attachments prepared (no character images loaded)')
             4496 PRECALL                  1
             4500 CALL                     1
             4510 POP_TOP
         >>  4512 JUMP_FORWARD            16 (to 4546)
         >>  4514 PUSH_EXC_INFO

2473         4516 LOAD_GLOBAL             96 (Exception)
             4528 CHECK_EXC_MATCH
             4530 POP_JUMP_FORWARD_IF_FALSE     3 (to 4538)
             4532 POP_TOP

2474         4534 POP_EXCEPT
             4536 JUMP_FORWARD             4 (to 4546)

2473     >>  4538 RERAISE                  0
         >>  4540 COPY                     3
             4542 POP_EXCEPT
             4544 RERAISE                  1

2478     >>  4546 LOAD_CONST              66 ('s')
             4548 LOAD_GLOBAL            102 (str)
             4560 LOAD_CONST              38 ('return')
             4562 LOAD_GLOBAL            142 (bool)
             4574 BUILD_TUPLE              4
             4576 LOAD_CONST              67 (<code object _is_vietnamese_text at 0x100affa60, file "main_window_imagen.pyc", line 2478>)
             4578 MAKE_FUNCTION            4 (annotations)
             4580 STORE_DEREF             92 (_is_vietnamese_text)

2485         4582 LOAD_CLOSURE             0 (self)
             4584 BUILD_TUPLE              1
             4586 LOAD_CONST              68 (<code object _collect_character_name_map at 0x14d657bd0, file "main_window_imagen.pyc", line 2485>)
             4588 MAKE_FUNCTION            8 (closure)
             4590 STORE_DEREF             89 (_collect_character_name_map)

2508         4592 LOAD_CONST              69 ('prompts_in')
             4594 LOAD_GLOBAL            110 (list)
             4606 BUILD_TUPLE              2
             4608 LOAD_CLOSURE            89 (_collect_character_name_map)
             4610 LOAD_CLOSURE            92 (_is_vietnamese_text)
             4612 BUILD_TUPLE              2
             4614 LOAD_CONST              70 (<code object _build_attachments_and_replace at 0x14d883200, file "main_window_imagen.pyc", line 2508>)
             4616 MAKE_FUNCTION           12 (annotations, closure)
             4618 STORE_FAST              34 (_build_attachments_and_replace)

2596         4620 PUSH_NULL
             4622 LOAD_FAST               34 (_build_attachments_and_replace)
             4624 LOAD_FAST                8 (final_prompts)
             4626 PRECALL                  1
             4630 CALL                     1
             4640 UNPACK_SEQUENCE          3
             4644 STORE_FAST              35 (attachments_by_index)
             4646 STORE_FAST               8 (final_prompts)
             4648 STORE_FAST              36 (attachments_order_by_index)

2598         4650 NOP

2599         4652 LOAD_FAST               36 (attachments_order_by_index)
             4654 LOAD_DEREF               0 (self)
             4656 STORE_ATTR              72 (preview_attachment_order)
             4666 JUMP_FORWARD            16 (to 4700)
         >>  4668 PUSH_EXC_INFO

2600         4670 LOAD_GLOBAL             96 (Exception)
             4682 CHECK_EXC_MATCH
             4684 POP_JUMP_FORWARD_IF_FALSE     3 (to 4692)
             4686 POP_TOP

2601         4688 POP_EXCEPT
             4690 JUMP_FORWARD             4 (to 4700)

2600     >>  4692 RERAISE                  0
         >>  4694 COPY                     3
             4696 POP_EXCEPT
             4698 RERAISE                  1

2604     >>  4700 BUILD_LIST               0
             4702 STORE_FAST              37 (issues)

2605         4704 NOP

2607         4706 NOP

2608         4708 PUSH_NULL
             4710 LOAD_DEREF              89 (_collect_character_name_map)
             4712 PRECALL                  0
             4716 CALL                     0
             4726 STORE_FAST              38 (name_map_for_check)
             4728 JUMP_FORWARD            18 (to 4766)
         >>  4730 PUSH_EXC_INFO

2609         4732 LOAD_GLOBAL             96 (Exception)
             4744 CHECK_EXC_MATCH
             4746 POP_JUMP_FORWARD_IF_FALSE     5 (to 4758)
             4748 POP_TOP

2610         4750 BUILD_LIST               0
             4752 STORE_FAST              38 (name_map_for_check)
             4754 POP_EXCEPT
             4756 JUMP_FORWARD             4 (to 4766)

2609     >>  4758 RERAISE                  0
         >>  4760 COPY                     3
             4762 POP_EXCEPT
             4764 RERAISE                  1

2611     >>  4766 LOAD_GLOBAL            147 (NULL + any)
             4778 LOAD_CONST              71 (<code object <genexpr> at 0x100c14120, file "main_window_imagen.pyc", line 2611>)
             4780 MAKE_FUNCTION            0
             4782 LOAD_GLOBAL            109 (NULL + getattr)
             4794 LOAD_DEREF               0 (self)
             4796 LOAD_CONST              44 ('character_import_slots')
             4798 BUILD_LIST               0
             4800 PRECALL                  3
             4804 CALL                     3
             4814 LOAD_CONST               3 (None)
             4816 LOAD_GLOBAL            109 (NULL + getattr)
             4828 LOAD_DEREF               0 (self)
             4830 LOAD_CONST              42 ('max_character_slots')
             4832 LOAD_CONST              43 (10)
             4834 PRECALL                  3
             4838 CALL                     3
             4848 BUILD_SLICE              2
             4850 BINARY_SUBSCR
             4860 GET_ITER
             4862 PRECALL                  0
             4866 CALL                     0
             4876 PRECALL                  1
             4880 CALL                     1
             4890 STORE_FAST              39 (has_any_image)

2613         4892 NOP

2614         4894 BUILD_LIST               0
             4896 STORE_FAST              40 (missing_name_slots)

2615         4898 LOAD_GLOBAL            109 (NULL + getattr)
             4910 LOAD_DEREF               0 (self)
             4912 LOAD_CONST              42 ('max_character_slots')
             4914 LOAD_CONST              43 (10)
             4916 PRECALL                  3
             4920 CALL                     3
             4930 STORE_FAST              41 (max_slots_check)

2616         4932 LOAD_GLOBAL            113 (NULL + range)
             4944 LOAD_GLOBAL            123 (NULL + min)
             4956 LOAD_FAST               41 (max_slots_check)
             4958 LOAD_GLOBAL             15 (NULL + len)
             4970 LOAD_DEREF               0 (self)
             4972 LOAD_ATTR               74 (character_import_slots)
             4982 PRECALL                  1
             4986 CALL                     1
             4996 PRECALL                  2
             5000 CALL                     2
             5010 PRECALL                  1
             5014 CALL                     1
             5024 GET_ITER
         >>  5026 FOR_ITER               141 (to 5310)
             5028 STORE_FAST              42 (i)

2617         5030 LOAD_DEREF               0 (self)
             5032 LOAD_ATTR               74 (character_import_slots)
             5042 LOAD_FAST               42 (i)
             5044 BINARY_SUBSCR
             5054 STORE_FAST              18 (slot)

2618         5056 LOAD_FAST               18 (slot)
             5058 POP_JUMP_FORWARD_IF_FALSE   124 (to 5308)
             5060 LOAD_GLOBAL            109 (NULL + getattr)
             5072 LOAD_FAST               18 (slot)
             5074 LOAD_CONST              35 ('image_path')
             5076 LOAD_CONST               3 (None)
             5078 PRECALL                  3
             5082 CALL                     3
             5092 POP_JUMP_FORWARD_IF_FALSE   107 (to 5308)

2619         5094 LOAD_FAST               42 (i)
             5096 LOAD_GLOBAL             15 (NULL + len)
             5108 LOAD_DEREF               0 (self)
             5110 LOAD_ATTR               66 (character_name_edits)
             5120 PRECALL                  1
             5124 CALL                     1
             5134 COMPARE_OP               0 (<)
             5140 POP_JUMP_FORWARD_IF_FALSE    13 (to 5168)
             5142 LOAD_DEREF               0 (self)
             5144 LOAD_ATTR               66 (character_name_edits)
             5154 LOAD_FAST               42 (i)
             5156 BINARY_SUBSCR
             5166 JUMP_FORWARD             1 (to 5170)
         >>  5168 LOAD_CONST               3 (None)
         >>  5170 STORE_FAST              43 (name_edit)

2620         5172 LOAD_FAST               43 (name_edit)
             5174 POP_JUMP_FORWARD_IF_FALSE    38 (to 5252)
             5176 LOAD_FAST               43 (name_edit)
             5178 LOAD_METHOD             67 (text)
             5200 PRECALL                  0
             5204 CALL                     0
             5214 LOAD_METHOD              2 (strip)
             5236 PRECALL                  0
             5240 CALL                     0
             5250 JUMP_FORWARD             1 (to 5254)
         >>  5252 LOAD_CONST              10 ('')
         >>  5254 STORE_FAST              44 (name_text)

2621         5256 LOAD_FAST               44 (name_text)
             5258 POP_JUMP_FORWARD_IF_TRUE    24 (to 5308)

2622         5260 LOAD_FAST               40 (missing_name_slots)
             5262 LOAD_METHOD             58 (append)
             5284 LOAD_FAST               42 (i)
             5286 LOAD_CONST              18 (1)
             5288 BINARY_OP                0 (+)
             5292 PRECALL                  1
             5296 CALL                     1
             5306 POP_TOP
         >>  5308 JUMP_BACKWARD          142 (to 5026)

2624     >>  5310 LOAD_FAST               39 (has_any_image)
             5312 EXTENDED_ARG             1
             5314 POP_JUMP_FORWARD_IF_FALSE   270 (to 5856)
             5316 LOAD_FAST               40 (missing_name_slots)
             5318 POP_JUMP_FORWARD_IF_TRUE     3 (to 5326)
             5320 LOAD_FAST               38 (name_map_for_check)
             5322 EXTENDED_ARG             1
             5324 POP_JUMP_FORWARD_IF_TRUE   265 (to 5856)

2625     >>  5326 NOP

2626         5328 LOAD_FAST               40 (missing_name_slots)
             5330 POP_JUMP_FORWARD_IF_FALSE    39 (to 5410)
             5332 LOAD_CONST              72 (', ')
             5334 LOAD_METHOD             75 (join)
             5356 LOAD_CONST              73 (<code object <genexpr> at 0x100c14210, file "main_window_imagen.pyc", line 2626>)
             5358 MAKE_FUNCTION            0
             5360 LOAD_FAST               40 (missing_name_slots)
             5362 LOAD_CONST               3 (None)
             5364 LOAD_CONST              43 (10)
             5366 BUILD_SLICE              2
             5368 BINARY_SUBSCR
             5378 GET_ITER
             5380 PRECALL                  0
             5384 CALL                     0
             5394 PRECALL                  1
             5398 CALL                     1
             5408 JUMP_FORWARD             1 (to 5412)
         >>  5410 LOAD_CONST              60 ('-')
         >>  5412 STORE_FAST              45 (disp_missing)

2627         5414 LOAD_FAST               40 (missing_name_slots)
             5416 POP_JUMP_FORWARD_IF_FALSE    24 (to 5466)
             5418 LOAD_GLOBAL             15 (NULL + len)
             5430 LOAD_FAST               40 (missing_name_slots)
             5432 PRECALL                  1
             5436 CALL                     1
             5446 LOAD_CONST              43 (10)
             5448 COMPARE_OP               4 (>)
             5454 POP_JUMP_FORWARD_IF_FALSE     5 (to 5466)

2628         5456 LOAD_FAST               45 (disp_missing)
             5458 LOAD_CONST              74 (', ...')
             5460 BINARY_OP               13 (+=)
             5464 STORE_FAST              45 (disp_missing)

2629     >>  5466 LOAD_GLOBAL              7 (NULL + QMessageBox)
             5478 LOAD_ATTR               76 (critical)

2630         5488 LOAD_DEREF               0 (self)

2631         5490 LOAD_CONST              75 ('Thiếu tên nhân vật')

2632         5492 LOAD_CONST              76 ('Bạn đã đính kèm ảnh nhưng chưa đặt tên cho các slot sau: ')
             5494 LOAD_FAST               45 (disp_missing)
             5496 FORMAT_VALUE             0
             5498 LOAD_CONST              77 ('.\nVui lòng đặt tên cho tất cả ảnh hoặc xoá ảnh chưa được đặt tên rồi thử lại.')
             5500 BUILD_STRING             3

2629         5502 PRECALL                  3
             5506 CALL                     3
             5516 POP_TOP
             5518 JUMP_FORWARD            16 (to 5552)
         >>  5520 PUSH_EXC_INFO

2634         5522 LOAD_GLOBAL             96 (Exception)
             5534 CHECK_EXC_MATCH
             5536 POP_JUMP_FORWARD_IF_FALSE     3 (to 5544)
             5538 POP_TOP

2635         5540 POP_EXCEPT
             5542 JUMP_FORWARD             4 (to 5552)

2634     >>  5544 RERAISE                  0
         >>  5546 COPY                     3
             5548 POP_EXCEPT
             5550 RERAISE                  1

2637     >>  5552 LOAD_CONST              29 (False)
             5554 LOAD_DEREF               0 (self)
             5556 STORE_ATTR              34 (is_generating)

2638         5566 LOAD_GLOBAL             63 (NULL + hasattr)
             5578 LOAD_DEREF               0 (self)
             5580 LOAD_CONST              26 ('results_panel')
             5582 PRECALL                  2
             5586 CALL                     2
             5596 POP_JUMP_FORWARD_IF_FALSE    26 (to 5650)

2639         5598 LOAD_DEREF               0 (self)
             5600 LOAD_ATTR               36 (results_panel)
             5610 LOAD_METHOD             37 (set_generating_state)
             5632 LOAD_CONST              29 (False)
             5634 PRECALL                  1
             5638 CALL                     1
             5648 POP_TOP

2640     >>  5650 NOP

2641         5652 LOAD_DEREF               0 (self)
             5654 LOAD_ATTR               38 (main_btn)
             5664 LOAD_METHOD             40 (setEnabled)
             5686 LOAD_CONST              25 (True)
             5688 PRECALL                  1
             5692 CALL                     1
             5702 POP_TOP

2642         5704 LOAD_DEREF               0 (self)
             5706 LOAD_ATTR               38 (main_btn)
             5716 LOAD_METHOD             39 (setText)
             5738 LOAD_CONST              78 ('🚀 Bắt đầu tạo ảnh')
             5740 PRECALL                  1
             5744 CALL                     1
             5754 POP_TOP

2643         5756 LOAD_DEREF               0 (self)
             5758 LOAD_ATTR               36 (results_panel)
             5768 LOAD_ATTR               43 (progress_bar)
             5778 LOAD_METHOD             44 (setVisible)
             5800 LOAD_CONST              29 (False)
             5802 PRECALL                  1
             5806 CALL                     1
             5816 POP_TOP
             5818 JUMP_FORWARD            16 (to 5852)
         >>  5820 PUSH_EXC_INFO

2644         5822 LOAD_GLOBAL             96 (Exception)
             5834 CHECK_EXC_MATCH
             5836 POP_JUMP_FORWARD_IF_FALSE     3 (to 5844)
             5838 POP_TOP

2645         5840 POP_EXCEPT
             5842 JUMP_FORWARD             4 (to 5852)

2644     >>  5844 RERAISE                  0
         >>  5846 COPY                     3
             5848 POP_EXCEPT
             5850 RERAISE                  1

2646     >>  5852 LOAD_CONST               3 (None)
             5854 RETURN_VALUE
         >>  5856 JUMP_FORWARD            16 (to 5890)
         >>  5858 PUSH_EXC_INFO

2647         5860 LOAD_GLOBAL             96 (Exception)
             5872 CHECK_EXC_MATCH
             5874 POP_JUMP_FORWARD_IF_FALSE     3 (to 5882)
             5876 POP_TOP

2648         5878 POP_EXCEPT
             5880 JUMP_FORWARD             4 (to 5890)

2647     >>  5882 RERAISE                  0
         >>  5884 COPY                     3
             5886 POP_EXCEPT
             5888 RERAISE                  1

2652     >>  5890 NOP

2653         5892 LOAD_FAST               39 (has_any_image)
             5894 POP_JUMP_FORWARD_IF_FALSE   114 (to 6124)

2654         5896 LOAD_CONST              79 (<code object <listcomp> at 0x100bcd330, file "main_window_imagen.pyc", line 2654>)
             5898 MAKE_FUNCTION            0
             5900 LOAD_GLOBAL            115 (NULL + enumerate)
             5912 LOAD_FAST               35 (attachments_by_index)
             5914 PRECALL                  1
             5918 CALL                     1
             5928 GET_ITER
             5930 PRECALL                  0
             5934 CALL                     0
             5944 STORE_FAST              46 (prompts_no_name)

2655         5946 LOAD_FAST               46 (prompts_no_name)
             5948 POP_JUMP_FORWARD_IF_FALSE    87 (to 6124)

2656         5950 LOAD_CONST              72 (', ')
             5952 LOAD_METHOD             75 (join)
             5974 LOAD_CONST              80 (<code object <genexpr> at 0x100c143f0, file "main_window_imagen.pyc", line 2656>)
             5976 MAKE_FUNCTION            0
             5978 LOAD_FAST               46 (prompts_no_name)
             5980 LOAD_CONST               3 (None)
             5982 LOAD_CONST              43 (10)
             5984 BUILD_SLICE              2
             5986 BINARY_SUBSCR
             5996 GET_ITER
             5998 PRECALL                  0
             6002 CALL                     0
             6012 PRECALL                  1
             6016 CALL                     1
             6026 STORE_FAST              47 (disp)

2657         6028 LOAD_GLOBAL             15 (NULL + len)
             6040 LOAD_FAST               46 (prompts_no_name)
             6042 PRECALL                  1
             6046 CALL                     1
             6056 LOAD_CONST              43 (10)
             6058 COMPARE_OP               4 (>)
             6064 POP_JUMP_FORWARD_IF_FALSE     5 (to 6076)

2658         6066 LOAD_FAST               47 (disp)
             6068 LOAD_CONST              74 (', ...')
             6070 BINARY_OP               13 (+=)
             6074 STORE_FAST              47 (disp)

2659     >>  6076 LOAD_FAST               37 (issues)
             6078 LOAD_METHOD             58 (append)
             6100 LOAD_CONST              81 ('Các dòng prompt không chứa tên nhân vật: ')
             6102 LOAD_FAST               47 (disp)
             6104 FORMAT_VALUE             0
             6106 BUILD_STRING             2
             6108 PRECALL                  1
             6112 CALL                     1
             6122 POP_TOP
         >>  6124 JUMP_FORWARD            16 (to 6158)
         >>  6126 PUSH_EXC_INFO

2660         6128 LOAD_GLOBAL             96 (Exception)
             6140 CHECK_EXC_MATCH
             6142 POP_JUMP_FORWARD_IF_FALSE     3 (to 6150)
             6144 POP_TOP

2661         6146 POP_EXCEPT
             6148 JUMP_FORWARD             4 (to 6158)

2660     >>  6150 RERAISE                  0
         >>  6152 COPY                     3
             6154 POP_EXCEPT
             6156 RERAISE                  1

2664     >>  6158 NOP

2666         6160 LOAD_FAST               38 (name_map_for_check)
             6162 EXTENDED_ARG             1
             6164 POP_JUMP_FORWARD_IF_FALSE   503 (to 7172)

2667         6166 LOAD_CONST              82 (<code object <listcomp> at 0x100affb90, file "main_window_imagen.pyc", line 2667>)
             6168 MAKE_FUNCTION            0
             6170 LOAD_FAST               38 (name_map_for_check)
             6172 GET_ITER
             6174 PRECALL                  0
             6178 CALL                     0
             6188 STORE_FAST              48 (alts)

2668         6190 LOAD_FAST               48 (alts)
             6192 EXTENDED_ARG             1
             6194 POP_JUMP_FORWARD_IF_FALSE   488 (to 7172)

2669         6196 LOAD_GLOBAL            155 (NULL + re)
             6208 LOAD_ATTR               78 (compile)
             6218 LOAD_CONST              83 ('(?iu)\\b(')
             6220 LOAD_CONST              84 ('|')
             6222 LOAD_METHOD             75 (join)
             6244 LOAD_FAST               48 (alts)
             6246 PRECALL                  1
             6250 CALL                     1
             6260 BINARY_OP                0 (+)
             6264 LOAD_CONST              85 (')\\b')
             6266 BINARY_OP                0 (+)
             6270 PRECALL                  1
             6274 CALL                     1
             6284 STORE_FAST              49 (pat)

2670         6286 BUILD_LIST               0
             6288 STORE_FAST              50 (overflow_lines)

2671         6290 LOAD_GLOBAL            115 (NULL + enumerate)
             6302 LOAD_FAST                9 (final_prompts_before_replace)
             6304 PRECALL                  1
             6308 CALL                     1
             6318 GET_ITER
         >>  6320 FOR_ITER               164 (to 6650)
             6322 UNPACK_SEQUENCE          2
             6326 STORE_FAST              51 (idx_p)
             6328 STORE_FAST              52 (line)

2672         6330 LOAD_GLOBAL            159 (NULL + set)
             6342 PRECALL                  0
             6346 CALL                     0
             6356 STORE_FAST              53 (found_names)

2673         6358 LOAD_FAST               49 (pat)
             6360 LOAD_METHOD             80 (finditer)
             6382 LOAD_FAST               52 (line)
             6384 JUMP_IF_TRUE_OR_POP      1 (to 6388)
             6386 LOAD_CONST              10 ('')
         >>  6388 PRECALL                  1
             6392 CALL                     1
             6402 GET_ITER
         >>  6404 FOR_ITER                78 (to 6562)
             6406 STORE_FAST              54 (m)

2674         6408 LOAD_FAST               53 (found_names)
             6410 LOAD_METHOD             81 (add)
             6432 LOAD_FAST               54 (m)
             6434 LOAD_METHOD             82 (group)
             6456 LOAD_CONST              17 (0)
             6458 PRECALL                  1
             6462 CALL                     1
             6472 LOAD_METHOD              2 (strip)
             6494 PRECALL                  0
             6498 CALL                     0
             6508 LOAD_METHOD             83 (lower)
             6530 PRECALL                  0
             6534 CALL                     0
             6544 PRECALL                  1
             6548 CALL                     1
             6558 POP_TOP
             6560 JUMP_BACKWARD           79 (to 6404)

2675     >>  6562 LOAD_GLOBAL             15 (NULL + len)
             6574 LOAD_FAST               53 (found_names)
             6576 PRECALL                  1
             6580 CALL                     1
             6590 LOAD_CONST              43 (10)
             6592 COMPARE_OP               4 (>)
             6598 POP_JUMP_FORWARD_IF_FALSE    24 (to 6648)

2676         6600 LOAD_FAST               50 (overflow_lines)
             6602 LOAD_METHOD             58 (append)
             6624 LOAD_FAST               51 (idx_p)
             6626 LOAD_CONST              18 (1)
             6628 BINARY_OP                0 (+)
             6632 PRECALL                  1
             6636 CALL                     1
             6646 POP_TOP
         >>  6648 JUMP_BACKWARD          165 (to 6320)

2678     >>  6650 LOAD_FAST               50 (overflow_lines)
             6652 EXTENDED_ARG             1
             6654 POP_JUMP_FORWARD_IF_FALSE   258 (to 7172)

2679         6656 NOP

2680         6658 LOAD_CONST              72 (', ')
             6660 LOAD_METHOD             75 (join)
             6682 LOAD_CONST              86 (<code object <genexpr> at 0x100c144e0, file "main_window_imagen.pyc", line 2680>)
             6684 MAKE_FUNCTION            0
             6686 LOAD_FAST               50 (overflow_lines)
             6688 LOAD_CONST               3 (None)
             6690 LOAD_CONST              43 (10)
             6692 BUILD_SLICE              2
             6694 BINARY_SUBSCR
             6704 GET_ITER
             6706 PRECALL                  0
             6710 CALL                     0
             6720 PRECALL                  1
             6724 CALL                     1
             6734 STORE_FAST              55 (disp_ov)

2681         6736 LOAD_GLOBAL             15 (NULL + len)
             6748 LOAD_FAST               50 (overflow_lines)
             6750 PRECALL                  1
             6754 CALL                     1
             6764 LOAD_CONST              43 (10)
             6766 COMPARE_OP               4 (>)
             6772 POP_JUMP_FORWARD_IF_FALSE     5 (to 6784)

2682         6774 LOAD_FAST               55 (disp_ov)
             6776 LOAD_CONST              74 (', ...')
             6778 BINARY_OP               13 (+=)
             6782 STORE_FAST              55 (disp_ov)

2683     >>  6784 LOAD_GLOBAL              7 (NULL + QMessageBox)
             6796 LOAD_ATTR               76 (critical)

2684         6806 LOAD_DEREF               0 (self)

2685         6808 LOAD_CONST              87 ('Quá 10 ảnh đính kèm')

2686         6810 LOAD_CONST              88 ('Một số prompt chứa hơn 10 nhân vật được tham chiếu theo tên.\nMỗi prompt chỉ được đính kèm tối đa 10 ảnh.\nDòng vi phạm: ')
             6812 LOAD_FAST               55 (disp_ov)
             6814 FORMAT_VALUE             0
             6816 BUILD_STRING             2

2683         6818 PRECALL                  3
             6822 CALL                     3
             6832 POP_TOP
             6834 JUMP_FORWARD            16 (to 6868)
         >>  6836 PUSH_EXC_INFO

2688         6838 LOAD_GLOBAL             96 (Exception)
             6850 CHECK_EXC_MATCH
             6852 POP_JUMP_FORWARD_IF_FALSE     3 (to 6860)
             6854 POP_TOP

2689         6856 POP_EXCEPT
             6858 JUMP_FORWARD             4 (to 6868)

2688     >>  6860 RERAISE                  0
         >>  6862 COPY                     3
             6864 POP_EXCEPT
             6866 RERAISE                  1

2691     >>  6868 LOAD_CONST              29 (False)
             6870 LOAD_DEREF               0 (self)
             6872 STORE_ATTR              34 (is_generating)

2692         6882 LOAD_GLOBAL             63 (NULL + hasattr)
             6894 LOAD_DEREF               0 (self)
             6896 LOAD_CONST              26 ('results_panel')
             6898 PRECALL                  2
             6902 CALL                     2
             6912 POP_JUMP_FORWARD_IF_FALSE    26 (to 6966)

2693         6914 LOAD_DEREF               0 (self)
             6916 LOAD_ATTR               36 (results_panel)
             6926 LOAD_METHOD             37 (set_generating_state)
             6948 LOAD_CONST              29 (False)
             6950 PRECALL                  1
             6954 CALL                     1
             6964 POP_TOP

2694     >>  6966 NOP

2695         6968 LOAD_DEREF               0 (self)
             6970 LOAD_ATTR               38 (main_btn)
             6980 LOAD_METHOD             40 (setEnabled)
             7002 LOAD_CONST              25 (True)
             7004 PRECALL                  1
             7008 CALL                     1
             7018 POP_TOP

2696         7020 LOAD_DEREF               0 (self)
             7022 LOAD_ATTR               38 (main_btn)
             7032 LOAD_METHOD             39 (setText)
             7054 LOAD_CONST              78 ('🚀 Bắt đầu tạo ảnh')
             7056 PRECALL                  1
             7060 CALL                     1
             7070 POP_TOP

2697         7072 LOAD_DEREF               0 (self)
             7074 LOAD_ATTR               36 (results_panel)
             7084 LOAD_ATTR               43 (progress_bar)
             7094 LOAD_METHOD             44 (setVisible)
             7116 LOAD_CONST              29 (False)
             7118 PRECALL                  1
             7122 CALL                     1
             7132 POP_TOP
             7134 JUMP_FORWARD            16 (to 7168)
         >>  7136 PUSH_EXC_INFO

2698         7138 LOAD_GLOBAL             96 (Exception)
             7150 CHECK_EXC_MATCH
             7152 POP_JUMP_FORWARD_IF_FALSE     3 (to 7160)
             7154 POP_TOP

2699         7156 POP_EXCEPT
             7158 JUMP_FORWARD             4 (to 7168)

2698     >>  7160 RERAISE                  0
         >>  7162 COPY                     3
             7164 POP_EXCEPT
             7166 RERAISE                  1

2700     >>  7168 LOAD_CONST               3 (None)
             7170 RETURN_VALUE
         >>  7172 JUMP_FORWARD            16 (to 7206)
         >>  7174 PUSH_EXC_INFO

2701         7176 LOAD_GLOBAL             96 (Exception)
             7188 CHECK_EXC_MATCH
             7190 POP_JUMP_FORWARD_IF_FALSE     3 (to 7198)
             7192 POP_TOP

2702         7194 POP_EXCEPT
             7196 JUMP_FORWARD             4 (to 7206)

2701     >>  7198 RERAISE                  0
         >>  7200 COPY                     3
             7202 POP_EXCEPT
             7204 RERAISE                  1

2705     >>  7206 NOP

2706         7208 LOAD_CONST              89 ('x')
             7210 LOAD_GLOBAL            104 (int)
             7222 BUILD_TUPLE              2
             7224 LOAD_CONST              90 (<code object _count_bits at 0x100c04580, file "main_window_imagen.pyc", line 2706>)
             7226 MAKE_FUNCTION            4 (annotations)
             7228 STORE_FAST              56 (_count_bits)

2713         7230 BUILD_LIST               0
             7232 STORE_FAST              57 (overflow_bit_lines)

2714         7234 LOAD_GLOBAL            115 (NULL + enumerate)
             7246 LOAD_FAST               35 (attachments_by_index)
             7248 JUMP_IF_TRUE_OR_POP      1 (to 7252)
             7250 BUILD_LIST               0
         >>  7252 PRECALL                  1
             7256 CALL                     1
             7266 GET_ITER
         >>  7268 FOR_ITER                44 (to 7358)
             7270 UNPACK_SEQUENCE          2
             7274 STORE_FAST              58 (i_b)
             7276 STORE_FAST              59 (b)

2715         7278 PUSH_NULL
             7280 LOAD_FAST               56 (_count_bits)
             7282 LOAD_FAST               59 (b)
             7284 PRECALL                  1
             7288 CALL                     1
             7298 LOAD_CONST              43 (10)
             7300 COMPARE_OP               4 (>)
             7306 POP_JUMP_FORWARD_IF_FALSE    24 (to 7356)

2716         7308 LOAD_FAST               57 (overflow_bit_lines)
             7310 LOAD_METHOD             58 (append)
             7332 LOAD_FAST               58 (i_b)
             7334 LOAD_CONST              18 (1)
             7336 BINARY_OP                0 (+)
             7340 PRECALL                  1
             7344 CALL                     1
             7354 POP_TOP
         >>  7356 JUMP_BACKWARD           45 (to 7268)

2717     >>  7358 LOAD_FAST               57 (overflow_bit_lines)
             7360 EXTENDED_ARG             1
             7362 POP_JUMP_FORWARD_IF_FALSE   258 (to 7880)

2718         7364 NOP

2719         7366 LOAD_CONST              72 (', ')
             7368 LOAD_METHOD             75 (join)
             7390 LOAD_CONST              91 (<code object <genexpr> at 0x100c145d0, file "main_window_imagen.pyc", line 2719>)
             7392 MAKE_FUNCTION            0
             7394 LOAD_FAST               57 (overflow_bit_lines)
             7396 LOAD_CONST               3 (None)
             7398 LOAD_CONST              43 (10)
             7400 BUILD_SLICE              2
             7402 BINARY_SUBSCR
             7412 GET_ITER
             7414 PRECALL                  0
             7418 CALL                     0
             7428 PRECALL                  1
             7432 CALL                     1
             7442 STORE_FAST              60 (disp_ob)

2720         7444 LOAD_GLOBAL             15 (NULL + len)
             7456 LOAD_FAST               57 (overflow_bit_lines)
             7458 PRECALL                  1
             7462 CALL                     1
             7472 LOAD_CONST              43 (10)
             7474 COMPARE_OP               4 (>)
             7480 POP_JUMP_FORWARD_IF_FALSE     5 (to 7492)

2721         7482 LOAD_FAST               60 (disp_ob)
             7484 LOAD_CONST              74 (', ...')
             7486 BINARY_OP               13 (+=)
             7490 STORE_FAST              60 (disp_ob)

2722     >>  7492 LOAD_GLOBAL              7 (NULL + QMessageBox)
             7504 LOAD_ATTR               76 (critical)

2723         7514 LOAD_DEREF               0 (self)

2724         7516 LOAD_CONST              87 ('Quá 10 ảnh đính kèm')

2725         7518 LOAD_CONST              92 ('Một số prompt đính kèm hơn 10 ảnh (theo chỉ số).\nMỗi prompt chỉ được đính kèm tối đa 10 ảnh.\nDòng vi phạm: ')
             7520 LOAD_FAST               60 (disp_ob)
             7522 FORMAT_VALUE             0
             7524 BUILD_STRING             2

2722         7526 PRECALL                  3
             7530 CALL                     3
             7540 POP_TOP
             7542 JUMP_FORWARD            16 (to 7576)
         >>  7544 PUSH_EXC_INFO

2727         7546 LOAD_GLOBAL             96 (Exception)
             7558 CHECK_EXC_MATCH
             7560 POP_JUMP_FORWARD_IF_FALSE     3 (to 7568)
             7562 POP_TOP

2728         7564 POP_EXCEPT
             7566 JUMP_FORWARD             4 (to 7576)

2727     >>  7568 RERAISE                  0
         >>  7570 COPY                     3
             7572 POP_EXCEPT
             7574 RERAISE                  1

2730     >>  7576 LOAD_CONST              29 (False)
             7578 LOAD_DEREF               0 (self)
             7580 STORE_ATTR              34 (is_generating)

2731         7590 LOAD_GLOBAL             63 (NULL + hasattr)
             7602 LOAD_DEREF               0 (self)
             7604 LOAD_CONST              26 ('results_panel')
             7606 PRECALL                  2
             7610 CALL                     2
             7620 POP_JUMP_FORWARD_IF_FALSE    26 (to 7674)

2732         7622 LOAD_DEREF               0 (self)
             7624 LOAD_ATTR               36 (results_panel)
             7634 LOAD_METHOD             37 (set_generating_state)
             7656 LOAD_CONST              29 (False)
             7658 PRECALL                  1
             7662 CALL                     1
             7672 POP_TOP

2733     >>  7674 NOP

2734         7676 LOAD_DEREF               0 (self)
             7678 LOAD_ATTR               38 (main_btn)
             7688 LOAD_METHOD             40 (setEnabled)
             7710 LOAD_CONST              25 (True)
             7712 PRECALL                  1
             7716 CALL                     1
             7726 POP_TOP

2735         7728 LOAD_DEREF               0 (self)
             7730 LOAD_ATTR               38 (main_btn)
             7740 LOAD_METHOD             39 (setText)
             7762 LOAD_CONST              78 ('🚀 Bắt đầu tạo ảnh')
             7764 PRECALL                  1
             7768 CALL                     1
             7778 POP_TOP

2736         7780 LOAD_DEREF               0 (self)
             7782 LOAD_ATTR               36 (results_panel)
             7792 LOAD_ATTR               43 (progress_bar)
             7802 LOAD_METHOD             44 (setVisible)
             7824 LOAD_CONST              29 (False)
             7826 PRECALL                  1
             7830 CALL                     1
             7840 POP_TOP
             7842 JUMP_FORWARD            16 (to 7876)
         >>  7844 PUSH_EXC_INFO

2737         7846 LOAD_GLOBAL             96 (Exception)
             7858 CHECK_EXC_MATCH
             7860 POP_JUMP_FORWARD_IF_FALSE     3 (to 7868)
             7862 POP_TOP

2738         7864 POP_EXCEPT
             7866 JUMP_FORWARD             4 (to 7876)

2737     >>  7868 RERAISE                  0
         >>  7870 COPY                     3
             7872 POP_EXCEPT
             7874 RERAISE                  1

2739     >>  7876 LOAD_CONST               3 (None)
             7878 RETURN_VALUE

2717     >>  7880 JUMP_FORWARD            16 (to 7914)
         >>  7882 PUSH_EXC_INFO

2741         7884 LOAD_GLOBAL             96 (Exception)
             7896 CHECK_EXC_MATCH
             7898 POP_JUMP_FORWARD_IF_FALSE     3 (to 7906)
             7900 POP_TOP

2742         7902 POP_EXCEPT
             7904 JUMP_FORWARD             4 (to 7914)

2741     >>  7906 RERAISE                  0
         >>  7908 COPY                     3
             7910 POP_EXCEPT
             7912 RERAISE                  1

2745     >>  7914 NOP

2746         7916 JUMP_FORWARD            16 (to 7950)
             7918 PUSH_EXC_INFO

2747         7920 LOAD_GLOBAL             96 (Exception)
             7932 CHECK_EXC_MATCH
             7934 POP_JUMP_FORWARD_IF_FALSE     3 (to 7942)
             7936 POP_TOP

2748         7938 POP_EXCEPT
             7940 JUMP_FORWARD             4 (to 7950)

2747     >>  7942 RERAISE                  0
         >>  7944 COPY                     3
             7946 POP_EXCEPT
             7948 RERAISE                  1

2750     >>  7950 LOAD_FAST               37 (issues)
             7952 EXTENDED_ARG             1
             7954 POP_JUMP_FORWARD_IF_FALSE   267 (to 8490)

2752         7956 LOAD_CONST              93 ('\n\n')
             7958 LOAD_METHOD             75 (join)
             7980 LOAD_FAST               37 (issues)
             7982 PRECALL                  1
             7986 CALL                     1
             7996 STORE_FAST              61 (msg)

2753         7998 NOP

2754         8000 LOAD_GLOBAL              7 (NULL + QMessageBox)
             8012 LOAD_ATTR               84 (question)

2755         8022 LOAD_DEREF               0 (self)

2756         8024 LOAD_CONST              94 ('Xác nhận tạo ảnh')

2757         8026 LOAD_FAST               61 (msg)
             8028 LOAD_CONST              95 ('\n\nBạn có muốn tiếp tục không?')
             8030 BINARY_OP                0 (+)

2758         8034 LOAD_GLOBAL              6 (QMessageBox)
             8046 LOAD_ATTR               85 (Yes)
             8056 LOAD_GLOBAL              6 (QMessageBox)
             8068 LOAD_ATTR               86 (No)
             8078 BINARY_OP                7 (|)

2759         8082 LOAD_GLOBAL              6 (QMessageBox)
             8094 LOAD_ATTR               85 (Yes)

2754         8104 PRECALL                  5
             8108 CALL                     5
             8118 STORE_FAST              62 (reply)

2761         8120 LOAD_FAST               62 (reply)
             8122 LOAD_GLOBAL              6 (QMessageBox)
             8134 LOAD_ATTR               86 (No)
             8144 COMPARE_OP               2 (==)
             8150 POP_JUMP_FORWARD_IF_FALSE   152 (to 8456)

2763         8152 LOAD_CONST              29 (False)
             8154 LOAD_DEREF               0 (self)
             8156 STORE_ATTR              34 (is_generating)

2764         8166 LOAD_GLOBAL             63 (NULL + hasattr)
             8178 LOAD_DEREF               0 (self)
             8180 LOAD_CONST              26 ('results_panel')
             8182 PRECALL                  2
             8186 CALL                     2
             8196 POP_JUMP_FORWARD_IF_FALSE    26 (to 8250)

2765         8198 LOAD_DEREF               0 (self)
             8200 LOAD_ATTR               36 (results_panel)
             8210 LOAD_METHOD             37 (set_generating_state)
             8232 LOAD_CONST              29 (False)
             8234 PRECALL                  1
             8238 CALL                     1
             8248 POP_TOP

2766     >>  8250 NOP

2767         8252 LOAD_DEREF               0 (self)
             8254 LOAD_ATTR               38 (main_btn)
             8264 LOAD_METHOD             40 (setEnabled)
             8286 LOAD_CONST              25 (True)
             8288 PRECALL                  1
             8292 CALL                     1
             8302 POP_TOP

2768         8304 LOAD_DEREF               0 (self)
             8306 LOAD_ATTR               38 (main_btn)
             8316 LOAD_METHOD             39 (setText)
             8338 LOAD_CONST              78 ('🚀 Bắt đầu tạo ảnh')
             8340 PRECALL                  1
             8344 CALL                     1
             8354 POP_TOP

2769         8356 LOAD_DEREF               0 (self)
             8358 LOAD_ATTR               36 (results_panel)
             8368 LOAD_ATTR               43 (progress_bar)
             8378 LOAD_METHOD             44 (setVisible)
             8400 LOAD_CONST              29 (False)
             8402 PRECALL                  1
             8406 CALL                     1
             8416 POP_TOP
             8418 JUMP_FORWARD            16 (to 8452)
         >>  8420 PUSH_EXC_INFO

2770         8422 LOAD_GLOBAL             96 (Exception)
             8434 CHECK_EXC_MATCH
             8436 POP_JUMP_FORWARD_IF_FALSE     3 (to 8444)
             8438 POP_TOP

2771         8440 POP_EXCEPT
             8442 JUMP_FORWARD             4 (to 8452)

2770     >>  8444 RERAISE                  0
         >>  8446 COPY                     3
             8448 POP_EXCEPT
             8450 RERAISE                  1

2772     >>  8452 LOAD_CONST               3 (None)
             8454 RETURN_VALUE

2761     >>  8456 JUMP_FORWARD            16 (to 8490)
         >>  8458 PUSH_EXC_INFO

2773         8460 LOAD_GLOBAL             96 (Exception)
             8472 CHECK_EXC_MATCH
             8474 POP_JUMP_FORWARD_IF_FALSE     3 (to 8482)
             8476 POP_TOP

2774         8478 POP_EXCEPT
             8480 JUMP_FORWARD             4 (to 8490)

2773     >>  8482 RERAISE                  0
         >>  8484 COPY                     3
             8486 POP_EXCEPT
             8488 RERAISE                  1
         >>  8490 JUMP_FORWARD            16 (to 8524)
         >>  8492 PUSH_EXC_INFO

2775         8494 LOAD_GLOBAL             96 (Exception)
             8506 CHECK_EXC_MATCH
             8508 POP_JUMP_FORWARD_IF_FALSE     3 (to 8516)
             8510 POP_TOP

2776         8512 POP_EXCEPT
             8514 JUMP_FORWARD             4 (to 8524)

2775     >>  8516 RERAISE                  0
         >>  8518 COPY                     3
             8520 POP_EXCEPT
             8522 RERAISE                  1

2779     >>  8524 NOP

2780         8526 LOAD_GLOBAL             63 (NULL + hasattr)
             8538 LOAD_DEREF               0 (self)
             8540 LOAD_ATTR               36 (results_panel)
             8550 LOAD_CONST              96 ('add_processing_task')
             8552 PRECALL                  2
             8556 CALL                     2
             8566 EXTENDED_ARG             1
             8568 POP_JUMP_FORWARD_IF_FALSE   258 (to 9086)

2781         8570 LOAD_CONST              66 ('s')
             8572 LOAD_DEREF               0 (self)
             8574 LOAD_ATTR               35 (generation_session_id)
             8584 FORMAT_VALUE             0
             8586 LOAD_CONST              97 ('_idx_')
             8588 BUILD_STRING             3
             8590 STORE_FAST              63 (ui_task_prefix)

2783         8592 LOAD_GLOBAL            109 (NULL + getattr)
             8604 LOAD_DEREF               0 (self)
             8606 LOAD_CONST              98 ('_regeneration_row_mode')
             8608 LOAD_CONST              29 (False)
             8610 PRECALL                  3
             8614 CALL                     3
             8624 STORE_FAST              64 (is_row_regen)

2784         8626 LOAD_GLOBAL            109 (NULL + getattr)
             8638 LOAD_DEREF               0 (self)
             8640 LOAD_CONST              99 ('_regeneration_rows_and_prompts')
             8642 BUILD_LIST               0
             8644 PRECALL                  3
             8648 CALL                     3
             8658 STORE_FAST              65 (rows_and_prompts_regen)

2786         8660 LOAD_GLOBAL            115 (NULL + enumerate)
             8672 LOAD_FAST                2 (prompts)
             8674 PRECALL                  1
             8678 CALL                     1
             8688 GET_ITER
         >>  8690 FOR_ITER               181 (to 9054)
             8692 UNPACK_SEQUENCE          2
             8696 STORE_FAST              42 (i)
             8698 STORE_FAST              66 (prompt)

2788         8700 LOAD_FAST               63 (ui_task_prefix)
             8702 FORMAT_VALUE             0
             8704 LOAD_FAST               42 (i)
             8706 FORMAT_VALUE             0
             8708 BUILD_STRING             2
             8710 STORE_FAST              67 (task_id)

2790         8712 LOAD_FAST               64 (is_row_regen)
             8714 POP_JUMP_FORWARD_IF_FALSE   139 (to 8994)
             8716 LOAD_FAST               42 (i)
             8718 LOAD_GLOBAL             15 (NULL + len)
             8730 LOAD_FAST               65 (rows_and_prompts_regen)
             8732 PRECALL                  1
             8736 CALL                     1
             8746 COMPARE_OP               0 (<)
             8752 POP_JUMP_FORWARD_IF_FALSE   120 (to 8994)

2792         8754 LOAD_FAST               65 (rows_and_prompts_regen)
             8756 LOAD_FAST               42 (i)
             8758 BINARY_SUBSCR
             8768 LOAD_CONST              17 (0)
             8770 BINARY_SUBSCR
             8780 STORE_FAST              68 (target_row)

2793         8782 LOAD_GLOBAL             63 (NULL + hasattr)
             8794 LOAD_DEREF               0 (self)
             8796 LOAD_ATTR               36 (results_panel)
             8806 LOAD_CONST             100 ('add_regeneration_processing_task')
             8808 PRECALL                  2
             8812 CALL                     2
             8822 POP_JUMP_FORWARD_IF_FALSE    55 (to 8934)

2794         8824 LOAD_DEREF               0 (self)
             8826 LOAD_ATTR               36 (results_panel)
             8836 LOAD_METHOD             87 (add_regeneration_processing_task)
             8858 LOAD_FAST               67 (task_id)
             8860 LOAD_FAST               66 (prompt)
             8862 LOAD_FAST               68 (target_row)
             8864 PRECALL                  3
             8868 CALL                     3
             8878 POP_TOP

2795         8880 LOAD_GLOBAL             43 (NULL + logging)
             8892 LOAD_ATTR               22 (info)
             8902 LOAD_CONST             101 ('[REGEN] Cập nhật hàng ')
             8904 LOAD_FAST               68 (target_row)
             8906 FORMAT_VALUE             0
             8908 LOAD_CONST             102 (' với task ')
             8910 LOAD_FAST               67 (task_id)
             8912 FORMAT_VALUE             0
             8914 BUILD_STRING             4
             8916 PRECALL                  1
             8920 CALL                     1
             8930 POP_TOP
             8932 JUMP_BACKWARD          122 (to 8690)

2797     >>  8934 LOAD_DEREF               0 (self)
             8936 LOAD_ATTR               36 (results_panel)
             8946 LOAD_METHOD             88 (add_processing_task)
             8968 LOAD_FAST               67 (task_id)
             8970 LOAD_FAST               66 (prompt)
             8972 LOAD_FAST               42 (i)
             8974 KW_NAMES               103
             8976 PRECALL                  3
             8980 CALL                     3
             8990 POP_TOP
             8992 JUMP_BACKWARD          152 (to 8690)

2800     >>  8994 LOAD_DEREF               0 (self)
             8996 LOAD_ATTR               36 (results_panel)
             9006 LOAD_METHOD             88 (add_processing_task)
             9028 LOAD_FAST               67 (task_id)
             9030 LOAD_FAST               66 (prompt)
             9032 LOAD_FAST               42 (i)
             9034 KW_NAMES               103
             9036 PRECALL                  3
             9040 CALL                     3
             9050 POP_TOP
             9052 JUMP_BACKWARD          182 (to 8690)

2803     >>  9054 LOAD_FAST               64 (is_row_regen)
             9056 POP_JUMP_FORWARD_IF_FALSE    14 (to 9086)

2804         9058 LOAD_CONST              29 (False)
             9060 LOAD_DEREF               0 (self)
             9062 STORE_ATTR              89 (_regeneration_row_mode)

2805         9072 BUILD_LIST               0
             9074 LOAD_DEREF               0 (self)
             9076 STORE_ATTR              90 (_regeneration_rows_and_prompts)
         >>  9086 JUMP_FORWARD            46 (to 9180)
         >>  9088 PUSH_EXC_INFO

2806         9090 LOAD_GLOBAL             96 (Exception)
             9102 CHECK_EXC_MATCH
             9104 POP_JUMP_FORWARD_IF_FALSE    33 (to 9172)
             9106 STORE_FAST              25 (e)

2807         9108 LOAD_GLOBAL             43 (NULL + logging)
             9120 LOAD_ATTR                4 (warning)
             9130 LOAD_CONST             104 ('⚠️ Error adding processing tasks to UI: ')
             9132 LOAD_FAST               25 (e)
             9134 FORMAT_VALUE             0
             9136 BUILD_STRING             2
             9138 PRECALL                  1
             9142 CALL                     1
             9152 POP_TOP
             9154 POP_EXCEPT
             9156 LOAD_CONST               3 (None)
             9158 STORE_FAST              25 (e)
             9160 DELETE_FAST             25 (e)
             9162 JUMP_FORWARD             8 (to 9180)
         >>  9164 LOAD_CONST               3 (None)
             9166 STORE_FAST              25 (e)
             9168 DELETE_FAST             25 (e)
             9170 RERAISE                  1

2806     >>  9172 RERAISE                  0
         >>  9174 COPY                     3
             9176 POP_EXCEPT
             9178 RERAISE                  1

2810     >>  9180 NOP

2811         9182 LOAD_CONST             105 ('bits')
             9184 LOAD_GLOBAL            104 (int)
             9196 LOAD_CONST             106 ('max_slots')
             9198 LOAD_GLOBAL            104 (int)
             9210 BUILD_TUPLE              4
             9212 LOAD_CONST             107 (<code object _bits_to_indices at 0x100b625b0, file "main_window_imagen.pyc", line 2811>)
             9214 MAKE_FUNCTION            4 (annotations)
             9216 STORE_FAST              69 (_bits_to_indices)

2817         9218 LOAD_GLOBAL            109 (NULL + getattr)
             9230 LOAD_DEREF               0 (self)
             9232 LOAD_CONST              42 ('max_character_slots')
             9234 LOAD_CONST              43 (10)
             9236 PRECALL                  3
             9240 CALL                     3
             9250 STORE_FAST              27 (max_slots_dbg)

2818         9252 LOAD_GLOBAL             43 (NULL + logging)
             9264 LOAD_ATTR               22 (info)
             9274 LOAD_CONST             108 ('===== FINAL PROMPTS (after name replacement) =====')
             9276 PRECALL                  1
             9280 CALL                     1
             9290 POP_TOP

2819         9292 LOAD_GLOBAL            115 (NULL + enumerate)
             9304 LOAD_GLOBAL            183 (NULL + zip)
             9316 LOAD_FAST                2 (prompts)
             9318 LOAD_FAST                8 (final_prompts)
             9320 LOAD_FAST               35 (attachments_by_index)
             9322 PRECALL                  3
             9326 CALL                     3
             9336 LOAD_CONST              18 (1)
             9338 KW_NAMES               109
             9340 PRECALL                  2
             9344 CALL                     2
             9354 GET_ITER
         >>  9356 FOR_ITER               116 (to 9590)
             9358 UNPACK_SEQUENCE          2
             9362 STORE_FAST              42 (i)
             9364 UNPACK_SEQUENCE          3
             9368 STORE_FAST              70 (orig_p)
             9370 STORE_FAST              71 (send_p)
             9372 STORE_FAST              72 (bits)

2820         9374 PUSH_NULL
             9376 LOAD_FAST               69 (_bits_to_indices)
             9378 LOAD_FAST               72 (bits)
             9380 LOAD_FAST               27 (max_slots_dbg)
             9382 PRECALL                  2
             9386 CALL                     2
             9396 STORE_FAST              73 (idxs)

2822         9398 LOAD_FAST               42 (i)
             9400 LOAD_CONST              18 (1)
             9402 BINARY_OP               10 (-)
             9406 LOAD_GLOBAL             15 (NULL + len)
             9418 LOAD_FAST               36 (attachments_order_by_index)
             9420 PRECALL                  1
             9424 CALL                     1
             9434 COMPARE_OP               0 (<)
             9440 POP_JUMP_FORWARD_IF_FALSE    11 (to 9464)
             9442 LOAD_FAST               36 (attachments_order_by_index)
             9444 LOAD_FAST               42 (i)
             9446 LOAD_CONST              18 (1)
             9448 BINARY_OP               10 (-)
             9452 BINARY_SUBSCR
             9462 JUMP_FORWARD             1 (to 9466)
         >>  9464 BUILD_LIST               0
         >>  9466 STORE_FAST              74 (ords)

2823         9468 LOAD_GLOBAL             43 (NULL + logging)
             9480 LOAD_ATTR               22 (info)
             9490 LOAD_CONST             110 ('[P')
             9492 LOAD_FAST               42 (i)
             9494 LOAD_CONST             111 ('03d')
             9496 FORMAT_VALUE             4 (with format)
             9498 LOAD_CONST             112 ('] attach=')
             9500 LOAD_FAST               73 (idxs)
             9502 FORMAT_VALUE             0
             9504 LOAD_CONST             113 (' order=')
             9506 LOAD_FAST               74 (ords)
             9508 FORMAT_VALUE             0
             9510 LOAD_CONST             114 (' | ORIG: ')
             9512 LOAD_FAST               70 (orig_p)
             9514 FORMAT_VALUE             0
             9516 BUILD_STRING             8
             9518 PRECALL                  1
             9522 CALL                     1
             9532 POP_TOP

2824         9534 LOAD_GLOBAL             43 (NULL + logging)
             9546 LOAD_ATTR               22 (info)
             9556 LOAD_CONST             110 ('[P')
             9558 LOAD_FAST               42 (i)
             9560 LOAD_CONST             111 ('03d')
             9562 FORMAT_VALUE             4 (with format)
             9564 LOAD_CONST             115 ('] SEND : ')
             9566 LOAD_FAST               71 (send_p)
             9568 FORMAT_VALUE             0
             9570 BUILD_STRING             4
             9572 PRECALL                  1
             9576 CALL                     1
             9586 POP_TOP
             9588 JUMP_BACKWARD          117 (to 9356)

2825     >>  9590 LOAD_GLOBAL             43 (NULL + logging)
             9602 LOAD_ATTR               22 (info)
             9612 LOAD_CONST             116 ('===== END FINAL PROMPTS =====')
             9614 PRECALL                  1
             9618 CALL                     1
             9628 POP_TOP
             9630 JUMP_FORWARD            16 (to 9664)
         >>  9632 PUSH_EXC_INFO

2826         9634 LOAD_GLOBAL             96 (Exception)
             9646 CHECK_EXC_MATCH
             9648 POP_JUMP_FORWARD_IF_FALSE     3 (to 9656)
             9650 POP_TOP

2827         9652 POP_EXCEPT
             9654 JUMP_FORWARD             4 (to 9664)

2826     >>  9656 RERAISE                  0
         >>  9658 COPY                     3
             9660 POP_EXCEPT
             9662 RERAISE                  1

2830     >>  9664 NOP

2831         9666 LOAD_DEREF               0 (self)
             9668 LOAD_ATTR                0 (prompts_edit)
             9678 LOAD_METHOD             92 (document)
             9700 PRECALL                  0
             9704 CALL                     0
             9714 STORE_FAST              75 (doc)

2832         9716 LOAD_FAST               75 (doc)
             9718 LOAD_METHOD             93 (begin)
             9740 PRECALL                  0
             9744 CALL                     0
             9754 STORE_FAST              76 (block)

2833         9756 LOAD_CONST              17 (0)
             9758 STORE_FAST              77 (i_non_empty)

2834         9760 LOAD_FAST               76 (block)
             9762 LOAD_METHOD             94 (isValid)
             9784 PRECALL                  0
             9788 CALL                     0
             9798 POP_JUMP_FORWARD_IF_FALSE   181 (to 10162)
             9800 LOAD_FAST               77 (i_non_empty)
             9802 LOAD_GLOBAL             15 (NULL + len)
             9814 LOAD_FAST               35 (attachments_by_index)
             9816 PRECALL                  1
             9820 CALL                     1
             9830 COMPARE_OP               0 (<)
             9836 POP_JUMP_FORWARD_IF_FALSE   162 (to 10162)

2835     >>  9838 LOAD_FAST               76 (block)
             9840 LOAD_METHOD             67 (text)
             9862 PRECALL                  0
             9866 CALL                     0
             9876 LOAD_METHOD              2 (strip)
             9898 PRECALL                  0
             9902 CALL                     0
             9912 STORE_FAST              78 (txt)

2836         9914 LOAD_FAST               78 (txt)
             9916 POP_JUMP_FORWARD_IF_FALSE    83 (to 10084)

2837         9918 NOP

2838         9920 LOAD_FAST               76 (block)
             9922 LOAD_METHOD             95 (setUserState)
             9944 LOAD_GLOBAL            105 (NULL + int)
             9956 LOAD_FAST               35 (attachments_by_index)
             9958 LOAD_FAST               77 (i_non_empty)
             9960 BINARY_SUBSCR
             9970 PRECALL                  1
             9974 CALL                     1
             9984 PRECALL                  1
             9988 CALL                     1
             9998 POP_TOP
            10000 JUMP_FORWARD            16 (to 10034)
         >> 10002 PUSH_EXC_INFO

2839        10004 LOAD_GLOBAL             96 (Exception)
            10016 CHECK_EXC_MATCH
            10018 POP_JUMP_FORWARD_IF_FALSE     3 (to 10026)
            10020 POP_TOP

2840        10022 POP_EXCEPT
            10024 JUMP_FORWARD             4 (to 10034)

2839     >> 10026 RERAISE                  0
         >> 10028 COPY                     3
            10030 POP_EXCEPT
            10032 RERAISE                  1

2841     >> 10034 LOAD_FAST               77 (i_non_empty)
            10036 LOAD_CONST              18 (1)
            10038 BINARY_OP               13 (+=)
            10042 STORE_FAST              77 (i_non_empty)

2842        10044 LOAD_FAST               76 (block)
            10046 LOAD_METHOD             96 (next)
            10068 PRECALL                  0
            10072 CALL                     0
            10082 STORE_FAST              76 (block)

2834     >> 10084 LOAD_FAST               76 (block)
            10086 LOAD_METHOD             94 (isValid)
            10108 PRECALL                  0
            10112 CALL                     0
            10122 POP_JUMP_FORWARD_IF_FALSE    19 (to 10162)
            10124 LOAD_FAST               77 (i_non_empty)
            10126 LOAD_GLOBAL             15 (NULL + len)
            10138 LOAD_FAST               35 (attachments_by_index)
            10140 PRECALL                  1
            10144 CALL                     1
            10154 COMPARE_OP               0 (<)
            10160 POP_JUMP_BACKWARD_IF_TRUE   162 (to 9838)

2843     >> 10162 LOAD_GLOBAL             63 (NULL + hasattr)
            10174 LOAD_DEREF               0 (self)
            10176 LOAD_ATTR                0 (prompts_edit)
            10186 LOAD_CONST             117 ('_attachmentArea')
            10188 PRECALL                  2
            10192 CALL                     2
            10202 POP_JUMP_FORWARD_IF_FALSE    30 (to 10264)

2844        10204 LOAD_DEREF               0 (self)
            10206 LOAD_ATTR                0 (prompts_edit)
            10216 LOAD_ATTR               97 (_attachmentArea)
            10226 LOAD_METHOD             98 (update)
            10248 PRECALL                  0
            10252 CALL                     0
            10262 POP_TOP
         >> 10264 JUMP_FORWARD            16 (to 10298)
         >> 10266 PUSH_EXC_INFO

2845        10268 LOAD_GLOBAL             96 (Exception)
            10280 CHECK_EXC_MATCH
            10282 POP_JUMP_FORWARD_IF_FALSE     3 (to 10290)
            10284 POP_TOP

2846        10286 POP_EXCEPT
            10288 JUMP_FORWARD             4 (to 10298)

2845     >> 10290 RERAISE                  0
         >> 10292 COPY                     3
            10294 POP_EXCEPT
            10296 RERAISE                  1

2849     >> 10298 LOAD_GLOBAL            143 (NULL + bool)
            10310 LOAD_FAST               26 (attachments_payload)
            10312 PRECALL                  1
            10316 CALL                     1
            10326 LOAD_DEREF               0 (self)
            10328 STORE_ATTR              99 (used_attachments_in_session)

2852        10338 LOAD_DEREF               0 (self)
            10340 LOAD_ATTR               18 (super_resolution_checkbox)
            10350 LOAD_METHOD             19 (isChecked)
            10372 PRECALL                  0
            10376 CALL                     0
            10386 STORE_FAST              79 (super_res)

2853        10388 LOAD_CONST               3 (None)
            10390 STORE_FAST              80 (ws_url)

2854        10392 LOAD_FAST               26 (attachments_payload)
            10394 POP_JUMP_FORWARD_IF_FALSE   225 (to 10846)

2856        10396 NOP

2857        10398 LOAD_GLOBAL             63 (NULL + hasattr)
            10410 LOAD_DEREF               0 (self)
            10412 LOAD_CONST             118 ('super_resolution_checkbox')
            10414 PRECALL                  2
            10418 CALL                     2
            10428 POP_JUMP_FORWARD_IF_FALSE    71 (to 10572)
            10430 LOAD_DEREF               0 (self)
            10432 LOAD_ATTR               18 (super_resolution_checkbox)
            10442 LOAD_METHOD             19 (isChecked)
            10464 PRECALL                  0
            10468 CALL                     0
            10478 POP_JUMP_FORWARD_IF_FALSE    46 (to 10572)

2858        10480 LOAD_DEREF               0 (self)
            10482 LOAD_ATTR               18 (super_resolution_checkbox)
            10492 LOAD_METHOD            100 (setChecked)
            10514 LOAD_CONST              29 (False)
            10516 PRECALL                  1
            10520 CALL                     1
            10530 POP_TOP

2859        10532 LOAD_GLOBAL             43 (NULL + logging)
            10544 LOAD_ATTR               22 (info)
            10554 LOAD_CONST             119 ('⚙️ Tắt chế độ ảnh siêu nét vì đang dùng ảnh đính kèm')
            10556 PRECALL                  1
            10560 CALL                     1
            10570 POP_TOP
         >> 10572 JUMP_FORWARD            16 (to 10606)
         >> 10574 PUSH_EXC_INFO

2860        10576 LOAD_GLOBAL             96 (Exception)
            10588 CHECK_EXC_MATCH
            10590 POP_JUMP_FORWARD_IF_FALSE     3 (to 10598)
            10592 POP_TOP

2861        10594 POP_EXCEPT
            10596 JUMP_FORWARD             4 (to 10606)

2860     >> 10598 RERAISE                  0
         >> 10600 COPY                     3
            10602 POP_EXCEPT
            10604 RERAISE                  1

2863     >> 10606 NOP

2864        10608 LOAD_GLOBAL            203 (NULL + get_websocket_url)
            10620 PRECALL                  0
            10624 CALL                     0
            10634 STORE_FAST              81 (env_ws_url)
            10636 JUMP_FORWARD            18 (to 10674)
         >> 10638 PUSH_EXC_INFO

2865        10640 LOAD_GLOBAL             96 (Exception)
            10652 CHECK_EXC_MATCH
            10654 POP_JUMP_FORWARD_IF_FALSE     5 (to 10666)
            10656 POP_TOP

2866        10658 LOAD_CONST               3 (None)
            10660 STORE_FAST              81 (env_ws_url)
            10662 POP_EXCEPT
            10664 JUMP_FORWARD             4 (to 10674)

2865     >> 10666 RERAISE                  0
         >> 10668 COPY                     3
            10670 POP_EXCEPT
            10672 RERAISE                  1

2867     >> 10674 LOAD_FAST               81 (env_ws_url)
            10676 POP_JUMP_FORWARD_IF_FALSE    47 (to 10772)
            10678 LOAD_FAST               81 (env_ws_url)
            10680 LOAD_METHOD            102 (startswith)
            10702 LOAD_CONST             120 ('wss://v2.chichbong.me')
            10704 PRECALL                  1
            10708 CALL                     1
            10718 POP_JUMP_FORWARD_IF_TRUE    26 (to 10772)

2868        10720 LOAD_GLOBAL             43 (NULL + logging)
            10732 LOAD_ATTR               22 (info)
            10742 LOAD_CONST             121 ('📡 Using ENV WebSocket for attachments: ')
            10744 LOAD_FAST               81 (env_ws_url)
            10746 FORMAT_VALUE             0
            10748 BUILD_STRING             2
            10750 PRECALL                  1
            10754 CALL                     1
            10764 POP_TOP

2869        10766 LOAD_FAST               81 (env_ws_url)
            10768 STORE_FAST              80 (ws_url)
            10770 JUMP_FORWARD            53 (to 10878)

2871     >> 10772 LOAD_GLOBAL            207 (NULL + get_imagen_websocket_url)
            10784 LOAD_CONST              29 (False)
            10786 KW_NAMES               122
            10788 PRECALL                  1
            10792 CALL                     1
            10802 STORE_FAST              80 (ws_url)

2872        10804 LOAD_GLOBAL             43 (NULL + logging)
            10816 LOAD_ATTR                4 (warning)
            10826 LOAD_CONST             123 ('⚠️ Attachments detected nhưng đang dùng production WSS. Khuyến nghị chạy server local và set IMAGEN4_WS_HOST/PORT')
            10828 PRECALL                  1
            10832 CALL                     1
            10842 POP_TOP
            10844 JUMP_FORWARD            16 (to 10878)

2874     >> 10846 LOAD_GLOBAL            207 (NULL + get_imagen_websocket_url)
            10858 LOAD_FAST               79 (super_res)
            10860 KW_NAMES               122
            10862 PRECALL                  1
            10866 CALL                     1
            10876 STORE_FAST              80 (ws_url)

2877     >> 10878 LOAD_GLOBAL            209 (NULL + SimpleWebSocketImageGenerator)

2878        10890 LOAD_FAST                3 (license_key)

2879        10892 LOAD_FAST               80 (ws_url)

2877        10894 KW_NAMES               124
            10896 PRECALL                  2
            10900 CALL                     2
            10910 STORE_FAST              82 (thread_image_generator)

2881        10912 LOAD_GLOBAL             43 (NULL + logging)
            10924 LOAD_ATTR               22 (info)
            10934 LOAD_CONST             125 ('🌐 Using Simple WebSocket mode for generation: ')
            10936 LOAD_FAST               80 (ws_url)
            10938 FORMAT_VALUE             0
            10940 BUILD_STRING             2
            10942 PRECALL                  1
            10946 CALL                     1
            10956 POP_TOP

2884        10958 LOAD_CONST              29 (False)
            10960 STORE_FAST              83 (use_legacy_model)

2885        10962 NOP

2886        10964 LOAD_GLOBAL            109 (NULL + getattr)
            10976 LOAD_DEREF               0 (self)
            10978 LOAD_CONST             126 ('legacy_model_checkbox')
            10980 LOAD_CONST               3 (None)
            10982 PRECALL                  3
            10986 CALL                     3
            10996 POP_JUMP_FORWARD_IF_FALSE    47 (to 11092)
            10998 LOAD_DEREF               0 (self)
            11000 LOAD_ATTR              105 (legacy_model_checkbox)
            11010 LOAD_METHOD             19 (isChecked)
            11032 PRECALL                  0
            11036 CALL                     0
            11046 POP_JUMP_FORWARD_IF_FALSE    22 (to 11092)

2887        11048 LOAD_CONST              25 (True)
            11050 STORE_FAST              83 (use_legacy_model)

2888        11052 LOAD_GLOBAL             43 (NULL + logging)
            11064 LOAD_ATTR               22 (info)
            11074 LOAD_CONST             127 ('🧩 Đang bật chế độ sử dụng model cũ (IMAGEN_3_5) cho phiên không đính kèm nhân vật')
            11076 PRECALL                  1
            11080 CALL                     1
            11090 POP_TOP
         >> 11092 JUMP_FORWARD            46 (to 11186)
         >> 11094 PUSH_EXC_INFO

2889        11096 LOAD_GLOBAL             96 (Exception)
            11108 CHECK_EXC_MATCH
            11110 POP_JUMP_FORWARD_IF_FALSE    33 (to 11178)
            11112 STORE_FAST              84 (_e)

2890        11114 LOAD_GLOBAL             43 (NULL + logging)
            11126 LOAD_ATTR                4 (warning)
            11136 LOAD_CONST             128 ('Lỗi khi đọc trạng thái legacy_model_checkbox: ')
            11138 LOAD_FAST               84 (_e)
            11140 FORMAT_VALUE             0
            11142 BUILD_STRING             2
            11144 PRECALL                  1
            11148 CALL                     1
            11158 POP_TOP
            11160 POP_EXCEPT
            11162 LOAD_CONST               3 (None)
            11164 STORE_FAST              84 (_e)
            11166 DELETE_FAST             84 (_e)
            11168 JUMP_FORWARD             8 (to 11186)
         >> 11170 LOAD_CONST               3 (None)
            11172 STORE_FAST              84 (_e)
            11174 DELETE_FAST             84 (_e)
            11176 RERAISE                  1

2889     >> 11178 RERAISE                  0
         >> 11180 COPY                     3
            11182 POP_EXCEPT
            11184 RERAISE                  1

2893     >> 11186 LOAD_CONST               3 (None)
            11188 STORE_FAST              85 (image_model_name)

2894        11190 NOP

2895        11192 LOAD_FAST               83 (use_legacy_model)
            11194 POP_JUMP_FORWARD_IF_TRUE    64 (to 11324)
            11196 LOAD_GLOBAL            109 (NULL + getattr)
            11208 LOAD_DEREF               0 (self)
            11210 LOAD_CONST             129 ('banana2_model_checkbox')
            11212 LOAD_CONST               3 (None)
            11214 PRECALL                  3
            11218 CALL                     3
            11228 POP_JUMP_FORWARD_IF_FALSE    47 (to 11324)
            11230 LOAD_DEREF               0 (self)
            11232 LOAD_ATTR              106 (banana2_model_checkbox)
            11242 LOAD_METHOD             19 (isChecked)
            11264 PRECALL                  0
            11268 CALL                     0
            11278 POP_JUMP_FORWARD_IF_FALSE    22 (to 11324)

2896        11280 LOAD_CONST             130 ('NARWHAL')
            11282 STORE_FAST              85 (image_model_name)

2897        11284 LOAD_GLOBAL             43 (NULL + logging)
            11296 LOAD_ATTR               22 (info)
            11306 LOAD_CONST             131 ('🍌 Đang chọn model Banana 2 (NARWHAL) cho phiên này')
            11308 PRECALL                  1
            11312 CALL                     1
            11322 POP_TOP
         >> 11324 JUMP_FORWARD            18 (to 11362)
         >> 11326 PUSH_EXC_INFO

2898        11328 LOAD_GLOBAL             96 (Exception)
            11340 CHECK_EXC_MATCH
            11342 POP_JUMP_FORWARD_IF_FALSE     5 (to 11354)
            11344 POP_TOP

2899        11346 LOAD_CONST               3 (None)
            11348 STORE_FAST              85 (image_model_name)
            11350 POP_EXCEPT
            11352 JUMP_FORWARD             4 (to 11362)

2898     >> 11354 RERAISE                  0
         >> 11356 COPY                     3
            11358 POP_EXCEPT
            11360 RERAISE                  1

2902     >> 11362 LOAD_CONST               3 (None)
            11364 STORE_FAST              86 (upscale_mode)

2903        11366 NOP

2904        11368 LOAD_GLOBAL            109 (NULL + getattr)
            11380 LOAD_DEREF               0 (self)
            11382 LOAD_CONST             132 ('upscale_2k_checkbox')
            11384 LOAD_CONST               3 (None)
            11386 PRECALL                  3
            11390 CALL                     3
            11400 POP_JUMP_FORWARD_IF_FALSE    28 (to 11458)
            11402 LOAD_DEREF               0 (self)
            11404 LOAD_ATTR              107 (upscale_2k_checkbox)
            11414 LOAD_METHOD             19 (isChecked)
            11436 PRECALL                  0
            11440 CALL                     0
            11450 POP_JUMP_FORWARD_IF_FALSE     3 (to 11458)

2905        11452 LOAD_CONST             133 ('2k')
            11454 STORE_FAST              86 (upscale_mode)
            11456 JUMP_FORWARD            44 (to 11546)

2906     >> 11458 LOAD_GLOBAL            109 (NULL + getattr)
            11470 LOAD_DEREF               0 (self)
            11472 LOAD_CONST             134 ('upscale_4k_checkbox')
            11474 LOAD_CONST               3 (None)
            11476 PRECALL                  3
            11480 CALL                     3
            11490 POP_JUMP_FORWARD_IF_FALSE    27 (to 11546)
            11492 LOAD_DEREF               0 (self)
            11494 LOAD_ATTR              108 (upscale_4k_checkbox)
            11504 LOAD_METHOD             19 (isChecked)
            11526 PRECALL                  0
            11530 CALL                     0
            11540 POP_JUMP_FORWARD_IF_FALSE     2 (to 11546)

2907        11542 LOAD_CONST             135 ('4k')
            11544 STORE_FAST              86 (upscale_mode)

2908     >> 11546 LOAD_GLOBAL             43 (NULL + logging)
            11558 LOAD_ATTR               22 (info)
            11568 LOAD_CONST             136 ('🖼️ Upscale mode for this session: ')
            11570 LOAD_FAST               86 (upscale_mode)
            11572 FORMAT_VALUE             0
            11574 BUILD_STRING             2
            11576 PRECALL                  1
            11580 CALL                     1
            11590 POP_TOP
            11592 JUMP_FORWARD            18 (to 11630)
         >> 11594 PUSH_EXC_INFO

2909        11596 LOAD_GLOBAL             96 (Exception)
            11608 CHECK_EXC_MATCH
            11610 POP_JUMP_FORWARD_IF_FALSE     5 (to 11622)
            11612 POP_TOP

2910        11614 LOAD_CONST               3 (None)
            11616 STORE_FAST              86 (upscale_mode)
            11618 POP_EXCEPT
            11620 JUMP_FORWARD             4 (to 11630)

2909     >> 11622 RERAISE                  0
         >> 11624 COPY                     3
            11626 POP_EXCEPT
            11628 RERAISE                  1

2912     >> 11630 LOAD_GLOBAL            219 (NULL + ImageGenerationThread)

2913        11642 LOAD_FAST               82 (thread_image_generator)

2914        11644 LOAD_FAST                8 (final_prompts)

2915        11646 LOAD_FAST                6 (output_dir)

2916        11648 LOAD_FAST                5 (aspect_ratio)

2917        11650 LOAD_FAST               11 (seed)

2918        11652 LOAD_DEREF               0 (self)
            11654 LOAD_ATTR               35 (generation_session_id)

2919        11664 LOAD_FAST                2 (prompts)

2920        11666 LOAD_GLOBAL            109 (NULL + getattr)
            11678 LOAD_DEREF               0 (self)
            11680 LOAD_CONST             137 ('regeneration_task_mapping')
            11682 LOAD_CONST               3 (None)
            11684 PRECALL                  3
            11688 CALL                     3

2921        11698 LOAD_FAST               26 (attachments_payload)

2922        11700 LOAD_FAST               35 (attachments_by_index)

2923        11702 LOAD_FAST               36 (attachments_order_by_index)

2924        11704 LOAD_FAST               83 (use_legacy_model)

2925        11706 LOAD_FAST               85 (image_model_name)

2926        11708 LOAD_FAST               86 (upscale_mode)

2912        11710 KW_NAMES               138
            11712 PRECALL                 14
            11716 CALL                    14
            11726 STORE_FAST              87 (new_thread)

2930        11728 LOAD_FAST               87 (new_thread)
            11730 LOAD_ATTR              110 (progress_updated)
            11740 LOAD_METHOD            111 (connect)
            11762 LOAD_DEREF               0 (self)
            11764 LOAD_ATTR              112 (update_progress)
            11774 PRECALL                  1
            11778 CALL                     1
            11788 POP_TOP

2931        11790 LOAD_FAST               87 (new_thread)
            11792 LOAD_ATTR              113 (status_updated)
            11802 LOAD_METHOD            111 (connect)
            11824 LOAD_DEREF               0 (self)
            11826 LOAD_ATTR              114 (update_status)
            11836 PRECALL                  1
            11840 CALL                     1
            11850 POP_TOP

2932        11852 LOAD_FAST               87 (new_thread)
            11854 LOAD_ATTR              115 (finished)
            11864 LOAD_METHOD            111 (connect)
            11886 LOAD_DEREF               0 (self)
            11888 LOAD_ATTR              116 (generation_finished)
            11898 PRECALL                  1
            11902 CALL                     1
            11912 POP_TOP

2934        11914 LOAD_FAST               87 (new_thread)
            11916 LOAD_ATTR              117 (task_status_updated)
            11926 LOAD_METHOD            111 (connect)
            11948 LOAD_DEREF               0 (self)
            11950 LOAD_ATTR              118 (on_task_status_updated)
            11960 PRECALL                  1
            11964 CALL                     1
            11974 POP_TOP

2935        11976 LOAD_FAST               87 (new_thread)
            11978 LOAD_ATTR              119 (task_result_updated)
            11988 LOAD_METHOD            111 (connect)
            12010 LOAD_DEREF               0 (self)
            12012 LOAD_ATTR              120 (on_task_result_updated)
            12022 PRECALL                  1
            12026 CALL                     1
            12036 POP_TOP

2937        12038 NOP

2938        12040 LOAD_DEREF               0 (self)
            12042 LOAD_ATTR               35 (generation_session_id)
            12052 LOAD_FAST               87 (new_thread)
            12054 STORE_ATTR             121 (session_id)
            12064 JUMP_FORWARD            16 (to 12098)
         >> 12066 PUSH_EXC_INFO

2939        12068 LOAD_GLOBAL             96 (Exception)
            12080 CHECK_EXC_MATCH
            12082 POP_JUMP_FORWARD_IF_FALSE     3 (to 12090)
            12084 POP_TOP

2940        12086 POP_EXCEPT
            12088 JUMP_FORWARD             4 (to 12098)

2939     >> 12090 RERAISE                  0
         >> 12092 COPY                     3
            12094 POP_EXCEPT
            12096 RERAISE                  1

2943     >> 12098 LOAD_FAST               26 (attachments_payload)
            12100 POP_JUMP_FORWARD_IF_FALSE   184 (to 12470)
            12102 LOAD_GLOBAL             63 (NULL + hasattr)
            12114 LOAD_DEREF               0 (self)
            12116 LOAD_ATTR               36 (results_panel)
            12126 LOAD_CONST             139 ('update_processing_status')
            12128 PRECALL                  2
            12132 CALL                     2
            12142 POP_JUMP_FORWARD_IF_FALSE   163 (to 12470)

2944        12144 NOP

2945        12146 LOAD_CONST              66 ('s')
            12148 LOAD_DEREF               0 (self)
            12150 LOAD_ATTR               35 (generation_session_id)
            12160 FORMAT_VALUE             0
            12162 LOAD_CONST              97 ('_idx_')
            12164 BUILD_STRING             3
            12166 STORE_FAST              63 (ui_task_prefix)

2946        12168 LOAD_GLOBAL            113 (NULL + range)
            12180 LOAD_GLOBAL             15 (NULL + len)
            12192 LOAD_FAST                2 (prompts)
            12194 PRECALL                  1
            12198 CALL                     1
            12208 PRECALL                  1
            12212 CALL                     1
            12222 GET_ITER
         >> 12224 FOR_ITER                38 (to 12302)
            12226 STORE_FAST              42 (i)

2947        12228 LOAD_FAST               63 (ui_task_prefix)
            12230 FORMAT_VALUE             0
            12232 LOAD_FAST               42 (i)
            12234 FORMAT_VALUE             0
            12236 BUILD_STRING             2
            12238 STORE_FAST              88 (task_id_ui)

2948        12240 LOAD_DEREF               0 (self)
            12242 LOAD_ATTR               36 (results_panel)
            12252 LOAD_METHOD            122 (update_processing_status)

2949        12274 LOAD_FAST               88 (task_id_ui)

2950        12276 LOAD_CONST             140 ('Đang tải ảnh...')

2951        12278 LOAD_CONST               3 (None)

2952        12280 LOAD_CONST             141 ('uploading')

2948        12282 KW_NAMES               142
            12284 PRECALL                  4
            12288 CALL                     4
            12298 POP_TOP
            12300 JUMP_BACKWARD           39 (to 12224)

2954     >> 12302 LOAD_GLOBAL             43 (NULL + logging)
            12314 LOAD_ATTR               22 (info)
            12324 LOAD_CONST             143 ('[UPLOAD] Set uploading status for ')
            12326 LOAD_GLOBAL             15 (NULL + len)
            12338 LOAD_FAST                2 (prompts)
            12340 PRECALL                  1
            12344 CALL                     1
            12354 FORMAT_VALUE             0
            12356 LOAD_CONST             144 (' tasks with attachments')
            12358 BUILD_STRING             3
            12360 PRECALL                  1
            12364 CALL                     1
            12374 POP_TOP
            12376 JUMP_FORWARD            46 (to 12470)
         >> 12378 PUSH_EXC_INFO

2955        12380 LOAD_GLOBAL             96 (Exception)
            12392 CHECK_EXC_MATCH
            12394 POP_JUMP_FORWARD_IF_FALSE    33 (to 12462)
            12396 STORE_FAST              25 (e)

2956        12398 LOAD_GLOBAL             43 (NULL + logging)
            12410 LOAD_ATTR                4 (warning)
            12420 LOAD_CONST             145 ('⚠️ Error setting uploading status: ')
            12422 LOAD_FAST               25 (e)
            12424 FORMAT_VALUE             0
            12426 BUILD_STRING             2
            12428 PRECALL                  1
            12432 CALL                     1
            12442 POP_TOP
            12444 POP_EXCEPT
            12446 LOAD_CONST               3 (None)
            12448 STORE_FAST              25 (e)
            12450 DELETE_FAST             25 (e)
            12452 JUMP_FORWARD             8 (to 12470)
         >> 12454 LOAD_CONST               3 (None)
            12456 STORE_FAST              25 (e)
            12458 DELETE_FAST             25 (e)
            12460 RERAISE                  1

2955     >> 12462 RERAISE                  0
         >> 12464 COPY                     3
            12466 POP_EXCEPT
            12468 RERAISE                  1

2959     >> 12470 LOAD_DEREF               0 (self)
            12472 LOAD_ATTR               50 (generation_threads)
            12482 LOAD_METHOD             58 (append)
            12504 LOAD_FAST               87 (new_thread)
            12506 PRECALL                  1
            12510 CALL                     1
            12520 POP_TOP

2960        12522 LOAD_FAST               87 (new_thread)
            12524 LOAD_METHOD            123 (start)
            12546 PRECALL                  0
            12550 CALL                     0
            12560 POP_TOP

2962        12562 LOAD_GLOBAL             43 (NULL + logging)
            12574 LOAD_ATTR               22 (info)
            12584 LOAD_CONST             146 ('Started WebSocket generation with ')
            12586 LOAD_GLOBAL             15 (NULL + len)
            12598 LOAD_FAST                2 (prompts)
            12600 PRECALL                  1
            12604 CALL                     1
            12614 FORMAT_VALUE             0
            12616 LOAD_CONST              15 (' prompts')
            12618 BUILD_STRING             3
            12620 PRECALL                  1
            12624 CALL                     1
            12634 POP_TOP
            12636 LOAD_CONST               3 (None)
            12638 RETURN_VALUE
         >> 12640 PUSH_EXC_INFO

2964        12642 LOAD_GLOBAL             96 (Exception)
            12654 CHECK_EXC_MATCH
            12656 POP_JUMP_FORWARD_IF_FALSE    61 (to 12780)
            12658 STORE_FAST              25 (e)

2965        12660 LOAD_GLOBAL             43 (NULL + logging)
            12672 LOAD_ATTR               65 (error)
            12682 LOAD_CONST             147 ('Error starting generation: ')
            12684 LOAD_FAST               25 (e)
            12686 FORMAT_VALUE             0
            12688 BUILD_STRING             2
            12690 LOAD_CONST              25 (True)
            12692 KW_NAMES               148
            12694 PRECALL                  2
            12698 CALL                     2
            12708 POP_TOP

2966        12710 LOAD_GLOBAL              7 (NULL + QMessageBox)
            12722 LOAD_ATTR               76 (critical)
            12732 LOAD_DEREF               0 (self)
            12734 LOAD_CONST               1 ('Lỗi')
            12736 LOAD_CONST             149 ('Lỗi khi bắt đầu tạo ảnh: ')
            12738 LOAD_FAST               25 (e)
            12740 FORMAT_VALUE             0
            12742 BUILD_STRING             2
            12744 PRECALL                  3
            12748 CALL                     3
            12758 POP_TOP
            12760 POP_EXCEPT
            12762 LOAD_CONST               3 (None)
            12764 STORE_FAST              25 (e)
            12766 DELETE_FAST             25 (e)
            12768 LOAD_CONST               3 (None)
            12770 RETURN_VALUE
         >> 12772 LOAD_CONST               3 (None)
            12774 STORE_FAST              25 (e)
            12776 DELETE_FAST             25 (e)
            12778 RERAISE                  1

2964     >> 12780 RERAISE                  0
         >> 12782 COPY                     3
            12784 POP_EXCEPT
            12786 RERAISE                  1
ExceptionTable:
  24 to 156 -> 12640 [0]
  162 to 270 -> 12640 [0]
  276 to 342 -> 12640 [0]
  348 to 448 -> 12640 [0]
  454 to 1082 -> 12640 [0]
  1088 to 2212 -> 12640 [0]
  2216 to 2306 -> 2310 [0]
  2308 to 2308 -> 12640 [0]
  2310 to 2328 -> 2336 [1] lasti
  2330 to 2332 -> 12640 [0]
  2334 to 2334 -> 2336 [1] lasti
  2336 to 2636 -> 12640 [0]
  2640 to 3044 -> 3410 [0]
  3046 to 3186 -> 3214 [1] lasti
  3190 to 3212 -> 3410 [0]
  3214 to 3220 -> 3222 [3] lasti
  3222 to 3226 -> 3410 [0]
  3228 to 3228 -> 3222 [3] lasti
  3230 to 3284 -> 3410 [0]
  3288 to 3352 -> 3356 [0]
  3354 to 3354 -> 3410 [0]
  3356 to 3378 -> 3386 [1] lasti
  3380 to 3382 -> 3410 [0]
  3384 to 3384 -> 3386 [1] lasti
  3386 to 3406 -> 3410 [0]
  3408 to 3408 -> 12640 [0]
  3410 to 3428 -> 3496 [1] lasti
  3430 to 3474 -> 3486 [1] lasti
  3476 to 3484 -> 12640 [0]
  3486 to 3494 -> 3496 [1] lasti
  3496 to 3568 -> 12640 [0]
  3572 to 3666 -> 4514 [0]
  3670 to 3742 -> 4440 [0]
  3746 to 3894 -> 3898 [1]
  3896 to 3896 -> 4440 [0]
  3898 to 3920 -> 3928 [2] lasti
  3922 to 3924 -> 4440 [0]
  3926 to 3926 -> 3928 [2] lasti
  3928 to 3936 -> 4440 [0]
  3940 to 4038 -> 4042 [1]
  4040 to 4040 -> 4440 [0]
  4042 to 4064 -> 4072 [2] lasti
  4066 to 4068 -> 4440 [0]
  4070 to 4070 -> 4072 [2] lasti
  4072 to 4080 -> 4440 [0]
  4084 to 4176 -> 4180 [1]
  4178 to 4178 -> 4440 [0]
  4180 to 4202 -> 4210 [2] lasti
  4204 to 4206 -> 4440 [0]
  4208 to 4208 -> 4210 [2] lasti
  4210 to 4252 -> 4440 [0]
  4256 to 4324 -> 4328 [1]
  4326 to 4326 -> 4440 [0]
  4328 to 4350 -> 4358 [2] lasti
  4352 to 4354 -> 4440 [0]
  4356 to 4356 -> 4358 [2] lasti
  4358 to 4436 -> 4440 [0]
  4438 to 4438 -> 4514 [0]
  4440 to 4458 -> 4466 [1] lasti
  4460 to 4462 -> 4514 [0]
  4464 to 4464 -> 4466 [1] lasti
  4466 to 4510 -> 4514 [0]
  4512 to 4512 -> 12640 [0]
  4514 to 4532 -> 4540 [1] lasti
  4534 to 4536 -> 12640 [0]
  4538 to 4538 -> 4540 [1] lasti
  4540 to 4648 -> 12640 [0]
  4652 to 4664 -> 4668 [0]
  4666 to 4666 -> 12640 [0]
  4668 to 4686 -> 4694 [1] lasti
  4688 to 4690 -> 12640 [0]
  4692 to 4692 -> 4694 [1] lasti
  4694 to 4702 -> 12640 [0]
  4708 to 4726 -> 4730 [0]
  4728 to 4728 -> 8492 [0]
  4730 to 4752 -> 4760 [1] lasti
  4754 to 4756 -> 8492 [0]
  4758 to 4758 -> 4760 [1] lasti
  4760 to 4890 -> 8492 [0]
  4894 to 5324 -> 5858 [0]
  5328 to 5516 -> 5520 [0]
  5518 to 5518 -> 5858 [0]
  5520 to 5538 -> 5546 [1] lasti
  5540 to 5542 -> 5858 [0]
  5544 to 5544 -> 5546 [1] lasti
  5546 to 5648 -> 5858 [0]
  5652 to 5816 -> 5820 [0]
  5818 to 5818 -> 5858 [0]
  5820 to 5838 -> 5846 [1] lasti
  5840 to 5842 -> 5858 [0]
  5844 to 5844 -> 5846 [1] lasti
  5846 to 5850 -> 5858 [0]
  5856 to 5856 -> 8492 [0]
  5858 to 5876 -> 5884 [1] lasti
  5878 to 5880 -> 8492 [0]
  5882 to 5882 -> 5884 [1] lasti
  5884 to 5888 -> 8492 [0]
  5892 to 6122 -> 6126 [0]
  6124 to 6124 -> 8492 [0]
  6126 to 6144 -> 6152 [1] lasti
  6146 to 6148 -> 8492 [0]
  6150 to 6150 -> 6152 [1] lasti
  6152 to 6156 -> 8492 [0]
  6160 to 6654 -> 7174 [0]
  6658 to 6832 -> 6836 [0]
  6834 to 6834 -> 7174 [0]
  6836 to 6854 -> 6862 [1] lasti
  6856 to 6858 -> 7174 [0]
  6860 to 6860 -> 6862 [1] lasti
  6862 to 6964 -> 7174 [0]
  6968 to 7132 -> 7136 [0]
  7134 to 7134 -> 7174 [0]
  7136 to 7154 -> 7162 [1] lasti
  7156 to 7158 -> 7174 [0]
  7160 to 7160 -> 7162 [1] lasti
  7162 to 7166 -> 7174 [0]
  7172 to 7172 -> 8492 [0]
  7174 to 7192 -> 7200 [1] lasti
  7194 to 7196 -> 8492 [0]
  7198 to 7198 -> 7200 [1] lasti
  7200 to 7204 -> 8492 [0]
  7208 to 7362 -> 7882 [0]
  7366 to 7540 -> 7544 [0]
  7542 to 7542 -> 7882 [0]
  7544 to 7562 -> 7570 [1] lasti
  7564 to 7566 -> 7882 [0]
  7568 to 7568 -> 7570 [1] lasti
  7570 to 7672 -> 7882 [0]
  7676 to 7840 -> 7844 [0]
  7842 to 7842 -> 7882 [0]
  7844 to 7862 -> 7870 [1] lasti
  7864 to 7866 -> 7882 [0]
  7868 to 7868 -> 7870 [1] lasti
  7870 to 7874 -> 7882 [0]
  7880 to 7880 -> 8492 [0]
  7882 to 7900 -> 7908 [1] lasti
  7902 to 7904 -> 8492 [0]
  7906 to 7906 -> 7908 [1] lasti
  7908 to 7912 -> 8492 [0]
  7916 to 7916 -> 8492 [0]
  7918 to 7936 -> 7944 [1] lasti
  7938 to 7940 -> 8492 [0]
  7942 to 7942 -> 7944 [1] lasti
  7944 to 7996 -> 8492 [0]
  8000 to 8248 -> 8458 [0]
  8252 to 8416 -> 8420 [0]
  8418 to 8418 -> 8458 [0]
  8420 to 8438 -> 8446 [1] lasti
  8440 to 8442 -> 8458 [0]
  8444 to 8444 -> 8446 [1] lasti
  8446 to 8450 -> 8458 [0]
  8456 to 8456 -> 8492 [0]
  8458 to 8476 -> 8484 [1] lasti
  8478 to 8480 -> 8492 [0]
  8482 to 8482 -> 8484 [1] lasti
  8484 to 8488 -> 8492 [0]
  8490 to 8490 -> 12640 [0]
  8492 to 8510 -> 8518 [1] lasti
  8512 to 8514 -> 12640 [0]
  8516 to 8516 -> 8518 [1] lasti
  8518 to 8522 -> 12640 [0]
  8526 to 9084 -> 9088 [0]
  9086 to 9086 -> 12640 [0]
  9088 to 9106 -> 9174 [1] lasti
  9108 to 9152 -> 9164 [1] lasti
  9154 to 9162 -> 12640 [0]
  9164 to 9172 -> 9174 [1] lasti
  9174 to 9178 -> 12640 [0]
  9182 to 9628 -> 9632 [0]
  9630 to 9630 -> 12640 [0]
  9632 to 9650 -> 9658 [1] lasti
  9652 to 9654 -> 12640 [0]
  9656 to 9656 -> 9658 [1] lasti
  9658 to 9662 -> 12640 [0]
  9666 to 9916 -> 10266 [0]
  9920 to 9998 -> 10002 [0]
  10000 to 10000 -> 10266 [0]
  10002 to 10020 -> 10028 [1] lasti
  10022 to 10024 -> 10266 [0]
  10026 to 10026 -> 10028 [1] lasti
  10028 to 10262 -> 10266 [0]
  10264 to 10264 -> 12640 [0]
  10266 to 10284 -> 10292 [1] lasti
  10286 to 10288 -> 12640 [0]
  10290 to 10290 -> 10292 [1] lasti
  10292 to 10394 -> 12640 [0]
  10398 to 10570 -> 10574 [0]
  10572 to 10572 -> 12640 [0]
  10574 to 10592 -> 10600 [1] lasti
  10594 to 10596 -> 12640 [0]
  10598 to 10598 -> 10600 [1] lasti
  10600 to 10604 -> 12640 [0]
  10608 to 10634 -> 10638 [0]
  10636 to 10636 -> 12640 [0]
  10638 to 10660 -> 10668 [1] lasti
  10662 to 10664 -> 12640 [0]
  10666 to 10666 -> 10668 [1] lasti
  10668 to 10960 -> 12640 [0]
  10964 to 11090 -> 11094 [0]
  11092 to 11092 -> 12640 [0]
  11094 to 11112 -> 11180 [1] lasti
  11114 to 11158 -> 11170 [1] lasti
  11160 to 11168 -> 12640 [0]
  11170 to 11178 -> 11180 [1] lasti
  11180 to 11188 -> 12640 [0]
  11192 to 11322 -> 11326 [0]
  11324 to 11324 -> 12640 [0]
  11326 to 11348 -> 11356 [1] lasti
  11350 to 11352 -> 12640 [0]
  11354 to 11354 -> 11356 [1] lasti
  11356 to 11364 -> 12640 [0]
  11368 to 11590 -> 11594 [0]
  11592 to 11592 -> 12640 [0]
  11594 to 11616 -> 11624 [1] lasti
  11618 to 11620 -> 12640 [0]
  11622 to 11622 -> 11624 [1] lasti
  11624 to 12036 -> 12640 [0]
  12040 to 12062 -> 12066 [0]
  12064 to 12064 -> 12640 [0]
  12066 to 12084 -> 12092 [1] lasti
  12086 to 12088 -> 12640 [0]
  12090 to 12090 -> 12092 [1] lasti
  12092 to 12142 -> 12640 [0]
  12146 to 12374 -> 12378 [0]
  12376 to 12376 -> 12640 [0]
  12378 to 12396 -> 12464 [1] lasti
  12398 to 12442 -> 12454 [1] lasti
  12444 to 12452 -> 12640 [0]
  12454 to 12462 -> 12464 [1] lasti
  12464 to 12634 -> 12640 [0]
  12640 to 12658 -> 12782 [1] lasti
  12660 to 12758 -> 12772 [1] lasti
  12772 to 12780 -> 12782 [1] lasti

Disassembly of <code object <listcomp> at 0x100b9d350, file "main_window_imagen.pyc", line 2213>:
2213           0 RESUME                   0
               2 BUILD_LIST               0
               4 LOAD_FAST                0 (.0)
         >>    6 FOR_ITER                42 (to 92)
               8 STORE_FAST               1 (p)
              10 LOAD_FAST                1 (p)
              12 LOAD_METHOD              0 (strip)
              34 PRECALL                  0
              38 CALL                     0
              48 POP_JUMP_BACKWARD_IF_FALSE    22 (to 6)
              50 LOAD_FAST                1 (p)
              52 LOAD_METHOD              0 (strip)
              74 PRECALL                  0
              78 CALL                     0
              88 LIST_APPEND              2
              90 JUMP_BACKWARD           43 (to 6)
         >>   92 RETURN_VALUE

Disassembly of <code object <listcomp> at 0x100bbe6b0, file "main_window_imagen.pyc", line 2243>:
               0 COPY_FREE_VARS           1

2243           2 RESUME                   0
               4 BUILD_LIST               0
               6 LOAD_FAST                0 (.0)
         >>    8 FOR_ITER                 9 (to 28)
              10 STORE_FAST               1 (prompt)
              12 LOAD_DEREF               2 (style_prefix)
              14 FORMAT_VALUE             0
              16 LOAD_CONST               0 (' ')
              18 LOAD_FAST                1 (prompt)
              20 FORMAT_VALUE             0
              22 BUILD_STRING             3
              24 LIST_APPEND              2
              26 JUMP_BACKWARD           10 (to 8)
         >>   28 RETURN_VALUE

Disassembly of <code object _compute_ratio_nums at 0x100b621f0, file "main_window_imagen.pyc", line 2309>:
2309           0 RESUME                   0

2310           2 NOP

2311           4 LOAD_FAST                0 (text)
               6 LOAD_METHOD              0 (startswith)
              28 LOAD_CONST               1 ('16:9')
              30 PRECALL                  1
              34 CALL                     1
              44 POP_JUMP_FORWARD_IF_FALSE     2 (to 50)

2312          46 LOAD_CONST               2 ((16, 9))
              48 RETURN_VALUE

2313     >>   50 LOAD_FAST                0 (text)
              52 LOAD_METHOD              0 (startswith)
              74 LOAD_CONST               3 ('9:16')
              76 PRECALL                  1
              80 CALL                     1
              90 POP_JUMP_FORWARD_IF_FALSE     2 (to 96)

2314          92 LOAD_CONST               4 ((9, 16))
              94 RETURN_VALUE

2315     >>   96 LOAD_CONST               5 ((1, 1))
              98 RETURN_VALUE
         >>  100 PUSH_EXC_INFO

2316         102 LOAD_GLOBAL              2 (Exception)
             114 CHECK_EXC_MATCH
             116 POP_JUMP_FORWARD_IF_FALSE     4 (to 126)
             118 POP_TOP

2317         120 POP_EXCEPT
             122 LOAD_CONST               5 ((1, 1))
             124 RETURN_VALUE

2316     >>  126 RERAISE                  0
         >>  128 COPY                     3
             130 POP_EXCEPT
             132 RERAISE                  1
ExceptionTable:
  4 to 44 -> 100 [0]
  50 to 90 -> 100 [0]
  100 to 118 -> 128 [1] lasti
  126 to 126 -> 128 [1] lasti

Disassembly of <code object _crop_to_ratio at 0x14d882c00, file "main_window_imagen.pyc", line 2319>:
               0 MAKE_CELL               19 (current_ratio)

2319           2 RESUME                   0

2320           4 NOP

2321           6 LOAD_GLOBAL              1 (NULL + time)
              18 LOAD_ATTR                0 (time)
              28 PRECALL                  0
              32 CALL                     0
              42 STORE_FAST               3 (t0)

2322          44 LOAD_GLOBAL              3 (NULL + QImage)
              56 LOAD_FAST                0 (image_path)
              58 PRECALL                  1
              62 CALL                     1
              72 STORE_FAST               4 (img)

2323          74 LOAD_FAST                4 (img)
              76 LOAD_METHOD              2 (isNull)
              98 PRECALL                  0
             102 CALL                     0
             112 POP_JUMP_FORWARD_IF_FALSE    37 (to 188)

2324         114 LOAD_GLOBAL              7 (NULL + logging)
             126 LOAD_ATTR                4 (warning)
             136 LOAD_CONST               1 ('[ATTACH][CROP] Load image failed: ')
             138 LOAD_FAST                0 (image_path)
             140 FORMAT_VALUE             0
             142 BUILD_STRING             2
             144 PRECALL                  1
             148 CALL                     1
             158 POP_TOP

2325         160 LOAD_GLOBAL              3 (NULL + QImage)
             172 PRECALL                  0
             176 CALL                     0
             186 RETURN_VALUE

2326     >>  188 LOAD_FAST                4 (img)
             190 LOAD_METHOD              5 (width)
             212 PRECALL                  0
             216 CALL                     0
             226 STORE_FAST               5 (w)

2327         228 LOAD_FAST                4 (img)
             230 LOAD_METHOD              6 (height)
             252 PRECALL                  0
             256 CALL                     0
             266 STORE_FAST               6 (h)

2330         268 LOAD_FAST                6 (h)
             270 POP_JUMP_FORWARD_IF_FALSE     5 (to 282)
             272 LOAD_FAST                5 (w)
             274 LOAD_FAST                6 (h)
             276 BINARY_OP               11 (/)
             280 JUMP_FORWARD             1 (to 284)
         >>  282 LOAD_CONST               2 (1.0)
         >>  284 STORE_DEREF             19 (current_ratio)

2331         286 LOAD_CONST               3 ((16, 9))
             288 LOAD_CONST               4 ((9, 16))
             290 BUILD_LIST               2
             292 STORE_FAST               7 (candidates)

2333         294 LOAD_GLOBAL             15 (NULL + min)

2334         306 LOAD_FAST                7 (candidates)

2335         308 LOAD_CLOSURE            19 (current_ratio)
             310 BUILD_TUPLE              1
             312 LOAD_CONST               5 (<code object <lambda> at 0x100b62330, file "main_window_imagen.pyc", line 2335>)
             314 MAKE_FUNCTION            8 (closure)

2333         316 KW_NAMES                 6
             318 PRECALL                  2
             322 CALL                     2
             332 UNPACK_SEQUENCE          2
             336 STORE_FAST               8 (best_w)
             338 STORE_FAST               9 (best_h)

2337         340 LOAD_FAST                9 (best_h)
             342 POP_JUMP_FORWARD_IF_FALSE     5 (to 354)
             344 LOAD_FAST                8 (best_w)
             346 LOAD_FAST                9 (best_h)
             348 BINARY_OP               11 (/)
             352 JUMP_FORWARD             1 (to 356)
         >>  354 LOAD_CONST               2 (1.0)
         >>  356 STORE_FAST              10 (target_ratio)

2338         358 LOAD_DEREF              19 (current_ratio)
             360 LOAD_FAST               10 (target_ratio)
             362 COMPARE_OP               4 (>)
             368 POP_JUMP_FORWARD_IF_FALSE    47 (to 464)

2340         370 LOAD_GLOBAL             17 (NULL + int)
             382 LOAD_FAST                6 (h)
             384 LOAD_FAST               10 (target_ratio)
             386 BINARY_OP                5 (*)
             390 PRECALL                  1
             394 CALL                     1
             404 STORE_FAST              11 (new_w)

2341         406 LOAD_GLOBAL             19 (NULL + max)
             418 LOAD_CONST               7 (0)
             420 LOAD_FAST                5 (w)
             422 LOAD_FAST               11 (new_w)
             424 BINARY_OP               10 (-)
             428 LOAD_CONST               8 (2)
             430 BINARY_OP                2 (//)
             434 PRECALL                  2
             438 CALL                     2
             448 STORE_FAST              12 (x)

2342         450 LOAD_FAST               12 (x)
             452 LOAD_CONST               7 (0)
             454 LOAD_FAST               11 (new_w)
             456 LOAD_FAST                6 (h)
             458 BUILD_TUPLE              4
             460 STORE_FAST              13 (rect)
             462 JUMP_FORWARD            46 (to 556)

2345     >>  464 LOAD_GLOBAL             17 (NULL + int)
             476 LOAD_FAST                5 (w)
             478 LOAD_FAST               10 (target_ratio)
             480 BINARY_OP               11 (/)
             484 PRECALL                  1
             488 CALL                     1
             498 STORE_FAST              14 (new_h)

2346         500 LOAD_GLOBAL             19 (NULL + max)
             512 LOAD_CONST               7 (0)
             514 LOAD_FAST                6 (h)
             516 LOAD_FAST               14 (new_h)
             518 BINARY_OP               10 (-)
             522 LOAD_CONST               8 (2)
             524 BINARY_OP                2 (//)
             528 PRECALL                  2
             532 CALL                     2
             542 STORE_FAST              15 (y)

2347         544 LOAD_CONST               7 (0)
             546 LOAD_FAST               15 (y)
             548 LOAD_FAST                5 (w)
             550 LOAD_FAST               14 (new_h)
             552 BUILD_TUPLE              4
             554 STORE_FAST              13 (rect)

2348     >>  556 LOAD_FAST                4 (img)
             558 LOAD_METHOD             10 (copy)
             580 LOAD_FAST               13 (rect)
             582 LOAD_CONST               7 (0)
             584 BINARY_SUBSCR
             594 LOAD_FAST               13 (rect)
             596 LOAD_CONST               9 (1)
             598 BINARY_SUBSCR
             608 LOAD_FAST               13 (rect)
             610 LOAD_CONST               8 (2)
             612 BINARY_SUBSCR
             622 LOAD_FAST               13 (rect)
             624 LOAD_CONST              10 (3)
             626 BINARY_SUBSCR
             636 PRECALL                  4
             640 CALL                     4
             650 STORE_FAST              16 (cropped)

2349         652 LOAD_GLOBAL              1 (NULL + time)
             664 LOAD_ATTR                0 (time)
             674 PRECALL                  0
             678 CALL                     0
             688 STORE_FAST              17 (t1)

2350         690 LOAD_GLOBAL              7 (NULL + logging)
             702 LOAD_ATTR               11 (info)

2351         712 LOAD_CONST              11 ('[ATTACH][CROP] path=')
             714 LOAD_GLOBAL             24 (os)
             726 LOAD_ATTR               13 (path)
             736 LOAD_METHOD             14 (basename)
             758 LOAD_FAST                0 (image_path)
             760 PRECALL                  1
             764 CALL                     1
             774 FORMAT_VALUE             0
             776 LOAD_CONST              12 (' orig=')
             778 LOAD_FAST                5 (w)
             780 FORMAT_VALUE             0
             782 LOAD_CONST              13 ('x')
             784 LOAD_FAST                6 (h)
             786 FORMAT_VALUE             0
             788 LOAD_CONST              14 (' chosen_ratio=')

2352         790 LOAD_FAST                8 (best_w)

2351         792 FORMAT_VALUE             0
             794 LOAD_CONST              15 (':')

2352         796 LOAD_FAST                9 (best_h)

2351         798 FORMAT_VALUE             0
             800 LOAD_CONST              16 (' crop_rect=')

2352         802 LOAD_FAST               13 (rect)

2351         804 FORMAT_VALUE             0
             806 LOAD_CONST              17 (' out=')

2353         808 LOAD_FAST               16 (cropped)
             810 LOAD_METHOD              5 (width)
             832 PRECALL                  0
             836 CALL                     0

2351         846 FORMAT_VALUE             0
             848 LOAD_CONST              13 ('x')

2353         850 LOAD_FAST               16 (cropped)
             852 LOAD_METHOD              6 (height)
             874 PRECALL                  0
             878 CALL                     0

2351         888 FORMAT_VALUE             0
             890 LOAD_CONST              18 (' time_ms=')

2353         892 LOAD_FAST               17 (t1)
             894 LOAD_FAST                3 (t0)
             896 BINARY_OP               10 (-)
             900 LOAD_CONST              19 (1000)
             902 BINARY_OP                5 (*)
             906 LOAD_CONST              20 ('.0f')

2351         908 FORMAT_VALUE             4 (with format)
             910 BUILD_STRING            18

2350         912 PRECALL                  1
             916 CALL                     1
             926 POP_TOP

2355         928 LOAD_FAST               16 (cropped)
             930 RETURN_VALUE
         >>  932 PUSH_EXC_INFO

2356         934 LOAD_GLOBAL             30 (Exception)
             946 CHECK_EXC_MATCH
             948 POP_JUMP_FORWARD_IF_FALSE    47 (to 1044)
             950 STORE_FAST              18 (e)

2357         952 LOAD_GLOBAL              7 (NULL + logging)
             964 LOAD_ATTR               16 (error)
             974 LOAD_CONST              21 ('❌ Crop error: ')
             976 LOAD_FAST               18 (e)
             978 FORMAT_VALUE             0
             980 BUILD_STRING             2
             982 PRECALL                  1
             986 CALL                     1
             996 POP_TOP

2358         998 LOAD_GLOBAL              3 (NULL + QImage)
            1010 PRECALL                  0
            1014 CALL                     0
            1024 SWAP                     2
            1026 POP_EXCEPT
            1028 LOAD_CONST               0 (None)
            1030 STORE_FAST              18 (e)
            1032 DELETE_FAST             18 (e)
            1034 RETURN_VALUE
         >> 1036 LOAD_CONST               0 (None)
            1038 STORE_FAST              18 (e)
            1040 DELETE_FAST             18 (e)
            1042 RERAISE                  1

2356     >> 1044 RERAISE                  0
         >> 1046 COPY                     3
            1048 POP_EXCEPT
            1050 RERAISE                  1
ExceptionTable:
  6 to 184 -> 932 [0]
  188 to 928 -> 932 [0]
  932 to 950 -> 1046 [1] lasti
  952 to 1022 -> 1036 [1] lasti
  1024 to 1024 -> 1046 [1] lasti
  1036 to 1044 -> 1046 [1] lasti

Disassembly of <code object <lambda> at 0x100b62330, file "main_window_imagen.pyc", line 2335>:
               0 COPY_FREE_VARS           1

2335           2 RESUME                   0
               4 LOAD_FAST                0 (rh)
               6 LOAD_CONST               1 (1)
               8 BINARY_SUBSCR
              18 LOAD_CONST               2 (0)
              20 COMPARE_OP               3 (!=)
              26 POP_JUMP_FORWARD_IF_FALSE    33 (to 94)
              28 LOAD_GLOBAL              1 (NULL + abs)
              40 LOAD_FAST                0 (rh)
              42 LOAD_CONST               2 (0)
              44 BINARY_SUBSCR
              54 LOAD_FAST                0 (rh)
              56 LOAD_CONST               1 (1)
              58 BINARY_SUBSCR
              68 BINARY_OP               11 (/)
              72 LOAD_DEREF               1 (current_ratio)
              74 BINARY_OP               10 (-)
              78 PRECALL                  1
              82 CALL                     1
              92 JUMP_FORWARD            14 (to 122)
         >>   94 LOAD_GLOBAL              3 (NULL + float)
             106 LOAD_CONST               3 ('inf')
             108 PRECALL                  1
             112 CALL                     1
         >>  122 RETURN_VALUE

Disassembly of <code object _image_to_base64 at 0x14d6573c0, file "main_window_imagen.pyc", line 2360>:
2360           0 RESUME                   0

2361           2 NOP

2362           4 LOAD_GLOBAL              1 (NULL + time)
              16 LOAD_ATTR                0 (time)
              26 PRECALL                  0
              30 CALL                     0
              40 STORE_FAST               1 (t0)

2363          42 LOAD_FAST                0 (img)
              44 LOAD_METHOD              1 (isNull)
              66 PRECALL                  0
              70 CALL                     0
              80 POP_JUMP_FORWARD_IF_FALSE     2 (to 86)

2364          82 LOAD_CONST               1 ('')
              84 RETURN_VALUE

2365     >>   86 LOAD_GLOBAL              5 (NULL + QBuffer)
              98 PRECALL                  0
             102 CALL                     0
             112 STORE_FAST               2 (buffer)

2366         114 LOAD_FAST                2 (buffer)
             116 LOAD_METHOD              3 (open)
             138 LOAD_GLOBAL              8 (QIODevice)
             150 LOAD_ATTR                5 (WriteOnly)
             160 PRECALL                  1
             164 CALL                     1
             174 POP_TOP

2368         176 LOAD_FAST                0 (img)
             178 LOAD_METHOD              6 (save)
             200 LOAD_FAST                2 (buffer)
             202 LOAD_CONST               2 ('JPG')
             204 LOAD_CONST               3 (92)
             206 KW_NAMES                 4
             208 PRECALL                  3
             212 CALL                     3
             222 POP_TOP

2369         224 LOAD_FAST                2 (buffer)
             226 LOAD_METHOD              7 (data)
             248 PRECALL                  0
             252 CALL                     0
             262 STORE_FAST               3 (ba)

2370         264 LOAD_GLOBAL             17 (NULL + base64)
             276 LOAD_ATTR                9 (b64encode)
             286 LOAD_GLOBAL             21 (NULL + bytes)
             298 LOAD_FAST                3 (ba)
             300 PRECALL                  1
             304 CALL                     1
             314 PRECALL                  1
             318 CALL                     1
             328 LOAD_METHOD             11 (decode)
             350 LOAD_CONST               5 ('ascii')
             352 PRECALL                  1
             356 CALL                     1
             366 STORE_FAST               4 (b64)

2371         368 LOAD_GLOBAL              1 (NULL + time)
             380 LOAD_ATTR                0 (time)
             390 PRECALL                  0
             394 CALL                     0
             404 STORE_FAST               5 (t1)

2372         406 LOAD_GLOBAL             25 (NULL + logging)
             418 LOAD_ATTR               13 (info)
             428 LOAD_CONST               6 ('[ATTACH][ENCODE] out_size_bytes=')
             430 LOAD_GLOBAL             29 (NULL + len)
             442 LOAD_FAST                3 (ba)
             444 PRECALL                  1
             448 CALL                     1
             458 FORMAT_VALUE             0
             460 LOAD_CONST               7 (' b64_len=')
             462 LOAD_GLOBAL             29 (NULL + len)
             474 LOAD_FAST                4 (b64)
             476 PRECALL                  1
             480 CALL                     1
             490 FORMAT_VALUE             0
             492 LOAD_CONST               8 (' time_ms=')
             494 LOAD_FAST                5 (t1)
             496 LOAD_FAST                1 (t0)
             498 BINARY_OP               10 (-)
             502 LOAD_CONST               9 (1000)
             504 BINARY_OP                5 (*)
             508 LOAD_CONST              10 ('.0f')
             510 FORMAT_VALUE             4 (with format)
             512 BUILD_STRING             6
             514 PRECALL                  1
             518 CALL                     1
             528 POP_TOP

2373         530 LOAD_FAST                4 (b64)
             532 RETURN_VALUE
         >>  534 PUSH_EXC_INFO

2374         536 LOAD_GLOBAL             30 (Exception)
             548 CHECK_EXC_MATCH
             550 POP_JUMP_FORWARD_IF_FALSE    34 (to 620)
             552 STORE_FAST               6 (e)

2375         554 LOAD_GLOBAL             25 (NULL + logging)
             566 LOAD_ATTR               16 (error)
             576 LOAD_CONST              11 ('❌ Encode base64 error: ')
             578 LOAD_FAST                6 (e)
             580 FORMAT_VALUE             0
             582 BUILD_STRING             2
             584 PRECALL                  1
             588 CALL                     1
             598 POP_TOP

2376         600 POP_EXCEPT
             602 LOAD_CONST               0 (None)
             604 STORE_FAST               6 (e)
             606 DELETE_FAST              6 (e)
             608 LOAD_CONST               1 ('')
             610 RETURN_VALUE
         >>  612 LOAD_CONST               0 (None)
             614 STORE_FAST               6 (e)
             616 DELETE_FAST              6 (e)
             618 RERAISE                  1

2374     >>  620 RERAISE                  0
         >>  622 COPY                     3
             624 POP_EXCEPT
             626 RERAISE                  1
ExceptionTable:
  4 to 80 -> 534 [0]
  86 to 530 -> 534 [0]
  534 to 552 -> 622 [1] lasti
  554 to 598 -> 612 [1] lasti
  612 to 620 -> 622 [1] lasti

Disassembly of <code object <listcomp> at 0x100bbe950, file "main_window_imagen.pyc", line 2386>:
2386           0 RESUME                   0
               2 BUILD_LIST               0
               4 LOAD_FAST                0 (.0)
         >>    6 FOR_ITER                11 (to 30)

2388           8 STORE_FAST               1 (i)

2387          10 LOAD_FAST                1 (i)
              12 LOAD_CONST               0 (1)
              14 BINARY_OP                0 (+)
              18 LOAD_CONST               1 ('')
              20 LOAD_CONST               2 ('image/jpeg')
              22 LOAD_CONST               3 (('index', 'base64', 'mimeType'))
              24 BUILD_CONST_KEY_MAP      3

2386          26 LIST_APPEND              2
              28 JUMP_BACKWARD           12 (to 6)
         >>   30 RETURN_VALUE

Disassembly of <code object encode_one at 0x14d657910, file "main_window_imagen.pyc", line 2396>:
               0 COPY_FREE_VARS           4

2396           2 RESUME                   0

2397           4 NOP

2398           6 LOAD_GLOBAL              1 (NULL + time)
              18 LOAD_ATTR                0 (time)
              28 PRECALL                  0
              32 CALL                     0
              42 STORE_FAST               2 (t0)

2399          44 PUSH_NULL
              46 LOAD_DEREF               7 (_crop_to_ratio)
              48 LOAD_FAST                1 (img_path)
              50 LOAD_DEREF              10 (ratio_w)
              52 LOAD_DEREF               9 (ratio_h)
              54 PRECALL                  3
              58 CALL                     3
              68 STORE_FAST               3 (cropped)

2400          70 PUSH_NULL
              72 LOAD_DEREF               8 (_image_to_base64)
              74 LOAD_FAST                3 (cropped)
              76 PRECALL                  1
              80 CALL                     1
              90 STORE_FAST               4 (b64)

2401          92 LOAD_FAST                4 (b64)
              94 POP_JUMP_FORWARD_IF_NONE   149 (to 394)

2402          96 LOAD_GLOBAL              1 (NULL + time)
             108 LOAD_ATTR                0 (time)
             118 PRECALL                  0
             122 CALL                     0
             132 STORE_FAST               5 (t1)

2403         134 LOAD_GLOBAL              3 (NULL + logging)
             146 LOAD_ATTR                2 (info)
             156 LOAD_CONST               1 ('[ATTACH][PREPARED] slot=')
             158 LOAD_FAST                0 (idx_slot)
             160 LOAD_CONST               2 (1)
             162 BINARY_OP                0 (+)
             166 FORMAT_VALUE             0
             168 LOAD_CONST               3 (' file=')
             170 LOAD_GLOBAL              6 (os)
             182 LOAD_ATTR                4 (path)
             192 LOAD_METHOD              5 (basename)
             214 LOAD_FAST                1 (img_path)
             216 PRECALL                  1
             220 CALL                     1
             230 FORMAT_VALUE             0
             232 LOAD_CONST               4 (' out_w=')
             234 LOAD_FAST                3 (cropped)
             236 LOAD_METHOD              6 (width)
             258 PRECALL                  0
             262 CALL                     0
             272 FORMAT_VALUE             0
             274 LOAD_CONST               5 (' out_h=')
             276 LOAD_FAST                3 (cropped)
             278 LOAD_METHOD              7 (height)
             300 PRECALL                  0
             304 CALL                     0
             314 FORMAT_VALUE             0
             316 LOAD_CONST               6 (' b64_len=')
             318 LOAD_GLOBAL             17 (NULL + len)
             330 LOAD_FAST                4 (b64)
             332 PRECALL                  1
             336 CALL                     1
             346 FORMAT_VALUE             0
             348 LOAD_CONST               7 (' total_ms=')
             350 LOAD_FAST                5 (t1)
             352 LOAD_FAST                2 (t0)
             354 BINARY_OP               10 (-)
             358 LOAD_CONST               8 (1000)
             360 BINARY_OP                5 (*)
             364 LOAD_CONST               9 ('.0f')
             366 FORMAT_VALUE             4 (with format)
             368 BUILD_STRING            12
             370 PRECALL                  1
             374 CALL                     1
             384 POP_TOP

2404         386 LOAD_FAST                0 (idx_slot)
             388 LOAD_FAST                4 (b64)
             390 BUILD_TUPLE              2
             392 RETURN_VALUE

2401     >>  394 JUMP_FORWARD            52 (to 500)
         >>  396 PUSH_EXC_INFO

2405         398 LOAD_GLOBAL             18 (Exception)
             410 CHECK_EXC_MATCH
             412 POP_JUMP_FORWARD_IF_FALSE    39 (to 492)
             414 STORE_FAST               6 (_e)

2406         416 LOAD_GLOBAL              3 (NULL + logging)
             428 LOAD_ATTR               10 (error)
             438 LOAD_CONST              10 ('❌ Slot ')
             440 LOAD_FAST                0 (idx_slot)
             442 LOAD_CONST               2 (1)
             444 BINARY_OP                0 (+)
             448 FORMAT_VALUE             0
             450 LOAD_CONST              11 (' parallel encode error: ')
             452 LOAD_FAST                6 (_e)
             454 FORMAT_VALUE             0
             456 BUILD_STRING             4
             458 PRECALL                  1
             462 CALL                     1
             472 POP_TOP
             474 POP_EXCEPT
             476 LOAD_CONST               0 (None)
             478 STORE_FAST               6 (_e)
             480 DELETE_FAST              6 (_e)
             482 JUMP_FORWARD             8 (to 500)
         >>  484 LOAD_CONST               0 (None)
             486 STORE_FAST               6 (_e)
             488 DELETE_FAST              6 (_e)
             490 RERAISE                  1

2405     >>  492 RERAISE                  0
         >>  494 COPY                     3
             496 POP_EXCEPT
             498 RERAISE                  1

2407     >>  500 LOAD_FAST                0 (idx_slot)
             502 LOAD_CONST               0 (None)
             504 BUILD_TUPLE              2
             506 RETURN_VALUE
ExceptionTable:
  6 to 390 -> 396 [0]
  396 to 414 -> 494 [1] lasti
  416 to 472 -> 484 [1] lasti
  484 to 492 -> 494 [1] lasti

Disassembly of <code object <listcomp> at 0x100bcd130, file "main_window_imagen.pyc", line 2409>:
               0 COPY_FREE_VARS           2

2409           2 RESUME                   0
               4 BUILD_LIST               0
               6 LOAD_FAST                0 (.0)
         >>    8 FOR_ITER                28 (to 66)
              10 UNPACK_SEQUENCE          2
              14 STORE_FAST               1 (idx)
              16 STORE_FAST               2 (p)
              18 LOAD_DEREF               4 (ex)
              20 LOAD_METHOD              0 (submit)
              42 LOAD_DEREF               3 (encode_one)
              44 LOAD_FAST                1 (idx)
              46 LOAD_FAST                2 (p)
              48 PRECALL                  3
              52 CALL                     3
              62 LIST_APPEND              2
              64 JUMP_BACKWARD           29 (to 8)
         >>   66 RETURN_VALUE

Disassembly of <code object <lambda> at 0x100bcd230, file "main_window_imagen.pyc", line 2419>:
2419           0 RESUME                   0
               2 LOAD_GLOBAL              1 (NULL + int)
              14 LOAD_FAST                0 (it)
              16 LOAD_METHOD              1 (get)
              38 LOAD_CONST               1 ('index')
              40 LOAD_CONST               2 (0)
              42 PRECALL                  2
              46 CALL                     2
              56 PRECALL                  1
              60 CALL                     1
              70 RETURN_VALUE

Disassembly of <code object _is_vietnamese_text at 0x100affa60, file "main_window_imagen.pyc", line 2478>:
2478           0 RESUME                   0

2479           2 NOP

2481           4 LOAD_GLOBAL              1 (NULL + bool)
              16 LOAD_GLOBAL              3 (NULL + re)
              28 LOAD_ATTR                2 (search)
              38 LOAD_CONST               1 ('[ăâêôơưđĂÂÊÔƠƯĐáàảãạÁÀẢÃẠấầẩẫậẤẦẨẪẬéèẻẽẹÉÈẺẼẸóòỏõọÓÒỎÕỌúùủũụÚÙỦŨỤýỳỷỹỵÝỲỶỸỴ]')
              40 LOAD_FAST                0 (s)
              42 PRECALL                  2
              46 CALL                     2
              56 PRECALL                  1
              60 CALL                     1
              70 RETURN_VALUE
         >>   72 PUSH_EXC_INFO

2482          74 LOAD_GLOBAL              6 (Exception)
              86 CHECK_EXC_MATCH
              88 POP_JUMP_FORWARD_IF_FALSE     4 (to 98)
              90 POP_TOP

2483          92 POP_EXCEPT
              94 LOAD_CONST               2 (False)
              96 RETURN_VALUE

2482     >>   98 RERAISE                  0
         >>  100 COPY                     3
             102 POP_EXCEPT
             104 RERAISE                  1
ExceptionTable:
  4 to 68 -> 72 [0]
  72 to 90 -> 100 [1] lasti
  98 to 98 -> 100 [1] lasti

Disassembly of <code object _collect_character_name_map at 0x14d657bd0, file "main_window_imagen.pyc", line 2485>:
               0 COPY_FREE_VARS           1

2485           2 RESUME                   0

2486           4 BUILD_LIST               0
               6 STORE_FAST               0 (mapping)

2487           8 NOP

2488          10 LOAD_GLOBAL              1 (NULL + enumerate)
              22 LOAD_GLOBAL              3 (NULL + getattr)
              34 LOAD_DEREF               5 (self)
              36 LOAD_CONST               1 ('character_import_slots')
              38 BUILD_LIST               0
              40 PRECALL                  3
              44 CALL                     3
              54 LOAD_CONST               0 (None)
              56 LOAD_GLOBAL              3 (NULL + getattr)
              68 LOAD_DEREF               5 (self)
              70 LOAD_CONST               2 ('max_character_slots')
              72 LOAD_CONST               3 (10)
              74 PRECALL                  3
              78 CALL                     3
              88 BUILD_SLICE              2
              90 BINARY_SUBSCR
             100 PRECALL                  1
             104 CALL                     1
             114 GET_ITER
         >>  116 FOR_ITER               151 (to 420)
             118 UNPACK_SEQUENCE          2
             122 STORE_FAST               1 (idx)
             124 STORE_FAST               2 (slot)

2489         126 LOAD_FAST                2 (slot)
             128 POP_JUMP_FORWARD_IF_FALSE    17 (to 164)
             130 LOAD_GLOBAL              3 (NULL + getattr)
             142 LOAD_FAST                2 (slot)
             144 LOAD_CONST               4 ('image_path')
             146 LOAD_CONST               0 (None)
             148 PRECALL                  3
             152 CALL                     3
             162 POP_JUMP_FORWARD_IF_TRUE     1 (to 166)

2490     >>  164 JUMP_BACKWARD           25 (to 116)

2491     >>  166 LOAD_CONST               0 (None)
             168 STORE_FAST               3 (name_edit)

2492         170 NOP

2493         172 LOAD_DEREF               5 (self)
             174 LOAD_ATTR                2 (character_name_edits)
             184 LOAD_FAST                1 (idx)
             186 BINARY_SUBSCR
             196 STORE_FAST               3 (name_edit)
             198 JUMP_FORWARD            18 (to 236)
         >>  200 PUSH_EXC_INFO

2494         202 LOAD_GLOBAL              6 (Exception)
             214 CHECK_EXC_MATCH
             216 POP_JUMP_FORWARD_IF_FALSE     5 (to 228)
             218 POP_TOP

2495         220 LOAD_CONST               0 (None)
             222 STORE_FAST               3 (name_edit)
             224 POP_EXCEPT
             226 JUMP_FORWARD             4 (to 236)

2494     >>  228 RERAISE                  0
         >>  230 COPY                     3
             232 POP_EXCEPT
             234 RERAISE                  1

2496     >>  236 LOAD_FAST                3 (name_edit)
             238 POP_JUMP_FORWARD_IF_FALSE    38 (to 316)
             240 LOAD_FAST                3 (name_edit)
             242 LOAD_METHOD              4 (text)
             264 PRECALL                  0
             268 CALL                     0
             278 LOAD_METHOD              5 (strip)
             300 PRECALL                  0
             304 CALL                     0
             314 JUMP_FORWARD             1 (to 318)
         >>  316 LOAD_CONST               5 ('')
         >>  318 STORE_FAST               4 (name_text)

2497         320 LOAD_FAST                4 (name_text)
             322 POP_JUMP_FORWARD_IF_TRUE     1 (to 326)

2498         324 JUMP_BACKWARD          105 (to 116)

2499     >>  326 LOAD_FAST                0 (mapping)
             328 LOAD_METHOD              6 (append)

2500         350 LOAD_FAST                1 (idx)
             352 LOAD_CONST               6 (1)
             354 BINARY_OP                0 (+)

2501         358 LOAD_FAST                4 (name_text)

2502         360 LOAD_FAST                4 (name_text)
             362 LOAD_METHOD              7 (lower)
             384 PRECALL                  0
             388 CALL                     0

2499         398 LOAD_CONST               7 (('index', 'name', 'name_lower'))
             400 BUILD_CONST_KEY_MAP      3
             402 PRECALL                  1
             406 CALL                     1
             416 POP_TOP
             418 JUMP_BACKWARD          152 (to 116)

2488     >>  420 JUMP_FORWARD            16 (to 454)
         >>  422 PUSH_EXC_INFO

2504         424 LOAD_GLOBAL              6 (Exception)
             436 CHECK_EXC_MATCH
             438 POP_JUMP_FORWARD_IF_FALSE     3 (to 446)
             440 POP_TOP

2505         442 POP_EXCEPT
             444 JUMP_FORWARD             4 (to 454)

2504     >>  446 RERAISE                  0
         >>  448 COPY                     3
             450 POP_EXCEPT
             452 RERAISE                  1

2506     >>  454 LOAD_FAST                0 (mapping)
             456 RETURN_VALUE
ExceptionTable:
  10 to 168 -> 422 [0]
  172 to 196 -> 200 [1]
  198 to 198 -> 422 [0]
  200 to 222 -> 230 [2] lasti
  224 to 226 -> 422 [0]
  228 to 228 -> 230 [2] lasti
  230 to 418 -> 422 [0]
  422 to 440 -> 448 [1] lasti
  446 to 446 -> 448 [1] lasti

Disassembly of <code object _build_attachments_and_replace at 0x14d883200, file "main_window_imagen.pyc", line 2508>:
               0 COPY_FREE_VARS           2
               2 MAKE_CELL               14 (attached_order)
               4 MAKE_CELL               15 (bitset)
               6 MAKE_CELL               16 (find_index_for_name)
               8 MAKE_CELL               17 (is_vn)
              10 MAKE_CELL               18 (local_ord_map)
              12 MAKE_CELL               19 (name_map)
              14 MAKE_CELL               20 (overflow)

2508          16 RESUME                   0

2509          18 PUSH_NULL
              20 LOAD_DEREF              21 (_collect_character_name_map)
              22 PRECALL                  0
              26 CALL                     0
              36 STORE_DEREF             19 (name_map)

2510          38 BUILD_LIST               0
              40 STORE_FAST               1 (attachments_bits)

2511          42 BUILD_LIST               0
              44 STORE_FAST               2 (replaced_prompts_out)

2512          46 BUILD_LIST               0
              48 STORE_FAST               3 (orders_by_prompt)

2513          50 BUILD_LIST               0
              52 STORE_FAST               4 (overflow_prompts)

2514          54 LOAD_DEREF              19 (name_map)
              56 POP_JUMP_FORWARD_IF_TRUE    32 (to 122)

2515          58 LOAD_CONST               1 (0)
              60 BUILD_LIST               1
              62 LOAD_GLOBAL              1 (NULL + len)
              74 LOAD_FAST                0 (prompts_in)
              76 PRECALL                  1
              80 CALL                     1
              90 BINARY_OP                5 (*)
              94 LOAD_FAST                0 (prompts_in)
              96 LOAD_CONST               2 (<code object <listcomp> at 0x100bc3020, file "main_window_imagen.pyc", line 2515>)
              98 MAKE_FUNCTION            0
             100 LOAD_FAST                0 (prompts_in)
             102 GET_ITER
             104 PRECALL                  0
             108 CALL                     0
             118 BUILD_TUPLE              3
             120 RETURN_VALUE

2517     >>  122 NOP

2518         124 LOAD_CONST               3 (<code object <listcomp> at 0x100c04470, file "main_window_imagen.pyc", line 2518>)
             126 MAKE_FUNCTION            0
             128 LOAD_DEREF              19 (name_map)
             130 GET_ITER
             132 PRECALL                  0
             136 CALL                     0
             146 STORE_FAST               5 (alternatives)

2519         148 LOAD_FAST                5 (alternatives)
             150 POP_JUMP_FORWARD_IF_TRUE    32 (to 216)

2520         152 LOAD_CONST               1 (0)
             154 BUILD_LIST               1
             156 LOAD_GLOBAL              1 (NULL + len)
             168 LOAD_FAST                0 (prompts_in)
             170 PRECALL                  1
             174 CALL                     1
             184 BINARY_OP                5 (*)
             188 LOAD_FAST                0 (prompts_in)
             190 LOAD_CONST               4 (<code object <listcomp> at 0x100bc30f0, file "main_window_imagen.pyc", line 2520>)
             192 MAKE_FUNCTION            0
             194 LOAD_FAST                0 (prompts_in)
             196 GET_ITER
             198 PRECALL                  0
             202 CALL                     0
             212 BUILD_TUPLE              3
             214 RETURN_VALUE

2521     >>  216 LOAD_GLOBAL              3 (NULL + re)
             228 LOAD_ATTR                2 (compile)
             238 LOAD_CONST               5 ('(?iu)\\b(')
             240 LOAD_CONST               6 ('|')
             242 LOAD_METHOD              3 (join)
             264 LOAD_FAST                5 (alternatives)
             266 PRECALL                  1
             270 CALL                     1
             280 BINARY_OP                0 (+)
             284 LOAD_CONST               7 (')\\b')
             286 BINARY_OP                0 (+)
             290 PRECALL                  1
             294 CALL                     1
             304 STORE_FAST               6 (pattern)
             306 JUMP_FORWARD            48 (to 404)
         >>  308 PUSH_EXC_INFO

2522         310 LOAD_GLOBAL              8 (Exception)
             322 CHECK_EXC_MATCH
             324 POP_JUMP_FORWARD_IF_FALSE    35 (to 396)
             326 POP_TOP

2523         328 LOAD_CONST               1 (0)
             330 BUILD_LIST               1
             332 LOAD_GLOBAL              1 (NULL + len)
             344 LOAD_FAST                0 (prompts_in)
             346 PRECALL                  1
             350 CALL                     1
             360 BINARY_OP                5 (*)
             364 LOAD_FAST                0 (prompts_in)
             366 LOAD_CONST               8 (<code object <listcomp> at 0x100bc31c0, file "main_window_imagen.pyc", line 2523>)
             368 MAKE_FUNCTION            0
             370 LOAD_FAST                0 (prompts_in)
             372 GET_ITER
             374 PRECALL                  0
             378 CALL                     0
             388 BUILD_TUPLE              3
             390 SWAP                     2
             392 POP_EXCEPT
             394 RETURN_VALUE

2522     >>  396 RERAISE                  0
         >>  398 COPY                     3
             400 POP_EXCEPT
             402 RERAISE                  1

2526     >>  404 LOAD_CONST               9 ('found')
             406 LOAD_GLOBAL             10 (str)
             418 LOAD_CONST              10 ('return')
             420 LOAD_GLOBAL             12 (int)
             432 BUILD_TUPLE              4
             434 LOAD_CLOSURE            19 (name_map)
             436 BUILD_TUPLE              1
             438 LOAD_CONST              11 (<code object find_index_for_name at 0x14d657e60, file "main_window_imagen.pyc", line 2526>)
             440 MAKE_FUNCTION           12 (annotations, closure)
             442 STORE_DEREF             16 (find_index_for_name)

2538         444 LOAD_GLOBAL             15 (NULL + enumerate)
             456 LOAD_FAST                0 (prompts_in)
             458 PRECALL                  1
             462 CALL                     1
             472 GET_ITER
         >>  474 FOR_ITER               246 (to 968)
             476 UNPACK_SEQUENCE          2
             480 STORE_FAST               7 (idx_prompt)
             482 STORE_FAST               8 (text)

2539         484 LOAD_CONST               1 (0)
             486 STORE_DEREF             15 (bitset)

2540         488 BUILD_LIST               0
             490 STORE_DEREF             14 (attached_order)

2541         492 BUILD_MAP                0
             494 STORE_DEREF             18 (local_ord_map)

2542         496 PUSH_NULL
             498 LOAD_DEREF              22 (_is_vietnamese_text)
             500 LOAD_FAST                8 (text)
             502 PRECALL                  1
             506 CALL                     1
             516 STORE_DEREF             17 (is_vn)

2543         518 LOAD_CONST              12 (False)
             520 STORE_DEREF             20 (overflow)

2545         522 LOAD_CLOSURE            14 (attached_order)
             524 LOAD_CLOSURE            15 (bitset)
             526 LOAD_CLOSURE            16 (find_index_for_name)
             528 LOAD_CLOSURE            17 (is_vn)
             530 LOAD_CLOSURE            18 (local_ord_map)
             532 LOAD_CLOSURE            20 (overflow)
             534 BUILD_TUPLE              6
             536 LOAD_CONST              13 (<code object repl at 0x14d658090, file "main_window_imagen.pyc", line 2545>)
             538 MAKE_FUNCTION            8 (closure)
             540 STORE_FAST               9 (repl)

2573         542 NOP

2574         544 LOAD_FAST                6 (pattern)
             546 LOAD_METHOD              8 (sub)
             568 LOAD_FAST                9 (repl)
             570 LOAD_FAST                8 (text)
             572 PRECALL                  2
             576 CALL                     2
             586 STORE_FAST              10 (new_text)
             588 JUMP_FORWARD            18 (to 626)
         >>  590 PUSH_EXC_INFO

2575         592 LOAD_GLOBAL              8 (Exception)
             604 CHECK_EXC_MATCH
             606 POP_JUMP_FORWARD_IF_FALSE     5 (to 618)
             608 POP_TOP

2576         610 LOAD_FAST                8 (text)
             612 STORE_FAST              10 (new_text)
             614 POP_EXCEPT
             616 JUMP_FORWARD             4 (to 626)

2575     >>  618 RERAISE                  0
         >>  620 COPY                     3
             622 POP_EXCEPT
             624 RERAISE                  1

2578     >>  626 NOP

2579         628 LOAD_GLOBAL             13 (NULL + int)
             640 LOAD_DEREF              15 (bitset)
             642 PRECALL                  1
             646 CALL                     1
             656 LOAD_CONST               1 (0)
             658 COMPARE_OP               3 (!=)
             664 POP_JUMP_FORWARD_IF_FALSE    21 (to 708)

2580         666 LOAD_CONST              14 ('nghiêm cấm thay đổi nét mặt các nhân vật')
             668 STORE_FAST              11 (extra_vi)

2581         670 LOAD_CONST              15 ("Do not alter the characters' facial expressions.")
             672 STORE_FAST              12 (extra_en)

2582         674 LOAD_DEREF              17 (is_vn)
             676 POP_JUMP_FORWARD_IF_FALSE     2 (to 682)
             678 LOAD_FAST               11 (extra_vi)
             680 JUMP_FORWARD             1 (to 684)
         >>  682 LOAD_FAST               12 (extra_en)
         >>  684 STORE_FAST              13 (extra_line)

2583         686 LOAD_FAST               13 (extra_line)
             688 LOAD_FAST               10 (new_text)
             690 CONTAINS_OP              1
             692 POP_JUMP_FORWARD_IF_FALSE     7 (to 708)

2584         694 LOAD_FAST               10 (new_text)
             696 FORMAT_VALUE             0
             698 LOAD_CONST              16 ('\n')
             700 LOAD_FAST               13 (extra_line)
             702 FORMAT_VALUE             0
             704 BUILD_STRING             3
             706 STORE_FAST              10 (new_text)
         >>  708 JUMP_FORWARD            16 (to 742)
         >>  710 PUSH_EXC_INFO

2585         712 LOAD_GLOBAL              8 (Exception)
             724 CHECK_EXC_MATCH
             726 POP_JUMP_FORWARD_IF_FALSE     3 (to 734)
             728 POP_TOP

2586         730 POP_EXCEPT
             732 JUMP_FORWARD             4 (to 742)

2585     >>  734 RERAISE                  0
         >>  736 COPY                     3
             738 POP_EXCEPT
             740 RERAISE                  1

2587     >>  742 LOAD_FAST                1 (attachments_bits)
             744 LOAD_METHOD              9 (append)
             766 LOAD_GLOBAL             13 (NULL + int)
             778 LOAD_DEREF              15 (bitset)
             780 PRECALL                  1
             784 CALL                     1
             794 PRECALL                  1
             798 CALL                     1
             808 POP_TOP

2588         810 LOAD_FAST                2 (replaced_prompts_out)
             812 LOAD_METHOD              9 (append)
             834 LOAD_FAST               10 (new_text)
             836 PRECALL                  1
             840 CALL                     1
             850 POP_TOP

2590         852 LOAD_FAST                3 (orders_by_prompt)
             854 LOAD_METHOD              9 (append)
             876 LOAD_GLOBAL             21 (NULL + list)
             888 LOAD_DEREF              14 (attached_order)
             890 PRECALL                  1
             894 CALL                     1
             904 PRECALL                  1
             908 CALL                     1
             918 POP_TOP

2591         920 LOAD_DEREF              20 (overflow)
             922 POP_JUMP_FORWARD_IF_FALSE    21 (to 966)

2592         924 LOAD_FAST                4 (overflow_prompts)
             926 LOAD_METHOD              9 (append)
             948 LOAD_FAST                7 (idx_prompt)
             950 PRECALL                  1
             954 CALL                     1
             964 POP_TOP
         >>  966 JUMP_BACKWARD          247 (to 474)

2594     >>  968 LOAD_FAST                1 (attachments_bits)
             970 LOAD_FAST                2 (replaced_prompts_out)
             972 LOAD_FAST                3 (orders_by_prompt)
             974 BUILD_TUPLE              3
             976 RETURN_VALUE
ExceptionTable:
  124 to 212 -> 308 [0]
  216 to 304 -> 308 [0]
  308 to 390 -> 398 [1] lasti
  396 to 396 -> 398 [1] lasti
  544 to 586 -> 590 [1]
  590 to 612 -> 620 [2] lasti
  618 to 618 -> 620 [2] lasti
  628 to 706 -> 710 [1]
  710 to 728 -> 736 [2] lasti
  734 to 734 -> 736 [2] lasti

Disassembly of <code object <listcomp> at 0x100bc3020, file "main_window_imagen.pyc", line 2515>:
2515           0 RESUME                   0
               2 BUILD_LIST               0
               4 LOAD_FAST                0 (.0)
         >>    6 FOR_ITER                 4 (to 16)
               8 STORE_FAST               1 (_)
              10 BUILD_LIST               0
              12 LIST_APPEND              2
              14 JUMP_BACKWARD            5 (to 6)
         >>   16 RETURN_VALUE

Disassembly of <code object <listcomp> at 0x100c04470, file "main_window_imagen.pyc", line 2518>:
2518           0 RESUME                   0
               2 BUILD_LIST               0
               4 LOAD_FAST                0 (.0)
         >>    6 FOR_ITER                36 (to 80)
               8 STORE_FAST               1 (it)
              10 LOAD_FAST                1 (it)
              12 LOAD_CONST               0 ('name')
              14 BINARY_SUBSCR
              24 POP_JUMP_BACKWARD_IF_FALSE    10 (to 6)
              26 LOAD_GLOBAL              1 (NULL + re)
              38 LOAD_ATTR                1 (escape)
              48 LOAD_FAST                1 (it)
              50 LOAD_CONST               0 ('name')
              52 BINARY_SUBSCR
              62 PRECALL                  1
              66 CALL                     1
              76 LIST_APPEND              2
              78 JUMP_BACKWARD           37 (to 6)
         >>   80 RETURN_VALUE

Disassembly of <code object <listcomp> at 0x100bc30f0, file "main_window_imagen.pyc", line 2520>:
2520           0 RESUME                   0
               2 BUILD_LIST               0
               4 LOAD_FAST                0 (.0)
         >>    6 FOR_ITER                 4 (to 16)
               8 STORE_FAST               1 (_)
              10 BUILD_LIST               0
              12 LIST_APPEND              2
              14 JUMP_BACKWARD            5 (to 6)
         >>   16 RETURN_VALUE

Disassembly of <code object <listcomp> at 0x100bc31c0, file "main_window_imagen.pyc", line 2523>:
2523           0 RESUME                   0
               2 BUILD_LIST               0
               4 LOAD_FAST                0 (.0)
         >>    6 FOR_ITER                 4 (to 16)
               8 STORE_FAST               1 (_)
              10 BUILD_LIST               0
              12 LIST_APPEND              2
              14 JUMP_BACKWARD            5 (to 6)
         >>   16 RETURN_VALUE

Disassembly of <code object find_index_for_name at 0x14d657e60, file "main_window_imagen.pyc", line 2526>:
               0 COPY_FREE_VARS           1

2526           2 RESUME                   0

2527           4 LOAD_FAST                0 (found)
               6 JUMP_IF_TRUE_OR_POP      1 (to 10)
               8 LOAD_CONST               1 ('')
         >>   10 LOAD_METHOD              0 (lower)
              32 PRECALL                  0
              36 CALL                     0
              46 STORE_FAST               1 (low)

2528          48 LOAD_DEREF               4 (name_map)
              50 GET_ITER
         >>   52 FOR_ITER                37 (to 128)
              54 STORE_FAST               2 (it)

2529          56 LOAD_FAST                2 (it)
              58 LOAD_CONST               2 ('name_lower')
              60 BINARY_SUBSCR
              70 LOAD_FAST                1 (low)
              72 COMPARE_OP               2 (==)
              78 POP_JUMP_FORWARD_IF_FALSE    23 (to 126)

2530          80 LOAD_GLOBAL              3 (NULL + int)
              92 LOAD_FAST                2 (it)
              94 LOAD_CONST               3 ('index')
              96 BINARY_SUBSCR
             106 PRECALL                  1
             110 CALL                     1
             120 SWAP                     2
             122 POP_TOP
             124 RETURN_VALUE

2529     >>  126 JUMP_BACKWARD           38 (to 52)

2532     >>  128 LOAD_CONST               4 (' ')
             130 LOAD_METHOD              2 (join)
             152 LOAD_FAST                1 (low)
             154 LOAD_METHOD              3 (split)
             176 PRECALL                  0
             180 CALL                     0
             190 PRECALL                  1
             194 CALL                     1
             204 STORE_FAST               3 (low_c)

2533         206 LOAD_DEREF               4 (name_map)
             208 GET_ITER
         >>  210 FOR_ITER                74 (to 360)
             212 STORE_FAST               2 (it)

2534         214 LOAD_CONST               4 (' ')
             216 LOAD_METHOD              2 (join)
             238 LOAD_FAST                2 (it)
             240 LOAD_CONST               2 ('name_lower')
             242 BINARY_SUBSCR
             252 LOAD_METHOD              3 (split)
             274 PRECALL                  0
             278 CALL                     0
             288 PRECALL                  1
             292 CALL                     1
             302 LOAD_FAST                3 (low_c)
             304 COMPARE_OP               2 (==)
             310 POP_JUMP_FORWARD_IF_FALSE    23 (to 358)

2535         312 LOAD_GLOBAL              3 (NULL + int)
             324 LOAD_FAST                2 (it)
             326 LOAD_CONST               3 ('index')
             328 BINARY_SUBSCR
             338 PRECALL                  1
             342 CALL                     1
             352 SWAP                     2
             354 POP_TOP
             356 RETURN_VALUE

2534     >>  358 JUMP_BACKWARD           75 (to 210)

2536     >>  360 LOAD_CONST               5 (-1)
             362 RETURN_VALUE

Disassembly of <code object repl at 0x14d658090, file "main_window_imagen.pyc", line 2545>:
               0 COPY_FREE_VARS           6

2545           2 RESUME                   0

2546           4 NOP

2547           6 LOAD_FAST                0 (m)
               8 LOAD_METHOD              0 (group)
              30 LOAD_CONST               1 (0)
              32 PRECALL                  1
              36 CALL                     1
              46 STORE_FAST               1 (found)

2548          48 PUSH_NULL
              50 LOAD_DEREF               7 (find_index_for_name)
              52 LOAD_FAST                1 (found)
              54 PRECALL                  1
              58 CALL                     1
              68 STORE_FAST               2 (idx_img)

2549          70 LOAD_FAST                2 (idx_img)
              72 LOAD_CONST               2 (-1)
              74 COMPARE_OP               2 (==)
              80 POP_JUMP_FORWARD_IF_FALSE     2 (to 86)

2550          82 LOAD_FAST                1 (found)
              84 RETURN_VALUE

2552     >>   86 LOAD_FAST                2 (idx_img)
              88 LOAD_DEREF               5 (attached_order)
              90 CONTAINS_OP              1
              92 POP_JUMP_FORWARD_IF_FALSE    23 (to 140)
              94 LOAD_GLOBAL              3 (NULL + len)
             106 LOAD_DEREF               5 (attached_order)
             108 PRECALL                  1
             112 CALL                     1
             122 LOAD_CONST               3 (10)
             124 COMPARE_OP               5 (>=)
             130 POP_JUMP_FORWARD_IF_FALSE     4 (to 140)

2555         132 LOAD_CONST               4 (True)
             134 STORE_DEREF             10 (overflow)

2556         136 LOAD_FAST                1 (found)
             138 RETURN_VALUE

2558     >>  140 LOAD_FAST                2 (idx_img)
             142 LOAD_DEREF               5 (attached_order)
             144 CONTAINS_OP              1
             146 POP_JUMP_FORWARD_IF_FALSE    21 (to 190)

2559         148 LOAD_DEREF               5 (attached_order)
             150 LOAD_METHOD              2 (append)
             172 LOAD_FAST                2 (idx_img)
             174 PRECALL                  1
             178 CALL                     1
             188 POP_TOP

2561     >>  190 LOAD_FAST                2 (idx_img)
             192 LOAD_DEREF               9 (local_ord_map)
             194 CONTAINS_OP              1
             196 POP_JUMP_FORWARD_IF_FALSE    18 (to 234)

2562         198 LOAD_GLOBAL              3 (NULL + len)
             210 LOAD_DEREF               5 (attached_order)
             212 PRECALL                  1
             216 CALL                     1
             226 LOAD_DEREF               9 (local_ord_map)
             228 LOAD_FAST                2 (idx_img)
             230 STORE_SUBSCR

2565     >>  234 LOAD_DEREF               6 (bitset)
             236 LOAD_CONST               5 (1)
             238 LOAD_FAST                2 (idx_img)
             240 LOAD_CONST               5 (1)
             242 BINARY_OP               10 (-)
             246 BINARY_OP                3 (<<)
             250 BINARY_OP               20 (|=)
             254 STORE_DEREF              6 (bitset)

2567         256 LOAD_DEREF               9 (local_ord_map)
             258 LOAD_METHOD              3 (get)
             280 LOAD_FAST                2 (idx_img)
             282 LOAD_CONST               5 (1)
             284 PRECALL                  2
             288 CALL                     2
             298 STORE_FAST               3 (local_no)

2568         300 LOAD_DEREF               8 (is_vn)
             302 POP_JUMP_FORWARD_IF_FALSE     5 (to 314)
             304 LOAD_CONST               6 ('nhân vật trong ảnh ')
             306 LOAD_FAST                3 (local_no)
             308 FORMAT_VALUE             0
             310 BUILD_STRING             2
             312 JUMP_FORWARD             4 (to 322)
         >>  314 LOAD_CONST               7 ('character in image ')
             316 LOAD_FAST                3 (local_no)
             318 FORMAT_VALUE             0
             320 BUILD_STRING             2
         >>  322 STORE_FAST               4 (phrase)

2569         324 LOAD_FAST                4 (phrase)
             326 RETURN_VALUE
         >>  328 PUSH_EXC_INFO

2570         330 LOAD_GLOBAL              8 (Exception)
             342 CHECK_EXC_MATCH
             344 POP_JUMP_FORWARD_IF_FALSE    24 (to 394)
             346 POP_TOP

2571         348 LOAD_FAST                0 (m)
             350 LOAD_METHOD              0 (group)
             372 LOAD_CONST               1 (0)
             374 PRECALL                  1
             378 CALL                     1
             388 SWAP                     2
             390 POP_EXCEPT
             392 RETURN_VALUE

2570     >>  394 RERAISE                  0
         >>  396 COPY                     3
             398 POP_EXCEPT
             400 RERAISE                  1
ExceptionTable:
  6 to 82 -> 328 [0]
  86 to 136 -> 328 [0]
  140 to 324 -> 328 [0]
  328 to 388 -> 396 [1] lasti
  394 to 394 -> 396 [1] lasti

Disassembly of <code object <genexpr> at 0x100c14120, file "main_window_imagen.pyc", line 2611>:
2611           0 RETURN_GENERATOR
               2 POP_TOP
               4 RESUME                   0
               6 LOAD_FAST                0 (.0)
         >>    8 FOR_ITER                21 (to 52)
              10 STORE_FAST               1 (slot)
              12 LOAD_GLOBAL              1 (NULL + getattr)
              24 LOAD_FAST                1 (slot)
              26 LOAD_CONST               0 ('image_path')
              28 LOAD_CONST               1 (None)
              30 PRECALL                  3
              34 CALL                     3
              44 YIELD_VALUE
              46 RESUME                   1
              48 POP_TOP
              50 JUMP_BACKWARD           22 (to 8)
         >>   52 LOAD_CONST               1 (None)
              54 RETURN_VALUE

Disassembly of <code object <genexpr> at 0x100c14210, file "main_window_imagen.pyc", line 2626>:
2626           0 RETURN_GENERATOR
               2 POP_TOP
               4 RESUME                   0
               6 LOAD_FAST                0 (.0)
         >>    8 FOR_ITER                19 (to 48)
              10 STORE_FAST               1 (x)
              12 LOAD_GLOBAL              1 (NULL + str)
              24 LOAD_FAST                1 (x)
              26 PRECALL                  1
              30 CALL                     1
              40 YIELD_VALUE
              42 RESUME                   1
              44 POP_TOP
              46 JUMP_BACKWARD           20 (to 8)
         >>   48 LOAD_CONST               0 (None)
              50 RETURN_VALUE

Disassembly of <code object <listcomp> at 0x100bcd330, file "main_window_imagen.pyc", line 2654>:
2654           0 RESUME                   0
               2 BUILD_LIST               0
               4 LOAD_FAST                0 (.0)
         >>    6 FOR_ITER                29 (to 66)
               8 UNPACK_SEQUENCE          2
              12 STORE_FAST               1 (i)
              14 STORE_FAST               2 (b)
              16 LOAD_GLOBAL              1 (NULL + int)
              28 LOAD_FAST                2 (b)
              30 PRECALL                  1
              34 CALL                     1
              44 LOAD_CONST               0 (0)
              46 COMPARE_OP               2 (==)
              52 POP_JUMP_BACKWARD_IF_FALSE    24 (to 6)
              54 LOAD_FAST                1 (i)
              56 LOAD_CONST               1 (1)
              58 BINARY_OP                0 (+)
              62 LIST_APPEND              2
              64 JUMP_BACKWARD           30 (to 6)
         >>   66 RETURN_VALUE

Disassembly of <code object <genexpr> at 0x100c143f0, file "main_window_imagen.pyc", line 2656>:
2656           0 RETURN_GENERATOR
               2 POP_TOP
               4 RESUME                   0
               6 LOAD_FAST                0 (.0)
         >>    8 FOR_ITER                19 (to 48)
              10 STORE_FAST               1 (x)
              12 LOAD_GLOBAL              1 (NULL + str)
              24 LOAD_FAST                1 (x)
              26 PRECALL                  1
              30 CALL                     1
              40 YIELD_VALUE
              42 RESUME                   1
              44 POP_TOP
              46 JUMP_BACKWARD           20 (to 8)
         >>   48 LOAD_CONST               0 (None)
              50 RETURN_VALUE

Disassembly of <code object <listcomp> at 0x100affb90, file "main_window_imagen.pyc", line 2667>:
2667           0 RESUME                   0
               2 BUILD_LIST               0
               4 LOAD_FAST                0 (.0)
         >>    6 FOR_ITER                49 (to 106)
               8 STORE_FAST               1 (it)
              10 LOAD_FAST                1 (it)
              12 LOAD_METHOD              0 (get)
              34 LOAD_CONST               0 ('name')
              36 PRECALL                  1
              40 CALL                     1
              50 POP_JUMP_BACKWARD_IF_FALSE    23 (to 6)
              52 LOAD_GLOBAL              3 (NULL + re)
              64 LOAD_ATTR                2 (escape)
              74 LOAD_FAST                1 (it)
              76 LOAD_CONST               0 ('name')
              78 BINARY_SUBSCR
              88 PRECALL                  1
              92 CALL                     1
             102 LIST_APPEND              2
             104 JUMP_BACKWARD           50 (to 6)
         >>  106 RETURN_VALUE

Disassembly of <code object <genexpr> at 0x100c144e0, file "main_window_imagen.pyc", line 2680>:
2680           0 RETURN_GENERATOR
               2 POP_TOP
               4 RESUME                   0
               6 LOAD_FAST                0 (.0)
         >>    8 FOR_ITER                19 (to 48)
              10 STORE_FAST               1 (x)
              12 LOAD_GLOBAL              1 (NULL + str)
              24 LOAD_FAST                1 (x)
              26 PRECALL                  1
              30 CALL                     1
              40 YIELD_VALUE
              42 RESUME                   1
              44 POP_TOP
              46 JUMP_BACKWARD           20 (to 8)
         >>   48 LOAD_CONST               0 (None)
              50 RETURN_VALUE

Disassembly of <code object _count_bits at 0x100c04580, file "main_window_imagen.pyc", line 2706>:
2706           0 RESUME                   0

2707           2 LOAD_CONST               1 (0)
               4 STORE_FAST               1 (c)

2708           6 LOAD_GLOBAL              1 (NULL + int)
              18 LOAD_FAST                0 (x)
              20 PRECALL                  1
              24 CALL                     1
              34 STORE_FAST               2 (v)

2709          36 LOAD_FAST                2 (v)
              38 POP_JUMP_FORWARD_IF_FALSE    15 (to 70)

2710     >>   40 LOAD_FAST                2 (v)
              42 LOAD_FAST                2 (v)
              44 LOAD_CONST               2 (1)
              46 BINARY_OP               10 (-)
              50 BINARY_OP               14 (&=)
              54 STORE_FAST               2 (v)

2711          56 LOAD_FAST                1 (c)
              58 LOAD_CONST               2 (1)
              60 BINARY_OP               13 (+=)
              64 STORE_FAST               1 (c)

2709          66 LOAD_FAST                2 (v)
              68 POP_JUMP_BACKWARD_IF_TRUE    15 (to 40)

2712     >>   70 LOAD_FAST                1 (c)
              72 RETURN_VALUE

Disassembly of <code object <genexpr> at 0x100c145d0, file "main_window_imagen.pyc", line 2719>:
2719           0 RETURN_GENERATOR
               2 POP_TOP
               4 RESUME                   0
               6 LOAD_FAST                0 (.0)
         >>    8 FOR_ITER                19 (to 48)
              10 STORE_FAST               1 (x)
              12 LOAD_GLOBAL              1 (NULL + str)
              24 LOAD_FAST                1 (x)
              26 PRECALL                  1
              30 CALL                     1
              40 YIELD_VALUE
              42 RESUME                   1
              44 POP_TOP
              46 JUMP_BACKWARD           20 (to 8)
         >>   48 LOAD_CONST               0 (None)
              50 RETURN_VALUE

Disassembly of <code object _bits_to_indices at 0x100b625b0, file "main_window_imagen.pyc", line 2811>:
2811           0 RESUME                   0

2812           2 BUILD_LIST               0
               4 STORE_FAST               2 (out)

2813           6 LOAD_GLOBAL              1 (NULL + range)
              18 LOAD_FAST                1 (max_slots)
              20 PRECALL                  1
              24 CALL                     1
              34 GET_ITER
         >>   36 FOR_ITER                47 (to 132)
              38 STORE_FAST               3 (i)

2814          40 LOAD_GLOBAL              3 (NULL + int)
              52 LOAD_FAST                0 (bits)
              54 PRECALL                  1
              58 CALL                     1
              68 LOAD_CONST               1 (1)
              70 LOAD_FAST                3 (i)
              72 BINARY_OP                3 (<<)
              76 BINARY_OP                1 (&)
              80 POP_JUMP_FORWARD_IF_FALSE    24 (to 130)

2815          82 LOAD_FAST                2 (out)
              84 LOAD_METHOD              2 (append)
             106 LOAD_FAST                3 (i)
             108 LOAD_CONST               1 (1)
             110 BINARY_OP                0 (+)
             114 PRECALL                  1
             118 CALL                     1
             128 POP_TOP
         >>  130 JUMP_BACKWARD           48 (to 36)

2816     >>  132 LOAD_FAST                2 (out)
             134 RETURN_VALUE
